Workbook

Sheet Start Here
B1: 💎 DFS Card Grader — Business Operations Kit
B2: A complete operating system for running a profitable sports card business
B4: 👋 WELCOME
B5: Whether you're just starting out or scaling an existing card business, this workbook gives you the same tools and systems used by serious collectors and resellers.
B6: It works hand-in-hand with the DFS Card Grader app — use the app to research cards and make grading decisions, then use this workbook to plan, track, and grow your business.
B7: Every tab has a job. Work through the Getting Started checklist below, fill in your numbers, and the workbook will start giving you real answers about your business.
B9: 🎯 STEP 1 — SET YOUR MONTHLY REVENUE GOAL
B10: ▸ What is your monthly revenue goal? | C10: Go to the Path to $40k tab → enter your target in the yellow input cell. The model will calculate how many cards you need to sell per day, at what average price, to hit it.
B11: ▸ What is your average card value? | C11: Look at your last 10–20 sales. What did they sell for on average? Enter this in the Path to $40k assumptions. Lower avg price = more volume needed.
B12: ▸ What margin are you targeting?
B13: ▸ How much capital do you have to work with? | C13: Enter your starting capital in the Capital Velocity tab. It will show you how many times you need to flip that capital per month to hit your revenue goal.
B15: 📦 STEP 2 — KNOW YOUR INVENTORY
B16: ▸ Log every card you own | C16: Use the Inventory & Aging tab. Enter the card, what you paid (cost basis), where it's listed, and the asking price. This is your business balance sheet.
B17: ▸ Watch the aging flags | C17: Any card listed 30+ days with no sale is a problem. The Inventory & Aging tab flags these automatically. Use the Stale Action Plan tab to decide what to do — drop price, relist, or consign.
B18: ▸ Know what's costing you money
B19: ▸ Build your buy list | C19: The Target Card List tab is where you track what to buy next. Set a Max Buy price and a Target Sell price before you buy anything — never buy without a plan.
B21: 💎 STEP 3 — USE GRADING AS A REVENUE LEVER
B22: ▸ Not every card is worth grading | C22: Only grade cards where: (1) the gem rate is 40%+, and (2) a PSA 10 sells for at least 4× your raw cost after fees. Use the Grading ROI Calculator tab to run the numbers before you submit anything.
B23: ▸ Search first in the app | C23: Open the DFS Card Grader app → search the card → get the gem rate from GemRate.com → enter the PSA 10 market value → the app tells you GO or NO-GO instantly.
B24: ▸ Log every submission | C24: Use the Grading Tracker tab to log every card you send to PSA — tier, fee, expected price, and target. When grades come back, update the actual results to track your real grading ROI over time.
B25: ▸ Build a grading pipeline
B27: 💰 STEP 4 — SELL SMARTER ACROSS CHANNELS
B28: ▸ Not all channels are equal | C28: eBay, HeyStack, COMC, Whatnot, and consignment houses all have different fees and buyer pools. The Channel Fees tab shows your net payout at each price point so you route the right card to the right platform.
B29: ▸ Log every sale immediately | C29: Use the Sales Log tab. Date, card, channel, sell price, fees, and net. This is your income statement. Review it weekly — your data will show you which channels and card types make you the most money.
B30: ▸ Use consignment for high-value cards | C30: Cards over $100–200 often do better at auction houses like DcSports87, PWCC, or Probstein. Track every consignment in the Consignment Tracker tab — submission date, estimated value, and when to expect payment.
B31: ▸ HeyStack priority scoring
B33: ✅ GETTING STARTED CHECKLIST
B34: ☐ | C34: Set your monthly revenue goal in the Path to $40k tab
B35: ☐ | C35: Enter your starting capital in the Capital Velocity tab
B36: ☐
B37: ☐ | C37: Build your buy list in the Target Card List tab
B38: ☐ | C38: Review the Channel Fees tab and understand your platform costs
B39: ☐ | C39: Search your first card in the DFS Card Grader app and get a GO/NO-GO
B40: ☐ | C40: Add your first grading candidate to the Grading Candidates tab
B41: ☐ | C41: Log your next sale in the Sales Log the day it sells
B42: ☐ | C42: Check Inventory & Aging weekly — flag anything listed 30+ days
B43: ☐
B45: 📑 TAB DIRECTORY
B46: 💎 GRADING TOOLS
B47: ➤ PSA Fee Schedule | C47: All 7 PSA tiers — fees, turnaround times, and eBay cost breakdown
B48: ➤ Grading ROI Calculator | C48: Input any card → get instant GO/NO-GO with target price and net profit
B49: ➤ Grading Tracker | C49: Log every PSA submission — track status, grade returned, and actual ROI
B50: ➤ Grading Candidates | C50: Build your next grading batch — shortlist cards before committing
B52: 📋 OPERATIONS
B53: ➤ Dashboard | C53: 60-second weekly check-in — revenue, margin, and volume at a glance
B54: ➤ Target Card List | C54: Your buy list — max buy price and target sell for every card you want
B55: ➤ Inventory Intel | C55: Deep snapshot of your full inventory — composition, value, and insights
B56: ➤ Stale Action Plan | C56: 90-day aged cards — specific recommended actions for each one
B57: ➤ 14-Day Volume Ramp | C57: Day-by-day sales velocity plan for when you need to move volume fast
B58: ➤ Sales Log | C58: Every completed sale — date, price, channel, fees, and net margin
B59: ➤ Consignment Tracker | C59: Track every card at auction houses — status, expected payout, close date
B61: 📦 INVENTORY
B62: ➤ Inventory & Aging | C62: Full inventory with cost basis, days listed, aging flags, and next action
B63: ➤ Lot Evaluator | C63: Pre-buy tool — enter comp total + target margin → get max offer price
B64: ➤ DcSports87 May 2026 | C64: Top scored cards for current DcSports87 consignment auction
B65: ➤ DcSports87 — Normal Batch | C65: Standard DcSports87 batch — $3–$25 range, scored by auction potential
B67: 🏈⚾🏀 HEYSTACK PRIORITY
B68: ➤ FB Cards — HeyStack Priority | C68: Football cards ranked by sell-through score for HeyStack relisting
B69: ➤ BB Cards — HeyStack Priority | C69: Baseball cards ranked by sell-through score for HeyStack relisting
B70: ➤ BK Cards — HeyStack Priority | C70: Basketball cards ranked by sell-through score for HeyStack relisting
B71: ➤ Stale Action — Market Comps | C71: Live eBay comp research for aging cards — drop, hold, or consign
B73: 💰 FINANCIAL MODELS
B74: ➤ Channel Fees | C74: Live fee comparison — eBay vs HeyStack vs COMC vs consignment at every price point
B75: ➤ Capital Velocity | C75: How fast is your money working? Tracks flip cycles and net profit per dollar deployed
B76: ➤ Helper ROI | C76: Thinking about hiring help? This model tells you exactly when it makes financial sense
B77: ➤ Path to $40k | C77: Monthly revenue projection — enter your goal and work backwards to daily targets
B79: © 2025 DFS Cards LLC · 8601 E Palo Verde Dr, Scottsdale AZ 85250 · All rights reserved

Sheet Dashboard
A1: 🏠 Start Here
A2: Your weekly 60-second check-in. Numbers pull from the other tabs.
A4: HEADLINE NUMBERS (from live data)
B5: Direct Sales Gross | D5: Direct Sales Net | F5: Consignment Net | H5: Total Net (all channels)
B6: ='Sales Log'!F3 -> 128 | D6: ='Sales Log'!J3 -> 44.78 | F6: ='Consignment Tracker'!I3 -> 0 | H6: ='Sales Log'!J3+'Consignment Tracker'!I3 -> 44.78
B8: Direct Margin % | D8: Avg Net / Consigned Card | F8: Stale Cards (≥60d) | H8: Capital at Risk (stale)
B9: =IFERROR('Sales Log'!J3/'Sales Log'!F3,"") -> 0.34984375 | D9: =IFERROR('Consignment Tracker'!I3/'Consignment Tracker'!C3,"") | F9: ='Inventory & Aging'!E3 -> 0 | H9: ='Inventory & Aging'!G3 -> 0
A12: PROGRESS vs TARGETS
B13: Monthly Net Target (current phase) | E13: 8000
B14: Actual Monthly Net (YTD-indicative) | E14: ='Sales Log'!J3+'Consignment Tracker'!I3 -> 44.78
B15: % of Phase Target | E15: =IFERROR(C14/C13,"")
A18: QUICK ACTIONS
B19: → Sales Log: log any sales since last week.
B20: → Consignment Tracker: update any auctions that closed.
B21: → Inventory & Aging: route all STALE-flagged cards to next consignment batch.
B22: → Path to $40k: compare actual net vs this month's milestone.
B23: → Helper ROI: if you haven't hired yet, re-run the calculator — it is the fastest win.

Sheet Target Card List
A1: 🏠 Start Here
A2: 25 NFL + 20 Soccer + 20 Baseball (liquid ≥10 sales/90d) — $8-155 band. WC 2026 LIVE in 6 weeks. 2025 MLB season catalyst active.
E3: TOTALS → | F3: =SUM(F5:F55) -> 73 | G3: =SUM(G5:G55) -> 180 | H3: =SUM(H5:H55) -> 281.4 | I3: =SUM(I5:I55) -> -174.4 | L3: =IFERROR(I3/G3,"") -> -0.96888889
A4: # | B4: Sport | C4: Player | D4: Card / Variant | E4: Grade / Cond. | F4: Max Buy ($) | G4: Target Sell ($) | H4: Est. Fees ($) | I4: Est. Net ($) | J4: Catalyst / Why | K4: Best Channel | L4: Margin % | M4: In Stock | N4: Your Avg $ | O4: Status
A5: 1 | B5: NFL | C5: Patrick Mahomes | D5: 2017 Panini Prizm #269 RC Silver | E5: Raw NM-M | F5: 35 | G5: 80 | H5: =G5*0.1325 -> 10.6 | I5: =G5-H5-F5 -> 34.4 | J5: SB contender, top QB | K5: eBay BIN | L5: =IFERROR(I5/G5,"") -> 0.43
A6: 2 | B6: NFL | C6: Ja'Marr Chase | D6: 2021 Panini Prizm #387 RC Silver | E6: Raw NM-M | F6: 20 | G6: 55 | H6: =G6*0.1325 -> 7.2875 | I6: =G6-H6-F6 -> 27.7125 | J6: WR1 threat | K6: eBay BIN | L6: =IFERROR(I6/G6,"") -> 0.50386364
A7: 3 | B7: MLB | C7: Juan Soto | D7: 2018 Topps Chrome #31 RC | E7: Raw NM-M | F7: 18 | G7: 45 | H7: =G7*0.1325 -> 5.9625 | I7: =G7-H7-F7 -> 21.0375 | J7: 2025 season catalyst | K7: eBay Auction | L7: =IFERROR(I7/G7,"") -> 0.4675
H8: =G8*0.136+0.4+4.5+0.75 -> 5.65 | I8: =G8-F8-H8 -> -5.65 | L8: =IFERROR(I8/G8,"")
H9: =G9*0.1+0+4.5+0.75 -> 5.25 | I9: =G9-F9-H9 -> -5.25 | L9: =IFERROR(I9/G9,"")
H10: =G10*0.136+0.4+4.5+0.75 -> 5.65 | I10: =G10-F10-H10 -> -5.65 | L10: =IFERROR(I10/G10,"")
H11: =G11*0.136+0.4+4.5+0.75 -> 5.65 | I11: =G11-F11-H11 -> -5.65 | L11: =IFERROR(I11/G11,"")
H12: =G12*0.136+0.4+4.5+0.75 -> 5.65 | I12: =G12-F12-H12 -> -5.65 | L12: =IFERROR(I12/G12,"")
H13: =G13*0.1+0+4.5+0.75 -> 5.25 | I13: =G13-F13-H13 -> -5.25 | L13: =IFERROR(I13/G13,"")
H14: =G14*0.136+0.4+4.5+0.75 -> 5.65 | I14: =G14-F14-H14 -> -5.65 | L14: =IFERROR(I14/G14,"")
H15: =G15*0.136+0.4+4.5+0.75 -> 5.65 | I15: =G15-F15-H15 -> -5.65 | L15: =IFERROR(I15/G15,"")
H16: =G16*0.136+0.4+4.5+0.75 -> 5.65 | I16: =G16-F16-H16 -> -5.65 | L16: =IFERROR(I16/G16,"")
H17: =G17*0.1+0+4.5+0.75 -> 5.25 | I17: =G17-F17-H17 -> -5.25 | L17: =IFERROR(I17/G17,"")
H18: =G18*0.1+0+4.5+0.75 -> 5.25 | I18: =G18-F18-H18 -> -5.25 | L18: =IFERROR(I18/G18,"")
H19: =G19*0.136+0.4+4.5+0.75 -> 5.65 | I19: =G19-F19-H19 -> -5.65 | L19: =IFERROR(I19/G19,"")
H20: =G20*0.1+0+4.5+0.75 -> 5.25 | I20: =G20-F20-H20 -> -5.25 | L20: =IFERROR(I20/G20,"")
H21: =G21*0.1+0+4.5+0.75 -> 5.25 | I21: =G21-F21-H21 -> -5.25 | L21: =IFERROR(I21/G21,"")
H22: =G22*0.1+0+4.5+0.75 -> 5.25 | I22: =G22-F22-H22 -> -5.25 | L22: =IFERROR(I22/G22,"")
H23: =G23*0.068+0.4+4.5+0.75 -> 5.65 | I23: =G23-F23-H23 -> -5.65 | L23: =IFERROR(I23/G23,"")
H24: =G24*0.136+0.4+4.5+0.75 -> 5.65 | I24: =G24-F24-H24 -> -5.65 | L24: =IFERROR(I24/G24,"")
H25: =G25*0.136+0.4+4.5+0.75 -> 5.65 | I25: =G25-F25-H25 -> -5.65 | L25: =IFERROR(I25/G25,"")
H26: =G26*0.068+0.4+4.5+0.75 -> 5.65 | I26: =G26-F26-H26 -> -5.65 | L26: =IFERROR(I26/G26,"")
H27: =G27*0.1+0+4.5+0.75 -> 5.25 | I27: =G27-F27-H27 -> -5.25 | L27: =IFERROR(I27/G27,"")
H28: =G28*0.136+0.4+4.5+0.75 -> 5.65 | I28: =G28-F28-H28 -> -5.65 | L28: =IFERROR(I28/G28,"")
H29: =G29*0.1+0+4.5+0.75 -> 5.25 | I29: =G29-F29-H29 -> -5.25 | L29: =IFERROR(I29/G29,"")
H30: =G30*0.136+0.4+4.5+0.75 -> 5.65 | I30: =G30-F30-H30 -> -5.65 | L30: =IFERROR(I30/G30,"")
H31: =G31*0.136+0.4+4.5+0.75 -> 5.65 | I31: =G31-F31-H31 -> -5.65 | L31: =IFERROR(I31/G31,"")
H32: =G32*0.136+0.4+4.5+0.75 -> 5.65 | I32: =G32-F32-H32 -> -5.65 | L32: =IFERROR(I32/G32,"")
H33: =G33*0.1+0+4.5+0.75 -> 5.25 | I33: =G33-F33-H33 -> -5.25 | L33: =IFERROR(I33/G33,"")
H34: =G34*0.136+0.4+4.5+0.75 -> 5.65 | I34: =G34-F34-H34 -> -5.65 | L34: =IFERROR(I34/G34,"")
H35: =G35*0.136+0.4+4.5+0.75 -> 5.65 | I35: =G35-F35-H35 -> -5.65 | L35: =IFERROR(I35/G35,"")
H36: =G36*0.136+0.4+4.5+0.75 -> 5.65 | I36: =G36-F36-H36 -> -5.65 | L36: =IFERROR(I36/G36,"")
H37: =G37*0.1+0+4.5+0.75 -> 5.25 | I37: =G37-F37-H37 -> -5.25 | L37: =IFERROR(I37/G37,"")
H38: =G38*0.136+0.4+4.5+0.75 -> 5.65 | I38: =G38-F38-H38 -> -5.65 | L38: =IFERROR(I38/G38,"")
H39: =G39*0.1+0+4.5+0.75 -> 5.25 | I39: =G39-F39-H39 -> -5.25 | L39: =IFERROR(I39/G39,"")
H40: =G40*0.136+0.4+4.5+0.75 -> 5.65 | I40: =G40-F40-H40 -> -5.65 | L40: =IFERROR(I40/G40,"")
H41: =G41*0.1+0+4.5+0.75 -> 5.25 | I41: =G41-F41-H41 -> -5.25 | L41: =IFERROR(I41/G41,"")
H42: =G42*0.1+0+4.5+0.75 -> 5.25 | I42: =G42-F42-H42 -> -5.25 | L42: =IFERROR(I42/G42,"")
H43: =G43*0.1+0+4.5+0.75 -> 5.25 | I43: =G43-F43-H43 -> -5.25 | L43: =IFERROR(I43/G43,"")
H44: =G44*0.1+0+4.5+0.75 -> 5.25 | I44: =G44-F44-H44 -> -5.25 | L44: =IFERROR(I44/G44,"")
H45: =G45*0.1+0+4.5+0.75 -> 5.25 | I45: =G45-F45-H45 -> -5.25 | L45: =IFERROR(I45/G45,"")
H46: =G46*0.1+0+4.5+0.75 -> 5.25 | I46: =G46-F46-H46 -> -5.25 | L46: =IFERROR(I46/G46,"")
H47: =G47*0.1+0+4.5+0.75 -> 5.25 | I47: =G47-F47-H47 -> -5.25 | L47: =IFERROR(I47/G47,"")
H48: =G48*0.136+0.4+4.5+0.75 -> 5.65 | I48: =G48-F48-H48 -> -5.65 | L48: =IFERROR(I48/G48,"")
H49: =G49*0.136+0.4+4.5+0.75 -> 5.65 | I49: =G49-F49-H49 -> -5.65 | L49: =IFERROR(I49/G49,"")
H50: =G50*0.136+0.4+4.5+0.75 -> 5.65 | I50: =G50-F50-H50 -> -5.65 | L50: =IFERROR(I50/G50,"")
H51: =G51*0.1+0+4.5+0.75 -> 5.25 | I51: =G51-F51-H51 -> -5.25 | L51: =IFERROR(I51/G51,"")
H53: =G53*0.136+0.4+4.5+0.75 -> 5.65 | I53: =G53-F53-H53 -> -5.65 | L53: =IFERROR(I53/G53,"")
H54: =G54*0.136+0.4+4.5+0.75 -> 5.65 | I54: =G54-F54-H54 -> -5.65 | L54: =IFERROR(I54/G54,"")
H55: =G55*0.136+0.4+4.5+0.75 -> 5.65 | I55: =G55-F55-H55 -> -5.65 | L55: =IFERROR(I55/G55,"")
H56: =G56*0.136+0.4+4.5+0.75 -> 5.65 | I56: =G56-F56-H56 -> -5.65 | L56: =IFERROR(I56/G56,"")
H57: =G57*0.136+0.4+4.5+0.75 -> 5.65 | I57: =G57-F57-H57 -> -5.65 | L57: =IFERROR(I57/G57,"")
H58: =G58*0.136+0.4+4.5+0.75 -> 5.65 | I58: =G58-F58-H58 -> -5.65 | L58: =IFERROR(I58/G58,"")
H59: =G59*0.1+0+4.5+0.75 -> 5.25 | I59: =G59-F59-H59 -> -5.25 | L59: =IFERROR(I59/G59,"")
H60: =G60*0.136+0.4+4.5+0.75 -> 5.65 | I60: =G60-F60-H60 -> -5.65 | L60: =IFERROR(I60/G60,"")
H61: =G61*0.136+0.4+4.5+0.75 -> 5.65 | I61: =G61-F61-H61 -> -5.65 | L61: =IFERROR(I61/G61,"")
H62: =G62*0.136+0.4+4.5+0.75 -> 5.65 | I62: =G62-F62-H62 -> -5.65 | L62: =IFERROR(I62/G62,"")
H63: =G63*0.136+0.4+4.5+0.75 -> 5.65 | I63: =G63-F63-H63 -> -5.65 | L63: =IFERROR(I63/G63,"")
H64: =G64*0.136+0.4+4.5+0.75 -> 5.65 | I64: =G64-F64-H64 -> -5.65 | L64: =IFERROR(I64/G64,"")
H65: =G65*0.1+0+4.5+0.75 -> 5.25 | I65: =G65-F65-H65 -> -5.25 | L65: =IFERROR(I65/G65,"")
H66: =G66*0.1+0+4.5+0.75 -> 5.25 | I66: =G66-F66-H66 -> -5.25 | L66: =IFERROR(I66/G66,"")
H67: =G67*0.136+0.4+4.5+0.75 -> 5.65 | I67: =G67-F67-H67 -> -5.65 | L67: =IFERROR(I67/G67,"")
H68: =G68*0.1+0+4.5+0.75 -> 5.25 | I68: =G68-F68-H68 -> -5.25 | L68: =IFERROR(I68/G68,"")
H69: =G69*0.136+0.4+4.5+0.75 -> 5.65 | I69: =G69-F69-H69 -> -5.65 | L69: =IFERROR(I69/G69,"")
H70: =G70*0.136+0.4+4.5+0.75 -> 5.65 | I70: =G70-F70-H70 -> -5.65 | L70: =IFERROR(I70/G70,"")
H71: =G71*0.136+0.4+4.5+0.75 -> 5.65 | I71: =G71-F71-H71 -> -5.65 | L71: =IFERROR(I71/G71,"")
H72: =G72*0.1+0+4.5+0.75 -> 5.25 | I72: =G72-F72-H72 -> -5.25 | L72: =IFERROR(I72/G72,"")

Sheet Inventory Intel
A1: 🏠 Start Here
A2: Based on your 4/20/26 active listings export — 4,233 items, 430 orders last 90d
A4: 1. INVENTORY PRICE COMPOSITION
A5: Price Bucket | B5: # Listings | C5: % of Total | D5: Category
A6: <$2 | B6: 2251 | C6: 0.53177416 | D6: LOW-END (sub-$5)
A7: $2-5 | B7: 1511 | C7: 0.35695724 | D7: LOW-END (sub-$5)
A8: $5-10 | B8: 263 | C8: 0.062130876 | D8: VOLUME TIER
A9: $10-20 | B9: 126 | C9: 0.029766123 | D9: VOLUME TIER
A10: $20-50 | B10: 55 | C10: 0.012993149 | D10: MID-TIER (sweet spot)
A11: $50-100 | B11: 14 | C11: 0.003307347 | D11: MID-TIER (sweet spot)
A12: >=$100 | B12: 13 | C12: 0.003071108 | D12: PREMIUM
A13: ⚠ KEY FINDING: 89% of your listings are under $5. Your mid-tier ($20-100) sweet spot is only 1.6% — this is the #1 reason you're capped at $3-8k/mo NET.
A15: 2. LAST 90 DAYS — SALES PROFILE
A16: Orders (90d) | B16: 430
A17: Total GMV | B17: 7029.83
A18: Avg sale price | B18: 16.348442
A19: Avg orders/day | B19: 4.7777778
A20: Monthly GMV run-rate | B20: 2343.2767
A21: Implied NET @ 30% margin | B21: 702.983
A23: 3. TARGET-LIST PLAYERS WITH SALES (last 90d)
A24: Player | B24: # Sold | C24: Avg $ | D24: Total $
A25: Messi | B25: 2 | C25: 24 | D25: 48
A26: Drake Maye | B26: 5 | C26: 9.034 | D26: 45.17
A27: Bo Nix | B27: 1 | C27: 41 | D27: 41
A28: Lamine Yamal | B28: 2 | C28: 15.995 | D28: 31.99
A29: Haaland | B29: 1 | C29: 9.08 | D29: 9.08
A30: Caleb Williams | B30: 1 | C30: 2.25 | D30: 2.25
A32: 4. YOUR TOP 10 SALES (last 90d) — WHAT'S ACTUALLY MOVING
A33: Sold For | B33: Title
A34: 600 | B34: 2025-26 Topps Chrome Kon Knueppel #254 (RC) Purple RayWave Hornets /75
A35: 425 | B35: Cooper Flagg 2025-26 Topps Chrome RC Silver X-Fractor Refractor #251
A36: 305 | B36: 2025-26 Topps Cooper Flagg #201 Gold Dallas Mavericks #/2025 (RC) 🔥🔥🔥
A37: 222 | B37: 2025-26 Topps Kon Knueppel #NA-KK New Applicants Autographs Hornets (AU), (RC)
A38: 185 | B38: 2025 Topps Update Chrome #98 Paul Skenes Gold Cup Gold Refractor 16/50
A39: 135 | B39: 2024 Topps Aaron Judge #HL-3 Heavy Lumber Yankees MVP
A40: 130 | B40: 2024 Bowman Draft Konnor Griffin #BDC-22 1st Refractor RC Pirates Top Prospect
A41: 122.5 | B41: 1909-11 T206 Sweet Caporal 350/30 Chief Bender #PR Pitching, Trees In Back
A42: 120 | B42: 2024 Bowman Draft Konnor Griffin #BDC-22 Chrome Refractor Pittsburgh Pirates
A43: 117.5 | B43: 2024 Pokemon Japanese Sv8a-Terastal Fest Ex #206 Glaceon Ex Sp Art Rare PSA 10
A45: 5. DATA-DRIVEN RECOMMENDATIONS
A46: Coverage gap | B46: 43/45 target cards have ZERO stock — these are your buy list this week.
A47: Mix shift | B47: Only 69 of 4,233 listings are in the $20-100 mid-tier. Shifting even 200 units from sub-$5 to mid-tier = +$6k-12k revenue potential.
A48: NBA signal | B48: Top 3 sales in 90d were NBA rookies (Flagg $305+$425, Knueppel $600+$222). Consider adding NBA mid-tier parallels to target list.
A49: Repricing | B49: Status column flags cards listed >40% under target sell — those are likely base versions, not the parallel the target expects. Audit + pull low-quality listings.
A50: Current run-rate | B50: You're at ~4.8 orders/day at $16.35 avg = ~$2343/mo GMV. Net ~30% = ~$703/mo. Ramp to 50 sold/day × $20 avg = ~$30000/mo GMV for the 14-day plan to deliver.

Sheet Stale Action Plan
A1: 🏠 Start Here
A2: Stale = 0 watchers, 0 bids, listed 30+ days ago. Based on 4,252 active listings.
A4: 1. STALE INVENTORY OVERVIEW
A5: Total active listings | E5: 4252
A6: Stale listings (30+ days, no interest) | E6: 3541
A7: Stale % of inventory | E7: 0.83278457
A8: Capital tied in stale listings | E8: 9758.39
A9: Stale with demand (reprice) | E9: 53
A10: Stale with no demand (consign/bulk) | E10: 3488
A11: Stale premium $20+ 60d+ | E11: 17
A12: Premium stale capital | E12: 508.72
A14: ⚠ 83% of your inventory is stale. $9,758 of working capital is locked up. The 3 plays below free it back into your turn.
A16: 2. STALE AGE BREAKDOWN
A17: Age Bucket | B17: # Stale | C17: Action
A18: 30-60 days | B18: 461 | C18: Reprice to market avg, add keyword tags
A19: 60-90 days | B19: 188 | C19: Audit photos/description, drop 10% or route to consign
A20: 90-180 days | B20: 782 | C20: Consign to DcSports87 or bundle as lots
A21: 180-365 days | B21: 2110 | C21: Bulk lot on Whatnot or consign — stop paying insertion fees
A22: 1+ year | B22: 0 | C22: Delist or bulk lot — zero chance at sticker price
A24: 3. TOP 30 REPRICE CANDIDATES — stale but same card sold in last 90d
A25: 💡 These cards sat with zero interest, BUT identical cards sold recently. Green = list above market (reprice DOWN). Red = list below market (reprice UP). Aim for 95-100% of sold avg.
A26: Days | B26: Your Ask | C26: Sold Avg | D26: Max Sale | E26: Δ% | F26: Qty | G26: Title | H26: New Price Target
A27: 43 | B27: 26 | C27: 5.66 | D27: 11 | E27: 3.5936396 | F27: 1 | G27: 2025 Bowman Draft Ethan Frey #BDC-67 Chrome Purple Refractor Astros #/250 | H27: 5.377
A28: 75 | B28: 13 | C28: 8.18 | D28: 8.18 | E28: 0.58924205 | F28: 1 | G28: 2024 Donruss Optic Drake Maye #229 New England Patriots RC | H28: 7.771
A29: 37 | B29: 13 | C29: 3.5 | D29: 3.5 | E29: 2.7142857 | F29: 1 | G29: 2025-26 Finest Allen Iverson #M-1 Muse Sky Blue Refractor 76ers #/150 | H29: 3.325
A30: 49 | B30: 12 | C30: 8.75 | D30: 11 | E30: 0.37142857 | F30: 1 | G30: 2025 Bowman Draft Eli Willits #BDC-1 Chrome Refractor Washington Nationals | H30: 8.3125
A31: 37 | B31: 10 | C31: 1 | D31: 1 | E31: 9 | F31: 1 | G31: 2025-26 Topps Chrome Noa Essengue #262 Negative Refractor Chicago Bulls | H31: 0.95
A32: 52 | B32: 7.55 | C32: 2.245 | D32: 2.5 | E32: 2.363029 | F32: 1 | G32: 2025 Bowman Draft Ryan Mitchell #BDC-77 Chrome Sky Blue Refractor Cardinals | H32: 2.13275
A33: 152 | B33: 6 | C33: 1.25 | D33: 1.25 | E33: 3.8 | F33: 1 | G33: 2025 Panini Prizm FIFA Club World Cup Ian Subiabre #176 River Plate | H33: 1.1875
A34: 50 | B34: 5.99 | C34: 25.75 | D34: 40 | E34: -0.76737864 | F34: 1 | G34: 2025 Bowman Draft Liam Doyle #BDC-12 Chrome Refractor St. Louis Cardinals | H34: 27.0375
A35: 51 | B35: 5.95 | C35: 3.99 | D35: 3.99 | E35: 0.49122807 | F35: 1 | G35: 2025 Bowman Draft Justin Lamkin #BDC-62 Chrome Sparkle Refractor Royals | H35: 3.7905
A36: 100 | B36: 4.99 | C36: 8.2966667 | D36: 20 | E36: -0.39855364 | F36: 1 | G36: 2025-26 Topps Chrome VJ Edgecombe #253 Philadelphia 76ers | H36: 8.7115
A37: 54 | B37: 1.59 | C37: 1.99 | D37: 1.99 | E37: -0.20100503 | F37: 3 | G37: 2025-26 Topps Chrome Ryan Kalkbrenner #284 Charlotte Hornets | H37: 2.0895
A38: 55 | B38: 3.99 | C38: 5.66 | D38: 11 | E38: -0.295053 | F38: 1 | G38: 2025 Bowman Draft Ethan Frey #BDC-67 Chrome Refractor Houston Astros | H38: 5.943
... A56: 98 | B56: 1.99 | C56: 1.99 | D56: 1.99 | E56: 0 | F56: 1 | G56: 2024 Bowman University Chrome Luther Burden III #55B-1 Tigers | H56: 2.0895
A58: 4. STALE DUPLICATES — bulk lot or consign (3+ copies, no recent sale)
A59: These are accumulating with no demand. Bundle in lots of 25-50 on Whatnot or route to DcSports87 — stop paying insertion fees to re-list monthly.
A60: Count | B60: Ask Each | C60: Total Value | D60: Card
A61: 17 | B61: 2.32 | C61: 40.55 | D61: 2018-19 Topps Match Attax UEFA Champions League Filipe Luís #22 Atletico Madrid | H61: Bundle as lot
A62: 7 | B62: 1.49 | C62: 11.93 | D62: 2024-25 Topps Finest Uefa Club Competitions - Joao Simoes #83 Refractor (RC) | H62: Bundle as lot
A63: 6 | B63: 1.99 | C63: 11.94 | D63: 2024 Panini Prizm Draft Picks Tristan da Silva #61 Prizms Green Buffaloes | H63: Bundle as lot
A64: 4 | B64: 6.69 | C64: 12.68 | D64: 2025 Panini Stars and Stripes USA Baseball Andres Armenta #158 Green | H64: Consign
A65: 4 | B65: 4.99 | C65: 10.56 | D65: 2024 Panini Prizm Draft Picks Matas Buzelis #67b Purple Wave NBA G League Ignite | H65: Consign
A66: 4 | B66: 2.99 | C66: 9.16 | D66: 2024 Panini Prizm Draft Picks Alexandre Sarr #52b Tampa Yankees | H66: Consign
A67: 4 | B67: 1.99 | C67: 7.66 | D67: 2024 Panini Prizm Draft Picks Yves Missi #54b Prizms Green Baylor Bears | H67: Consign
A68: 4 | B68: 1.99 | C68: 5.96 | D68: 2024 Panini Prizm Draft Picks Zaccharie Risacher #69 Prizms Orange Ice | H68: Consign
A69: 4 | B69: 1.5 | C69: 13.46 | D69: 2025-26 Topps Chrome Sion James #283 Charlotte Hornets | H69: Consign
A70: 4 | B70: 2.5 | C70: 6.24 | D70: 2025-26 Topps Chrome Walter Clayton Jr. #268 Refractor Utah Jazz | H70: Consign
A71: 3 | B71: 2.99 | C71: 7.44 | D71: 2024-25 Panini Select Premier League - Terrace Dara O'Shea #19 Red cracked Ice | H71: Consign
A72: 3 | B72: 4.49 | C72: 12.27 | D72: 2024 Topps Chrome Jasson Domínguez #89 Sepia Refractors New York Yankees | H72: Consign
... A79: 3 | B79: 1.5 | C79: 7.3 | D79: 2025 Bowman Draft Walker Janek #BDC-45 Chrome Houston Astros | H79: Consign
A81: 5. PREMIUM STALE ($20+, 60d+) — consignment candidates
A82: No sales in last 90d at your ask. Route to DcSports87 weekly batch — you'll get 60-75% net of true auction market vs zero at current prices.
A83: Days | B83: Your Ask | C83: Recent Sold Avg | D83: Title
A84: 279 | B84: 50 | C84: - | D84: 2021 Leaf Young Stars ANSU FATI Soccer FC Barcelona Spain Autograph Auto | H84: Consign to DcSports87
A85: 119 | B85: 43 | C85: - | D85: 2024 Bowman Chrome Jose Perdomo #BMA-JP Auto Green Mojo Refractors Braves /99 | H85: Consign to DcSports87
A86: 235 | B86: 38 | C86: - | D86: 2025 Panini National Silver Packs Hailey Van Lith RC Rookie # /399 SKY SHARP | H86: Consign to DcSports87
A87: 310 | B87: 35 | C87: - | D87: 2023 Topps Chrome Logofractor Edition #1 Juan Soto Yellow #/75 PSA Mets | H87: Consign to DcSports87
A88: 118 | B88: 30 | C88: - | D88: 2025 Panini The Ohio State University NIL Julian Sayin College Ticket Foil #2 | H88: Consign to DcSports87
A89: 207 | B89: 29.99 | C89: - | D89: 2025 Panini National Convention Gold Pack VIP David Beckham #60 England | H89: Consign to DcSports87
A90: 190 | B90: 29 | C90: - | D90: 2022-23 Topps NBL Ariel Hukporti #41 Gold Melbourne United #/50 | H90: Consign to DcSports87
A91: 182 | B91: 25 | C91: - | D91: 2024-25 Panini Obsidian Julian Strawther #MM-JSD Matrix Material (AU) #/99 | H91: Consign to DcSports87
A92: 179 | B92: 25 | C92: - | D92: 2025-26 Topps Scottie Barnes #SA-28 Stars of the NBA /99 Raptors | H92: Consign to DcSports87
A93: 167 | B93: 25 | C93: - | D93: 2024 Bowman Shohei Ohtani #33 GEM MINT Los Angeles Dodgers | H93: Consign to DcSports87
A94: 124 | B94: 25 | C94: - | D94: 2025 Panini National Convention Hailey Van Lith #RC5 Rookie Cards /399 | H94: Consign to DcSports87
A95: 276 | B95: 24.95 | C95: - | D95: 2024 Donruss Optic Rated Rookie DALLAS TURNER Negative Auto /325 #224 Vikings RC | H95: Reprice -20% or consign
... A100: 179 | B100: 20 | C100: - | D100: 2025-26 Topps Oso Ighodaro #ME-OI Marks of Excellence Phoenix Suns Auto | H100: Reprice -20% or consign
A102: 6. THE THREE-PLAY CHECKLIST — free $5k+ of capital in 14 days
A103: PLAY 1: REPRICE BATCH
A104: Today (2 hrs) | C104: Work the 30 reprice candidates above. Use the 'New Price Target' column. Cards listed 20%+ ABOVE sold avg come DOWN to 95% of avg. Cards listed BELOW avg go UP. Expected: 30-40% of these move within 14 days → $150-400 cash freed + rotation.
A106: PLAY 2: CONSIGNMENT BATCH
A107: This Friday | C107: Send all 17 premium stale ($20+, 60+ days, 0 interest) to DcSports87 as your biggest weekly batch yet. That's ~$509 in cards sitting dead. Even at 60% auction net you clear ~$305 — beats indefinite zero. Add 20-30 mid-tier ($10-20) stale for volume.
A109: PLAY 3: BULK LOTS
A110: Next 2 weeks | C110: The 3,488 stale-no-demand cards are insertion-fee leakage. Bundle top-20 duplicate categories into 50-card themed lots (soccer commons, NBA rookies, MLB prospects). List at $15-25/lot on eBay or pitch to Whatnot bulk buyers. 2,000+ cards move at ~$0.50/card = $1,000 cash freed + inventory cleanup.

Sheet 14-Day Volume Ramp
A1: 🏠 Start Here
A2: Tactical day-by-day plan. Volume comes from listing throughput + pricing discipline + Whatnot pushes.
A4: THE MATH — what has to happen
B5: Metric | C5: Current | D5: Week 1 Target | E5: Week 2 Target | F5: End-State
B6: Cards listed / day | C6: 50 | D6: 70 (+helper) | E6: 90-100 | F6: 100
B7: 30-day sell-through rate | C7: 60% | D7: 65% | E7: 68% | F7: 70%
B8: Cards sold / day (implied) | C8: 30 | D8: 40 | E8: 55 | F8: 65+
B9: Pricing discipline (% of median) | C9: 92% | D9: 90% | E9: 88% | F9: 88%
B10: Whatnot auction streams / week | C10: 0 | D10: 1 (50-80 cards) | E10: 2 (100+ cards) | F10: 2-3
B11: eBay 7-day auction listings / wk | C11: 0 | D11: 30 (aged inv.) | E11: 50+ | F11: 50+
A15: DAY-BY-DAY TACTICAL PLAN
B17: Day | C17: Focus | D17: Tactical Actions | E17: List Target | F17: Sold Target | G17: Whatnot? | H17: Price Rule | I17: Notes
B18: 1 (Mon) | C18: Helper onboarding | D18: Hire helper (10 hrs/wk). Write photo SOP. You list 50, helper observes + lists 10 trial. | E18: 60 | F18: 30 | G18: No | H18: 92% median
B19: 2 (Tue) | C19: Helper solo listing | D19: Helper lists 25 (QA every one). You list 50 + 30 Whatnot auction prep. | E19: 75 | F19: 35 | G19: Prep | H19: 92%
B20: 3 (Wed) | C20: Whatnot stream #1 | D20: Helper lists 30. You prep Whatnot (50 cards). 7-10pm live stream — clear aged inventory. | E20: 80 | F20: 45 | G20: YES | H20: Auction
B21: 4 (Thu) | C21: Recovery + list | D21: Helper lists 35. You list 45 + ship from Whatnot stream. | E21: 80 | F21: 40 | G21: No | H21: 92%
B22: 5 (Fri) | C22: eBay 7-day auctions | D22: Helper lists 40. You post 30 eBay auctions of aged 30+ day inventory at $0.99 start. | E22: 70 | F22: 42 | G22: No | H22: Auction
B23: 6 (Sat) | C23: Source day | D23: Helper off. You list 25 AM then hunt FB/eBay lots 3 hrs (use Lot Evaluator). List buys same day. | E23: 50 | F23: 40 | G23: No | H23: 90%
B24: 7 (Sun) | C24: Whatnot stream #2 | D24: You prep 60 cards. 6-9pm Whatnot stream — mix mid-tier + bulk. | E24: 60 | F24: 55 | G24: YES | H24: Auction
B25: 8 (Mon) | C25: Price cuts + re-list | D25: Helper 40. You re-price everything listed 30+ days: drop to 88%. List 40 new. | E25: 80 | F25: 45 | G25: No | H25: 88% on aged
B26: 9 (Tue) | C26: Helper at full speed | D26: Helper lists 50 (SOP dialed). You list 40. Total output: 90/day. | E26: 90 | F26: 50 | G26: No | H26: 88%
B27: 10 (Wed) | C27: Whatnot + aged cleanup | D27: Helper lists 45. You prep Whatnot (80 cards) — push aged + new. 7-10pm stream. | E27: 80 | F27: 60 | G27: YES | H27: Auction
B28: 11 (Thu) | C28: Consignment batch | D28: Helper lists 45. You pack 40 cards to DcSports87 + 30 to Probstein. List 35. | E28: 80 | F28: 50 | G28: No | H28: 88%
B29: 12 (Fri) | C29: eBay auctions + FB lot push | D29: Helper lists 50. You list 35 + post FB Marketplace bulk lot. Daily shipping. | E29: 85 | F29: 50 | G29: No | H29: 88%
... B31: 14 (Sun) | C31: Whatnot stream #3 + review | D31: Prep 100-card stream. 6-10pm. Post-stream: review KPIs, set Week 3 targets. | E31: 100 | F31: 65 | G31: YES | H31: Auction
B32: 14-DAY TOTAL | E32: =SUM(E18:E31) -> 1060 | F32: =SUM(F18:F31) -> 652
A35: THE FIVE LEVERS — ranked by impact
B37: 1. Helper hire (Day 1)
B38: Moves listing capacity from 50 → 90+/day. Single biggest unlock. $600/mo cost for ~$9k revenue add.
B39: 2. Whatnot weekly streams
B40: One 2-3 hour stream moves 50-100 cards. Live price discovery + impulse buying. 3 streams in 14 days = 300+ cards sold.
B41: 3. Pricing discipline
B42: Drop from 92% to 88% of median comp on aged inventory. Accelerates 30-day sell-through by 5-8 pts. Worth more than you think.
B43: 4. eBay 7-day auctions
B44: Auction-format listings with $0.99 start clear aged inventory hard. Run 30-50 aged cards per week as auctions.
B45: 5. Consignment batching
B46: Day 11 send 70 cards out to DcSports87 + Probstein. Frees capital + moves volume while your hands do other things.
A49: REALITY CAVEAT
A50: Hitting 50 sold/day is aggressive from 30/day baseline. Day-by-day targets assume helper hire happens Day 1, Whatnot streams execute on schedule, and pricing discipline is enforced. Realistic completion rate is 80-90% of this plan. If you hit 42-45 sold/day by Day 14, you're still massively ahead of where you started — adjust expectations accordingly.

Sheet Sales Log
A1: 🏠 Start Here
A2: Every direct-sale transaction. Enter new rows at the bottom.
A3: TOTALS → | E3: =SUM(E5:E734) -> 55 | F3: =SUM(F5:F734) -> 128 | G3: =SUM(G5:G734) -> 16.97 | H3: =SUM(H5:H734) -> 9 | I3: =SUM(I5:I734) -> 2.25 | J3: =SUM(J5:J734) -> 44.78 | K3: =IFERROR(J3/F3,"") -> 0.34984375
A4: Sale Date | B4: Channel | C4: Card Description | D4: Category | E4: Cost Basis ($) | F4: Sell Price ($) | G4: Fees ($) | H4: Shipping Cost ($) | I4: Supplies ($) | J4: Net ($) | K4: Margin % | L4: Days Held
A5: 46037 | B5: eBay | C5: 2024 Panini Prizm Patrick Mahomes RC Base #168 | D5: Football | E5: 18 | F5: 42 | G5: 5.57 | H5: 4.5 | I5: 0.75 | J5: =IFERROR(F5-E5-G5-H5-I5,"") -> 13.18 | K5: =IFERROR(J5/F5,"") -> 0.31380952
A6: 46054 | B6: eBay | C6: 2023 Topps Chrome Corbin Carroll RC #150 | D6: Baseball | E6: 12 | F6: 28 | G6: 3.71 | H6: 4.5 | I6: 0.75 | J6: =IFERROR(F6-E6-G6-H6-I6,"") -> 7.04 | K6: =IFERROR(J6/F6,"") -> 0.25142857
A7: 46091 | B7: Whatnot | C7: 2021 Panini Prizm LeBron James #129 Silver | D7: Basketball | E7: 25 | F7: 58 | G7: 7.69 | H7: 0 | I7: 0.75 | J7: =IFERROR(F7-E7-G7-H7-I7,"") -> 24.56 | K7: =IFERROR(J7/F7,"") -> 0.42344828
J8: =IFERROR(F8-E8-G8-H8-I8,"") -> 0 | K8: =IFERROR(J8/F8,"")
J9: =IFERROR(F9-E9-G9-H9-I9,"") -> 0 | K9: =IFERROR(J9/F9,"")
J10: =IFERROR(F10-E10-G10-H10-I10,"") -> 0 | K10: =IFERROR(J10/F10,"")
J11: =IFERROR(F11-E11-G11-H11-I11,"") -> 0 | K11: =IFERROR(J11/F11,"")
J12: =IFERROR(F12-E12-G12-H12-I12,"") -> 0 | K12: =IFERROR(J12/F12,"")
J13: =IFERROR(F13-E13-G13-H13-I13,"") -> 0 | K13: =IFERROR(J13/F13,"")
J14: =IFERROR(F14-E14-G14-H14-I14,"") -> 0 | K14: =IFERROR(J14/F14,"")
J15: =IFERROR(F15-E15-G15-H15-I15,"") -> 0 | K15: =IFERROR(J15/F15,"")
J16: =IFERROR(F16-E16-G16-H16-I16,"") -> 0 | K16: =IFERROR(J16/F16,"")
J17: =IFERROR(F17-E17-G17-H17-I17,"") -> 0 | K17: =IFERROR(J17/F17,"")
J18: =IFERROR(F18-E18-G18-H18-I18,"") -> 0 | K18: =IFERROR(J18/F18,"")
J19: =IFERROR(F19-E19-G19-H19-I19,"") -> 0 | K19: =IFERROR(J19/F19,"")
... J714: =IFERROR(F714-E714-G714-H714-I714,"") -> 0 | K714: =IFERROR(J714/F714,"")

Sheet Consignment Tracker
A1: 🏠 Start Here
A2: DcSports87, Probstein, PWCC, MyBrick submissions and net payouts.
A3: TOTALS → | C3: =SUM(C5:C104) -> 0 | G3: =SUM(G5:G104) -> 0 | H3: =SUM(H5:H104) -> 0 | I3: =SUM(I5:I104) -> 0 | J3: =IFERROR(I3/C3,"")
A4: Submission Date | B4: House | C4: # Cards | D4: Your Est. Value ($) | E4: Card Type Focus | F4: Auction Close Date | G4: Gross Proceeds ($) | H4: House Fees ($) | I4: Net Received ($) | J4: Net / Card ($)
I5: =IFERROR(G5-H5,"") -> 0 | J5: =IFERROR(I5/C5,"")
I6: =IFERROR(G6-H6,"") -> 0 | J6: =IFERROR(I6/C6,"")
I7: =IFERROR(G7-H7,"") -> 0 | J7: =IFERROR(I7/C7,"")
I8: =IFERROR(G8-H8,"") -> 0 | J8: =IFERROR(I8/C8,"")
I9: =IFERROR(G9-H9,"") -> 0 | J9: =IFERROR(I9/C9,"")
I10: =IFERROR(G10-H10,"") -> 0 | J10: =IFERROR(I10/C10,"")
I11: =IFERROR(G11-H11,"") -> 0 | J11: =IFERROR(I11/C11,"")
I12: =IFERROR(G12-H12,"") -> 0 | J12: =IFERROR(I12/C12,"")
I13: =IFERROR(G13-H13,"") -> 0 | J13: =IFERROR(I13/C13,"")
I14: =IFERROR(G14-H14,"") -> 0 | J14: =IFERROR(I14/C14,"")
I15: =IFERROR(G15-H15,"") -> 0 | J15: =IFERROR(I15/C15,"")
I16: =IFERROR(G16-H16,"") -> 0 | J16: =IFERROR(I16/C16,"")
... I104: =IFERROR(G104-H104,"") -> 0 | J104: =IFERROR(I104/C104,"")
B110: =COUNTIF(B5:B104,A110) -> 0 | C110: =SUMIF(B5:B104,A110,C5:C104) -> 0 | D110: =SUMIF(B5:B104,A110,I5:I104) -> 0 | E110: =IFERROR(D110/C110,"")
B111: =COUNTIF(B5:B104,A111) -> 0 | C111: =SUMIF(B5:B104,A111,C5:C104) -> 0 | D111: =SUMIF(B5:B104,A111,I5:I104) -> 0 | E111: =IFERROR(D111/C111,"")
B112: =COUNTIF(B5:B104,A112) -> 0 | C112: =SUMIF(B5:B104,A112,C5:C104) -> 0 | D112: =SUMIF(B5:B104,A112,I5:I104) -> 0 | E112: =IFERROR(D112/C112,"")
B113: =COUNTIF(B5:B104,A113) -> 0 | C113: =SUMIF(B5:B104,A113,C5:C104) -> 0 | D113: =SUMIF(B5:B104,A113,I5:I104) -> 0 | E113: =IFERROR(D113/C113,"")
B114: =COUNTIF(B5:B104,A114) -> 0 | C114: =SUMIF(B5:B104,A114,C5:C104) -> 0 | D114: =SUMIF(B5:B104,A114,I5:I104) -> 0 | E114: =IFERROR(D114/C114,"")

Sheet DcSports87 May 2026
A1: 🏠 Start Here
A2: Generated: May 03, 2026 | Top 20 by score, all listed > $25 | Est. Total Value: $2,040.17
A4: # | B4: Card Description | C4: Category | D4: Listed Price ($) | E4: Score | F4: Watchers | G4: Market Verdict | H4: DcSports87 Notes
D26: =SUM(D5:D24) -> 0

Sheet DcSports87 — Normal Batch
A1: 🏠 Start Here
A2: 75 cards | $3–$25 range | Total listed value: $829.38 | Avg: $11.06/card | All modern (no vintage) | Sorted by auction potential score (highest first)
A3: SCORE = Auto +8 | RC/1st +3 | Chrome/Prizm +2 | Print run (/25=+6, /99=+4, /199=+3, /499=+2, higher=+1) | Patch/Swatch +3 | Jersey/Relic +2 | Price tier ($3-8=+1, $8-15=+2, $15-25=+3) | Watchers = +N each
A5: # | B5: Card Description | C5: Category | D5: Listed ($) | E5: Score | F5: Score Breakdown | G5: Watchers | H5: SKU
D82: =SUM(D6:D80) -> 0 | E82: =AVERAGE(E6:E80) -> #DIV/0!

Sheet Inventory & Aging
A1: 🏠 Start Here
B2: Track every card you own: when you bought it, when you listed it, and how long it's been sitting. Aging is based on Listed Date — the 60-day clock starts when it goes live.
A3: SUMMARY → | B3: Active listings: | C3: =COUNTIF(H5:H504,"Listed") -> 0 | D3: Stale (≥60d): | E3: =COUNTIF(J5:J504,"STALE — route now") -> 0 | F3: Capital at risk ($): | G3: =SUMIFS(F5:F504,J5:J504,"STALE — route now") -> 0 | H3: Avg days listed: | I3: =IFERROR(AVERAGEIF(H5:H504,"Listed",I5:I504),"—") -> —
A4: Acquired | B4: Listed Date | C4: Source | D4: Card Description | E4: Category | F4: Cost Basis ($) | G4: Listed Price ($) | H4: Status | I4: Days Listed | J4: Aging Flag | K4: Next Action
I9: =IF(OR(B9="",H9="Sold"),"—",TODAY()-B9) -> — | J9: =IF(OR(B9="",H9="Sold"),"",IF(I9="—","",IF(I9>=60,"STALE — route now",IF(I9>=30,"Aging — watch",IF(I9>=0,"Fresh",""))))) | K9: =IF(J9="STALE — route now","→ Send to consignment batch",IF(J9="Aging — watch","→ Consider 10% price drop",IF(J9="Fresh","→ Hold & monitor","")))
I11: =IF(OR(B11="",H11="Sold"),"—",TODAY()-B11) -> — | J11: =IF(OR(B11="",H11="Sold"),"",IF(I11="—","",IF(I11>=60,"STALE — route now",IF(I11>=30,"Aging — watch",IF(I11>=0,"Fresh",""))))) | K11: =IF(J11="STALE — route now","→ Send to consignment batch",IF(J11="Aging — watch","→ Consider 10% price drop",IF(J11="Fresh","→ Hold & monitor","")))
I12: =IF(OR(B12="",H12="Sold"),"—",TODAY()-B12) -> — | J12: =IF(OR(B12="",H12="Sold"),"",IF(I12="—","",IF(I12>=60,"STALE — route now",IF(I12>=30,"Aging — watch",IF(I12>=0,"Fresh",""))))) | K12: =IF(J12="STALE — route now","→ Send to consignment batch",IF(J12="Aging — watch","→ Consider 10% price drop",IF(J12="Fresh","→ Hold & monitor","")))
I13: =IF(OR(B13="",H13="Sold"),"—",TODAY()-B13) -> — | J13: =IF(OR(B13="",H13="Sold"),"",IF(I13="—","",IF(I13>=60,"STALE — route now",IF(I13>=30,"Aging — watch",IF(I13>=0,"Fresh",""))))) | K13: =IF(J13="STALE — route now","→ Send to consignment batch",IF(J13="Aging — watch","→ Consider 10% price drop",IF(J13="Fresh","→ Hold & monitor","")))
I14: =IF(OR(B14="",H14="Sold"),"—",TODAY()-B14) -> — | J14: =IF(OR(B14="",H14="Sold"),"",IF(I14="—","",IF(I14>=60,"STALE — route now",IF(I14>=30,"Aging — watch",IF(I14>=0,"Fresh",""))))) | K14: =IF(J14="STALE — route now","→ Send to consignment batch",IF(J14="Aging — watch","→ Consider 10% price drop",IF(J14="Fresh","→ Hold & monitor","")))
I15: =IF(OR(B15="",H15="Sold"),"—",TODAY()-B15) -> — | J15: =IF(OR(B15="",H15="Sold"),"",IF(I15="—","",IF(I15>=60,"STALE — route now",IF(I15>=30,"Aging — watch",IF(I15>=0,"Fresh",""))))) | K15: =IF(J15="STALE — route now","→ Send to consignment batch",IF(J15="Aging — watch","→ Consider 10% price drop",IF(J15="Fresh","→ Hold & monitor","")))
I16: =IF(OR(B16="",H16="Sold"),"—",TODAY()-B16) -> — | J16: =IF(OR(B16="",H16="Sold"),"",IF(I16="—","",IF(I16>=60,"STALE — route now",IF(I16>=30,"Aging — watch",IF(I16>=0,"Fresh",""))))) | K16: =IF(J16="STALE — route now","→ Send to consignment batch",IF(J16="Aging — watch","→ Consider 10% price drop",IF(J16="Fresh","→ Hold & monitor","")))
I17: =IF(OR(B17="",H17="Sold"),"—",TODAY()-B17) -> — | J17: =IF(OR(B17="",H17="Sold"),"",IF(I17="—","",IF(I17>=60,"STALE — route now",IF(I17>=30,"Aging — watch",IF(I17>=0,"Fresh",""))))) | K17: =IF(J17="STALE — route now","→ Send to consignment batch",IF(J17="Aging — watch","→ Consider 10% price drop",IF(J17="Fresh","→ Hold & monitor","")))
I18: =IF(OR(B18="",H18="Sold"),"—",TODAY()-B18) -> — | J18: =IF(OR(B18="",H18="Sold"),"",IF(I18="—","",IF(I18>=60,"STALE — route now",IF(I18>=30,"Aging — watch",IF(I18>=0,"Fresh",""))))) | K18: =IF(J18="STALE — route now","→ Send to consignment batch",IF(J18="Aging — watch","→ Consider 10% price drop",IF(J18="Fresh","→ Hold & monitor","")))
I19: =IF(OR(B19="",H19="Sold"),"—",TODAY()-B19) -> — | J19: =IF(OR(B19="",H19="Sold"),"",IF(I19="—","",IF(I19>=60,"STALE — route now",IF(I19>=30,"Aging — watch",IF(I19>=0,"Fresh",""))))) | K19: =IF(J19="STALE — route now","→ Send to consignment batch",IF(J19="Aging — watch","→ Consider 10% price drop",IF(J19="Fresh","→ Hold & monitor","")))
I20: =IF(OR(B20="",H20="Sold"),"—",TODAY()-B20) -> — | J20: =IF(OR(B20="",H20="Sold"),"",IF(I20="—","",IF(I20>=60,"STALE — route now",IF(I20>=30,"Aging — watch",IF(I20>=0,"Fresh",""))))) | K20: =IF(J20="STALE — route now","→ Send to consignment batch",IF(J20="Aging — watch","→ Consider 10% price drop",IF(J20="Fresh","→ Hold & monitor","")))
I21: =IF(OR(B21="",H21="Sold"),"—",TODAY()-B21) -> — | J21: =IF(OR(B21="",H21="Sold"),"",IF(I21="—","",IF(I21>=60,"STALE — route now",IF(I21>=30,"Aging — watch",IF(I21>=0,"Fresh",""))))) | K21: =IF(J21="STALE — route now","→ Send to consignment batch",IF(J21="Aging — watch","→ Consider 10% price drop",IF(J21="Fresh","→ Hold & monitor","")))
... I504: =IF(OR(B504="",H504="Sold"),"—",TODAY()-B504) -> — | J504: =IF(OR(B504="",H504="Sold"),"",IF(I504="—","",IF(I504>=60,"STALE — route now",IF(I504>=30,"Aging — watch",IF(I504>=0,"Fresh",""))))) | K504: =IF(J504="STALE — route now","→ Send to consignment batch",IF(J504="Aging — watch","→ Consider 10% price drop",IF(J504="Fresh","→ Hold & monitor","")))

Sheet Reprice Queue
A1: 🏠 Start Here
A2: Reprice Queue — which listings to price-check today. Paste your eBay active-listings export into the grey columns (A–E). The queue flags itself by tier. Tiers 2 & 3 qualify instantly from the export; Tier 1 needs the app's CardHedger velocity pull.
A3: SUMMARY → | B3: Total listings: | C3: =COUNTA($B$5:$B$4600) -> 4480 | D3: In queue: | E3: =COUNTIF($H$5:$H$4600,"TIER*") -> 16 | F3: Needs API check: | G3: =COUNTIF($J$5:$J$4600,"YES*") -> 64 | H3: ="T1 "&COUNTIF($H$5:$H$4600,"TIER 1")&" | T2 "&COUNTIF($H$5:$H$4600,"TIER 2")&" | T3 "&COUNTIF($H$5:$H$4600,"TIER 3") -> T1 0 | T2 14 | T3 2
A4: Item # | B4: Title | C4: SKU / Custom Label | D4: Current Price ($) | E4: Daily Sales (mkt/day) | F4: Graded? | G4: PSA Grade | H4: QUALIFIES (Tier) | I4: Reason / Action | J4: Needs velocity pull?
A5: 226788716936 | B5: 2025 Bowman - Bowman Scouts Top 100 Marcelo Mayer #BTP-4 (RC) | C5: CDP-388FFD0 | D5: 1.49 | F5: =IF($B5="","",IF(ISNUMBER(SEARCH("PSA",$B5)),"Yes","No")) -> No | G5: =IF($B5="","",IF(ISNUMBER(SEARCH("PSA 10",$B5)),10,IF(ISNUMBER(SEARCH("PSA 9.5",$B5)),9.5,IF(ISNUMBER(SEARCH("PSA 9",$B5)),9,IF(ISNUMBER(SEARCH("PSA 8",$B5)),8,IF(ISNUMBER(SEARCH("PSA",$B5)),"<9","")))))) | H5: =IF($B5="","",IF($D5>=100,"TIER 2",IF(OR(ISNUMBER(SEARCH("PSA 10",$B5)),ISNUMBER(SEARCH("PSA 9.5",$B5)),ISNUMBER(SEARCH("PSA 9",$B5))),"TIER 3",IF(AND($D5>20,N($E5)>=15),"TIER 1","—")))) -> — | I5: =IF($B5="","",IF($D5>=100,"Premium $100+ (auto)",IF(OR(ISNUMBER(SEARCH("PSA 10",$B5)),ISNUMBER(SEARCH("PSA 9.5",$B5)),ISNUMBER(SEARCH("PSA 9",$B5))),"Graded PSA 9+ (auto)",IF(AND($D5>20,N($E5)>=15),"Hot: $20+ & "&$E5&"/day",IF($D5>20,"$20+ — needs velocity check","Below thresholds"))))) -> Below thresholds | J5: =IF($B5="","",IF(AND($D5>20,$D5<100,NOT(OR(ISNUMBER(SEARCH("PSA 10",$B5)),ISNUMBER(SEARCH("PSA 9.5",$B5)),ISNUMBER(SEARCH("PSA 9",$B5)))),$E5=""),"YES — pull CardHedger",""))
A6: 226788720400 | B6: 2024 Panini Absolute - Star Gazing Luke McCaffrey #SG-LMY (RC) | C6: CDP-B6E7E18 | D6: 0.99 | F6: =IF($B6="","",IF(ISNUMBER(SEARCH("PSA",$B6)),"Yes","No")) -> No | G6: =IF($B6="","",IF(ISNUMBER(SEARCH("PSA 10",$B6)),10,IF(ISNUMBER(SEARCH("PSA 9.5",$B6)),9.5,IF(ISNUMBER(SEARCH("PSA 9",$B6)),9,IF(ISNUMBER(SEARCH("PSA 8",$B6)),8,IF(ISNUMBER(SEARCH("PSA",$B6)),"<9","")))))) | H6: =IF($B6="","",IF($D6>=100,"TIER 2",IF(OR(ISNUMBER(SEARCH("PSA 10",$B6)),ISNUMBER(SEARCH("PSA 9.5",$B6)),ISNUMBER(SEARCH("PSA 9",$B6))),"TIER 3",IF(AND($D6>20,N($E6)>=15),"TIER 1","—")))) -> — | I6: =IF($B6="","",IF($D6>=100,"Premium $100+ (auto)",IF(OR(ISNUMBER(SEARCH("PSA 10",$B6)),ISNUMBER(SEARCH("PSA 9.5",$B6)),ISNUMBER(SEARCH("PSA 9",$B6))),"Graded PSA 9+ (auto)",IF(AND($D6>20,N($E6)>=15),"Hot: $20+ & "&$E6&"/day",IF($D6>20,"$20+ — needs velocity check","Below thresholds"))))) -> Below thresholds | J6: =IF($B6="","",IF(AND($D6>20,$D6<100,NOT(OR(ISNUMBER(SEARCH("PSA 10",$B6)),ISNUMBER(SEARCH("PSA 9.5",$B6)),ISNUMBER(SEARCH("PSA 9",$B6)))),$E6=""),"YES — pull CardHedger",""))
A7: 226788721897 | B7: 2024 Panini Illusions J.J. McCarthy #100 (RC) Vikings | C7: CDP-5D82D06 | D7: 1.49 | F7: =IF($B7="","",IF(ISNUMBER(SEARCH("PSA",$B7)),"Yes","No")) -> No | G7: =IF($B7="","",IF(ISNUMBER(SEARCH("PSA 10",$B7)),10,IF(ISNUMBER(SEARCH("PSA 9.5",$B7)),9.5,IF(ISNUMBER(SEARCH("PSA 9",$B7)),9,IF(ISNUMBER(SEARCH("PSA 8",$B7)),8,IF(ISNUMBER(SEARCH("PSA",$B7)),"<9","")))))) | H7: =IF($B7="","",IF($D7>=100,"TIER 2",IF(OR(ISNUMBER(SEARCH("PSA 10",$B7)),ISNUMBER(SEARCH("PSA 9.5",$B7)),ISNUMBER(SEARCH("PSA 9",$B7))),"TIER 3",IF(AND($D7>20,N($E7)>=15),"TIER 1","—")))) -> — | I7: =IF($B7="","",IF($D7>=100,"Premium $100+ (auto)",IF(OR(ISNUMBER(SEARCH("PSA 10",$B7)),ISNUMBER(SEARCH("PSA 9.5",$B7)),ISNUMBER(SEARCH("PSA 9",$B7))),"Graded PSA 9+ (auto)",IF(AND($D7>20,N($E7)>=15),"Hot: $20+ & "&$E7&"/day",IF($D7>20,"$20+ — needs velocity check","Below thresholds"))))) -> Below thresholds | J7: =IF($B7="","",IF(AND($D7>20,$D7<100,NOT(OR(ISNUMBER(SEARCH("PSA 10",$B7)),ISNUMBER(SEARCH("PSA 9.5",$B7)),ISNUMBER(SEARCH("PSA 9",$B7)))),$E7=""),"YES — pull CardHedger",""))
A8: 226788723318 | B8: 2025 Bowman Chrome Rece Hinds #RR-8 (RC) Rockstar Rookies | C8: CDP-B676C2C | D8: 1.5 | F8: =IF($B8="","",IF(ISNUMBER(SEARCH("PSA",$B8)),"Yes","No")) -> No | G8: =IF($B8="","",IF(ISNUMBER(SEARCH("PSA 10",$B8)),10,IF(ISNUMBER(SEARCH("PSA 9.5",$B8)),9.5,IF(ISNUMBER(SEARCH("PSA 9",$B8)),9,IF(ISNUMBER(SEARCH("PSA 8",$B8)),8,IF(ISNUMBER(SEARCH("PSA",$B8)),"<9","")))))) | H8: =IF($B8="","",IF($D8>=100,"TIER 2",IF(OR(ISNUMBER(SEARCH("PSA 10",$B8)),ISNUMBER(SEARCH("PSA 9.5",$B8)),ISNUMBER(SEARCH("PSA 9",$B8))),"TIER 3",IF(AND($D8>20,N($E8)>=15),"TIER 1","—")))) -> — | I8: =IF($B8="","",IF($D8>=100,"Premium $100+ (auto)",IF(OR(ISNUMBER(SEARCH("PSA 10",$B8)),ISNUMBER(SEARCH("PSA 9.5",$B8)),ISNUMBER(SEARCH("PSA 9",$B8))),"Graded PSA 9+ (auto)",IF(AND($D8>20,N($E8)>=15),"Hot: $20+ & "&$E8&"/day",IF($D8>20,"$20+ — needs velocity check","Below thresholds"))))) -> Below thresholds | J8: =IF($B8="","",IF(AND($D8>20,$D8<100,NOT(OR(ISNUMBER(SEARCH("PSA 10",$B8)),ISNUMBER(SEARCH("PSA 9.5",$B8)),ISNUMBER(SEARCH("PSA 9",$B8)))),$E8=""),"YES — pull CardHedger",""))
A9: 226788724174 | B9: 2025 Bowman 1st Chrome Jhonayker Ugarte #BCP-123 (RC) Royals | C9: CDP-E37E4FD | D9: 1.99 | F9: =IF($B9="","",IF(ISNUMBER(SEARCH("PSA",$B9)),"Yes","No")) -> No | G9: =IF($B9="","",IF(ISNUMBER(SEARCH("PSA 10",$B9)),10,IF(ISNUMBER(SEARCH("PSA 9.5",$B9)),9.5,IF(ISNUMBER(SEARCH("PSA 9",$B9)),9,IF(ISNUMBER(SEARCH("PSA 8",$B9)),8,IF(ISNUMBER(SEARCH("PSA",$B9)),"<9","")))))) | H9: =IF($B9="","",IF($D9>=100,"TIER 2",IF(OR(ISNUMBER(SEARCH("PSA 10",$B9)),ISNUMBER(SEARCH("PSA 9.5",$B9)),ISNUMBER(SEARCH("PSA 9",$B9))),"TIER 3",IF(AND($D9>20,N($E9)>=15),"TIER 1","—")))) -> — | I9: =IF($B9="","",IF($D9>=100,"Premium $100+ (auto)",IF(OR(ISNUMBER(SEARCH("PSA 10",$B9)),ISNUMBER(SEARCH("PSA 9.5",$B9)),ISNUMBER(SEARCH("PSA 9",$B9))),"Graded PSA 9+ (auto)",IF(AND($D9>20,N($E9)>=15),"Hot: $20+ & "&$E9&"/day",IF($D9>20,"$20+ — needs velocity check","Below thresholds"))))) -> Below thresholds | J9: =IF($B9="","",IF(AND($D9>20,$D9<100,NOT(OR(ISNUMBER(SEARCH("PSA 10",$B9)),ISNUMBER(SEARCH("PSA 9.5",$B9)),ISNUMBER(SEARCH("PSA 9",$B9)))),$E9=""),"YES — pull CardHedger",""))
A10: 226788730875 | B10: 2025 Bowman Chrome Kumar Rocker ROY-5 Texas Rangers | C10: CDP-067FF8D | D10: 1.25 | F10: =IF($B10="","",IF(ISNUMBER(SEARCH("PSA",$B10)),"Yes","No")) -> No | G10: =IF($B10="","",IF(ISNUMBER(SEARCH("PSA 10",$B10)),10,IF(ISNUMBER(SEARCH("PSA 9.5",$B10)),9.5,IF(ISNUMBER(SEARCH("PSA 9",$B10)),9,IF(ISNUMBER(SEARCH("PSA 8",$B10)),8,IF(ISNUMBER(SEARCH("PSA",$B10)),"<9","")))))) | H10: =IF($B10="","",IF($D10>=100,"TIER 2",IF(OR(ISNUMBER(SEARCH("PSA 10",$B10)),ISNUMBER(SEARCH("PSA 9.5",$B10)),ISNUMBER(SEARCH("PSA 9",$B10))),"TIER 3",IF(AND($D10>20,N($E10)>=15),"TIER 1","—")))) -> — | I10: =IF($B10="","",IF($D10>=100,"Premium $100+ (auto)",IF(OR(ISNUMBER(SEARCH("PSA 10",$B10)),ISNUMBER(SEARCH("PSA 9.5",$B10)),ISNUMBER(SEARCH("PSA 9",$B10))),"Graded PSA 9+ (auto)",IF(AND($D10>20,N($E10)>=15),"Hot: $20+ & "&$E10&"/day",IF($D10>20,"$20+ — needs velocity check","Below thresholds"))))) -> Below thresholds | J10: =IF($B10="","",IF(AND($D10>20,$D10<100,NOT(OR(ISNUMBER(SEARCH("PSA 10",$B10)),ISNUMBER(SEARCH("PSA 9.5",$B10)),ISNUMBER(SEARCH("PSA 9",$B10)))),$E10=""),"YES — pull CardHedger",""))
A11: 226788735090 | B11: 2024 Panini Illusions Michael Penix Jr. #4 (RC) Falcons | C11: CDP-6ABA4C8 | D11: 1.25 | F11: =IF($B11="","",IF(ISNUMBER(SEARCH("PSA",$B11)),"Yes","No")) -> No | G11: =IF($B11="","",IF(ISNUMBER(SEARCH("PSA 10",$B11)),10,IF(ISNUMBER(SEARCH("PSA 9.5",$B11)),9.5,IF(ISNUMBER(SEARCH("PSA 9",$B11)),9,IF(ISNUMBER(SEARCH("PSA 8",$B11)),8,IF(ISNUMBER(SEARCH("PSA",$B11)),"<9","")))))) | H11: =IF($B11="","",IF($D11>=100,"TIER 2",IF(OR(ISNUMBER(SEARCH("PSA 10",$B11)),ISNUMBER(SEARCH("PSA 9.5",$B11)),ISNUMBER(SEARCH("PSA 9",$B11))),"TIER 3",IF(AND($D11>20,N($E11)>=15),"TIER 1","—")))) -> — | I11: =IF($B11="","",IF($D11>=100,"Premium $100+ (auto)",IF(OR(ISNUMBER(SEARCH("PSA 10",$B11)),ISNUMBER(SEARCH("PSA 9.5",$B11)),ISNUMBER(SEARCH("PSA 9",$B11))),"Graded PSA 9+ (auto)",IF(AND($D11>20,N($E11)>=15),"Hot: $20+ & "&$E11&"/day",IF($D11>20,"$20+ — needs velocity check","Below thresholds"))))) -> Below thresholds | J11: =IF($B11="","",IF(AND($D11>20,$D11<100,NOT(OR(ISNUMBER(SEARCH("PSA 10",$B11)),ISNUMBER(SEARCH("PSA 9.5",$B11)),ISNUMBER(SEARCH("PSA 9",$B11)))),$E11=""),"YES — pull CardHedger",""))
A12: 226790522118 | B12: 2025 Topps Heritage Baseball #92 Bobby Witt Jr. 👑Kansas City Royals👑 | C12: CDP-E74F701 | D12: 1.99 | F12: =IF($B12="","",IF(ISNUMBER(SEARCH("PSA",$B12)),"Yes","No")) -> No | G12: =IF($B12="","",IF(ISNUMBER(SEARCH("PSA 10",$B12)),10,IF(ISNUMBER(SEARCH("PSA 9.5",$B12)),9.5,IF(ISNUMBER(SEARCH("PSA 9",$B12)),9,IF(ISNUMBER(SEARCH("PSA 8",$B12)),8,IF(ISNUMBER(SEARCH("PSA",$B12)),"<9","")))))) | H12: =IF($B12="","",IF($D12>=100,"TIER 2",IF(OR(ISNUMBER(SEARCH("PSA 10",$B12)),ISNUMBER(SEARCH("PSA 9.5",$B12)),ISNUMBER(SEARCH("PSA 9",$B12))),"TIER 3",IF(AND($D12>20,N($E12)>=15),"TIER 1","—")))) -> — | I12: =IF($B12="","",IF($D12>=100,"Premium $100+ (auto)",IF(OR(ISNUMBER(SEARCH("PSA 10",$B12)),ISNUMBER(SEARCH("PSA 9.5",$B12)),ISNUMBER(SEARCH("PSA 9",$B12))),"Graded PSA 9+ (auto)",IF(AND($D12>20,N($E12)>=15),"Hot: $20+ & "&$E12&"/day",IF($D12>20,"$20+ — needs velocity check","Below thresholds"))))) -> Below thresholds | J12: =IF($B12="","",IF(AND($D12>20,$D12<100,NOT(OR(ISNUMBER(SEARCH("PSA 10",$B12)),ISNUMBER(SEARCH("PSA 9.5",$B12)),ISNUMBER(SEARCH("PSA 9",$B12)))),$E12=""),"YES — pull CardHedger",""))
A13: 226792471627 | B13: 2025 Bowman Connor Norby #46 (RC) Marlins | C13: CDP-4895D6C | D13: 1.5 | F13: =IF($B13="","",IF(ISNUMBER(SEARCH("PSA",$B13)),"Yes","No")) -> No | G13: =IF($B13="","",IF(ISNUMBER(SEARCH("PSA 10",$B13)),10,IF(ISNUMBER(SEARCH("PSA 9.5",$B13)),9.5,IF(ISNUMBER(SEARCH("PSA 9",$B13)),9,IF(ISNUMBER(SEARCH("PSA 8",$B13)),8,IF(ISNUMBER(SEARCH("PSA",$B13)),"<9","")))))) | H13: =IF($B13="","",IF($D13>=100,"TIER 2",IF(OR(ISNUMBER(SEARCH("PSA 10",$B13)),ISNUMBER(SEARCH("PSA 9.5",$B13)),ISNUMBER(SEARCH("PSA 9",$B13))),"TIER 3",IF(AND($D13>20,N($E13)>=15),"TIER 1","—")))) -> — | I13: =IF($B13="","",IF($D13>=100,"Premium $100+ (auto)",IF(OR(ISNUMBER(SEARCH("PSA 10",$B13)),ISNUMBER(SEARCH("PSA 9.5",$B13)),ISNUMBER(SEARCH("PSA 9",$B13))),"Graded PSA 9+ (auto)",IF(AND($D13>20,N($E13)>=15),"Hot: $20+ & "&$E13&"/day",IF($D13>20,"$20+ — needs velocity check","Below thresholds"))))) -> Below thresholds | J13: =IF($B13="","",IF(AND($D13>20,$D13<100,NOT(OR(ISNUMBER(SEARCH("PSA 10",$B13)),ISNUMBER(SEARCH("PSA 9.5",$B13)),ISNUMBER(SEARCH("PSA 9",$B13)))),$E13=""),"YES — pull CardHedger",""))
A14: 226792475559 | B14: 2025 Topps Series 1 Ronald Acuña Jr. #TG-16 Training Grounds Braves | C14: CDP-B954CB1 | D14: 1.49 | F14: =IF($B14="","",IF(ISNUMBER(SEARCH("PSA",$B14)),"Yes","No")) -> No | G14: =IF($B14="","",IF(ISNUMBER(SEARCH("PSA 10",$B14)),10,IF(ISNUMBER(SEARCH("PSA 9.5",$B14)),9.5,IF(ISNUMBER(SEARCH("PSA 9",$B14)),9,IF(ISNUMBER(SEARCH("PSA 8",$B14)),8,IF(ISNUMBER(SEARCH("PSA",$B14)),"<9","")))))) | H14: =IF($B14="","",IF($D14>=100,"TIER 2",IF(OR(ISNUMBER(SEARCH("PSA 10",$B14)),ISNUMBER(SEARCH("PSA 9.5",$B14)),ISNUMBER(SEARCH("PSA 9",$B14))),"TIER 3",IF(AND($D14>20,N($E14)>=15),"TIER 1","—")))) -> — | I14: =IF($B14="","",IF($D14>=100,"Premium $100+ (auto)",IF(OR(ISNUMBER(SEARCH("PSA 10",$B14)),ISNUMBER(SEARCH("PSA 9.5",$B14)),ISNUMBER(SEARCH("PSA 9",$B14))),"Graded PSA 9+ (auto)",IF(AND($D14>20,N($E14)>=15),"Hot: $20+ & "&$E14&"/day",IF($D14>20,"$20+ — needs velocity check","Below thresholds"))))) -> Below thresholds | J14: =IF($B14="","",IF(AND($D14>20,$D14<100,NOT(OR(ISNUMBER(SEARCH("PSA 10",$B14)),ISNUMBER(SEARCH("PSA 9.5",$B14)),ISNUMBER(SEARCH("PSA 9",$B14)))),$E14=""),"YES — pull CardHedger",""))
A15: 226792488707 | B15: 2025 Topps 2024's Greatest Hits #GH-27 Wyatt Langford Texas Rangers | C15: CDP-4C8AF73 | D15: 1.99 | F15: =IF($B15="","",IF(ISNUMBER(SEARCH("PSA",$B15)),"Yes","No")) -> No | G15: =IF($B15="","",IF(ISNUMBER(SEARCH("PSA 10",$B15)),10,IF(ISNUMBER(SEARCH("PSA 9.5",$B15)),9.5,IF(ISNUMBER(SEARCH("PSA 9",$B15)),9,IF(ISNUMBER(SEARCH("PSA 8",$B15)),8,IF(ISNUMBER(SEARCH("PSA",$B15)),"<9","")))))) | H15: =IF($B15="","",IF($D15>=100,"TIER 2",IF(OR(ISNUMBER(SEARCH("PSA 10",$B15)),ISNUMBER(SEARCH("PSA 9.5",$B15)),ISNUMBER(SEARCH("PSA 9",$B15))),"TIER 3",IF(AND($D15>20,N($E15)>=15),"TIER 1","—")))) -> — | I15: =IF($B15="","",IF($D15>=100,"Premium $100+ (auto)",IF(OR(ISNUMBER(SEARCH("PSA 10",$B15)),ISNUMBER(SEARCH("PSA 9.5",$B15)),ISNUMBER(SEARCH("PSA 9",$B15))),"Graded PSA 9+ (auto)",IF(AND($D15>20,N($E15)>=15),"Hot: $20+ & "&$E15&"/day",IF($D15>20,"$20+ — needs velocity check","Below thresholds"))))) -> Below thresholds | J15: =IF($B15="","",IF(AND($D15>20,$D15<100,NOT(OR(ISNUMBER(SEARCH("PSA 10",$B15)),ISNUMBER(SEARCH("PSA 9.5",$B15)),ISNUMBER(SEARCH("PSA 9",$B15)))),$E15=""),"YES — pull CardHedger",""))
A16: 226792491039 | B16: 2025 Topps Series 1 Mookie Betts 1990 Topps Baseball #T90-60 Dodgers | C16: CDP-2EE740C | D16: 1.25 | F16: =IF($B16="","",IF(ISNUMBER(SEARCH("PSA",$B16)),"Yes","No")) -> No | G16: =IF($B16="","",IF(ISNUMBER(SEARCH("PSA 10",$B16)),10,IF(ISNUMBER(SEARCH("PSA 9.5",$B16)),9.5,IF(ISNUMBER(SEARCH("PSA 9",$B16)),9,IF(ISNUMBER(SEARCH("PSA 8",$B16)),8,IF(ISNUMBER(SEARCH("PSA",$B16)),"<9","")))))) | H16: =IF($B16="","",IF($D16>=100,"TIER 2",IF(OR(ISNUMBER(SEARCH("PSA 10",$B16)),ISNUMBER(SEARCH("PSA 9.5",$B16)),ISNUMBER(SEARCH("PSA 9",$B16))),"TIER 3",IF(AND($D16>20,N($E16)>=15),"TIER 1","—")))) -> — | I16: =IF($B16="","",IF($D16>=100,"Premium $100+ (auto)",IF(OR(ISNUMBER(SEARCH("PSA 10",$B16)),ISNUMBER(SEARCH("PSA 9.5",$B16)),ISNUMBER(SEARCH("PSA 9",$B16))),"Graded PSA 9+ (auto)",IF(AND($D16>20,N($E16)>=15),"Hot: $20+ & "&$E16&"/day",IF($D16>20,"$20+ — needs velocity check","Below thresholds"))))) -> Below thresholds | J16: =IF($B16="","",IF(AND($D16>20,$D16<100,NOT(OR(ISNUMBER(SEARCH("PSA 10",$B16)),ISNUMBER(SEARCH("PSA 9.5",$B16)),ISNUMBER(SEARCH("PSA 9",$B16)))),$E16=""),"YES — pull CardHedger",""))
... A4021: 227307171700 | B4021: 2025 Topps Now Aaron Judge Shohei Ohtani MVP Homers Same Inning #239 | C4021: MISC-0002-00003-90757 | D4021: 7 | F4021: =IF($B4021="","",IF(ISNUMBER(SEARCH("PSA",$B4021)),"Yes","No")) -> No | G4021: =IF($B4021="","",IF(ISNUMBER(SEARCH("PSA 10",$B4021)),10,IF(ISNUMBER(SEARCH("PSA 9.5",$B4021)),9.5,IF(ISNUMBER(SEARCH("PSA 9",$B4021)),9,IF(ISNUMBER(SEARCH("PSA 8",$B4021)),8,IF(ISNUMBER(SEARCH("PSA",$B4021)),"<9","")))))) | H4021: =IF($B4021="","",IF($D4021>=100,"TIER 2",IF(OR(ISNUMBER(SEARCH("PSA 10",$B4021)),ISNUMBER(SEARCH("PSA 9.5",$B4021)),ISNUMBER(SEARCH("PSA 9",$B4021))),"TIER 3",IF(AND($D4021>20,N($E4021)>=15),"TIER 1","—")))) -> — | I4021: =IF($B4021="","",IF($D4021>=100,"Premium $100+ (auto)",IF(OR(ISNUMBER(SEARCH("PSA 10",$B4021)),ISNUMBER(SEARCH("PSA 9.5",$B4021)),ISNUMBER(SEARCH("PSA 9",$B4021))),"Graded PSA 9+ (auto)",IF(AND($D4021>20,N($E4021)>=15),"Hot: $20+ & "&$E4021&"/day",IF($D4021>20,"$20+ — needs velocity check","Below thresholds"))))) -> Below thresholds | J4021: =IF($B4021="","",IF(AND($D4021>20,$D4021<100,NOT(OR(ISNUMBER(SEARCH("PSA 10",$B4021)),ISNUMBER(SEARCH("PSA 9.5",$B4021)),ISNUMBER(SEARCH("PSA 9",$B4021)))),$E4021=""),"YES — pull CardHedger",""))
A4022: 227307306880 | B4022: 2021-22 Topps Stadium Club Chrome Uefa Champions League - Lionel Messi #30 Aqua | D4022: 179.99 | F4022: =IF($B4022="","",IF(ISNUMBER(SEARCH("PSA",$B4022)),"Yes","No")) -> No | G4022: =IF($B4022="","",IF(ISNUMBER(SEARCH("PSA 10",$B4022)),10,IF(ISNUMBER(SEARCH("PSA 9.5",$B4022)),9.5,IF(ISNUMBER(SEARCH("PSA 9",$B4022)),9,IF(ISNUMBER(SEARCH("PSA 8",$B4022)),8,IF(ISNUMBER(SEARCH("PSA",$B4022)),"<9","")))))) | H4022: =IF($B4022="","",IF($D4022>=100,"TIER 2",IF(OR(ISNUMBER(SEARCH("PSA 10",$B4022)),ISNUMBER(SEARCH("PSA 9.5",$B4022)),ISNUMBER(SEARCH("PSA 9",$B4022))),"TIER 3",IF(AND($D4022>20,N($E4022)>=15),"TIER 1","—")))) -> TIER 2 | I4022: =IF($B4022="","",IF($D4022>=100,"Premium $100+ (auto)",IF(OR(ISNUMBER(SEARCH("PSA 10",$B4022)),ISNUMBER(SEARCH("PSA 9.5",$B4022)),ISNUMBER(SEARCH("PSA 9",$B4022))),"Graded PSA 9+ (auto)",IF(AND($D4022>20,N($E4022)>=15),"Hot: $20+ & "&$E4022&"/day",IF($D4022>20,"$20+ — needs velocity check","Below thresholds"))))) -> Premium $100+ (auto) | J4022: =IF($B4022="","",IF(AND($D4022>20,$D4022<100,NOT(OR(ISNUMBER(SEARCH("PSA 10",$B4022)),ISNUMBER(SEARCH("PSA 9.5",$B4022)),ISNUMBER(SEARCH("PSA 9",$B4022)))),$E4022=""),"YES — pull CardHedger",""))
A4023: 227307310214 | B4023: Leaf Legend Lionel Messi Exclusive Edition LE-02 Soccer Card 2023 | D4023: 25 | F4023: =IF($B4023="","",IF(ISNUMBER(SEARCH("PSA",$B4023)),"Yes","No")) -> No | G4023: =IF($B4023="","",IF(ISNUMBER(SEARCH("PSA 10",$B4023)),10,IF(ISNUMBER(SEARCH("PSA 9.5",$B4023)),9.5,IF(ISNUMBER(SEARCH("PSA 9",$B4023)),9,IF(ISNUMBER(SEARCH("PSA 8",$B4023)),8,IF(ISNUMBER(SEARCH("PSA",$B4023)),"<9","")))))) | H4023: =IF($B4023="","",IF($D4023>=100,"TIER 2",IF(OR(ISNUMBER(SEARCH("PSA 10",$B4023)),ISNUMBER(SEARCH("PSA 9.5",$B4023)),ISNUMBER(SEARCH("PSA 9",$B4023))),"TIER 3",IF(AND($D4023>20,N($E4023)>=15),"TIER 1","—")))) -> — | I4023: =IF($B4023="","",IF($D4023>=100,"Premium $100+ (auto)",IF(OR(ISNUMBER(SEARCH("PSA 10",$B4023)),ISNUMBER(SEARCH("PSA 9.5",$B4023)),ISNUMBER(SEARCH("PSA 9",$B4023))),"Graded PSA 9+ (auto)",IF(AND($D4023>20,N($E4023)>=15),"Hot: $20+ & "&$E4023&"/day",IF($D4023>20,"$20+ — needs velocity check","Below thresholds"))))) -> $20+ — needs velocity check | J4023: =IF($B4023="","",IF(AND($D4023>20,$D4023<100,NOT(OR(ISNUMBER(SEARCH("PSA 10",$B4023)),ISNUMBER(SEARCH("PSA 9.5",$B4023)),ISNUMBER(SEARCH("PSA 9",$B4023)))),$E4023=""),"YES — pull CardHedger","")) -> YES — pull CardHedger
A4024: 227308339104 | B4024: 2026 Topps Jac Caglianone #138 RC Royals | C4024: MISC-0002-00016-30315 | D4024: 1.99 | F4024: =IF($B4024="","",IF(ISNUMBER(SEARCH("PSA",$B4024)),"Yes","No")) -> No | G4024: =IF($B4024="","",IF(ISNUMBER(SEARCH("PSA 10",$B4024)),10,IF(ISNUMBER(SEARCH("PSA 9.5",$B4024)),9.5,IF(ISNUMBER(SEARCH("PSA 9",$B4024)),9,IF(ISNUMBER(SEARCH("PSA 8",$B4024)),8,IF(ISNUMBER(SEARCH("PSA",$B4024)),"<9","")))))) | H4024: =IF($B4024="","",IF($D4024>=100,"TIER 2",IF(OR(ISNUMBER(SEARCH("PSA 10",$B4024)),ISNUMBER(SEARCH("PSA 9.5",$B4024)),ISNUMBER(SEARCH("PSA 9",$B4024))),"TIER 3",IF(AND($D4024>20,N($E4024)>=15),"TIER 1","—")))) -> — | I4024: =IF($B4024="","",IF($D4024>=100,"Premium $100+ (auto)",IF(OR(ISNUMBER(SEARCH("PSA 10",$B4024)),ISNUMBER(SEARCH("PSA 9.5",$B4024)),ISNUMBER(SEARCH("PSA 9",$B4024))),"Graded PSA 9+ (auto)",IF(AND($D4024>20,N($E4024)>=15),"Hot: $20+ & "&$E4024&"/day",IF($D4024>20,"$20+ — needs velocity check","Below thresholds"))))) -> Below thresholds | J4024: =IF($B4024="","",IF(AND($D4024>20,$D4024<100,NOT(OR(ISNUMBER(SEARCH("PSA 10",$B4024)),ISNUMBER(SEARCH("PSA 9.5",$B4024)),ISNUMBER(SEARCH("PSA 9",$B4024)))),$E4024=""),"YES — pull CardHedger",""))
A4025: 227308339114 | B4025: 2025 Bowman's Best Cam Smith #29 Lazer Refractor 314/350 RC Astros | C4025: MISC-0002-00007-33697 | D4025: 4.79 | F4025: =IF($B4025="","",IF(ISNUMBER(SEARCH("PSA",$B4025)),"Yes","No")) -> No | G4025: =IF($B4025="","",IF(ISNUMBER(SEARCH("PSA 10",$B4025)),10,IF(ISNUMBER(SEARCH("PSA 9.5",$B4025)),9.5,IF(ISNUMBER(SEARCH("PSA 9",$B4025)),9,IF(ISNUMBER(SEARCH("PSA 8",$B4025)),8,IF(ISNUMBER(SEARCH("PSA",$B4025)),"<9","")))))) | H4025: =IF($B4025="","",IF($D4025>=100,"TIER 2",IF(OR(ISNUMBER(SEARCH("PSA 10",$B4025)),ISNUMBER(SEARCH("PSA 9.5",$B4025)),ISNUMBER(SEARCH("PSA 9",$B4025))),"TIER 3",IF(AND($D4025>20,N($E4025)>=15),"TIER 1","—")))) -> — | I4025: =IF($B4025="","",IF($D4025>=100,"Premium $100+ (auto)",IF(OR(ISNUMBER(SEARCH("PSA 10",$B4025)),ISNUMBER(SEARCH("PSA 9.5",$B4025)),ISNUMBER(SEARCH("PSA 9",$B4025))),"Graded PSA 9+ (auto)",IF(AND($D4025>20,N($E4025)>=15),"Hot: $20+ & "&$E4025&"/day",IF($D4025>20,"$20+ — needs velocity check","Below thresholds"))))) -> Below thresholds | J4025: =IF($B4025="","",IF(AND($D4025>20,$D4025<100,NOT(OR(ISNUMBER(SEARCH("PSA 10",$B4025)),ISNUMBER(SEARCH("PSA 9.5",$B4025)),ISNUMBER(SEARCH("PSA 9",$B4025)))),$E4025=""),"YES — pull CardHedger",""))
A4026: 227308339137 | B4026: 2025 Bowman's Best Ketel Marte #62 Refractor Diamondbacks | C4026: MISC-0002-00013-17413 | D4026: 1.99 | F4026: =IF($B4026="","",IF(ISNUMBER(SEARCH("PSA",$B4026)),"Yes","No")) -> No | G4026: =IF($B4026="","",IF(ISNUMBER(SEARCH("PSA 10",$B4026)),10,IF(ISNUMBER(SEARCH("PSA 9.5",$B4026)),9.5,IF(ISNUMBER(SEARCH("PSA 9",$B4026)),9,IF(ISNUMBER(SEARCH("PSA 8",$B4026)),8,IF(ISNUMBER(SEARCH("PSA",$B4026)),"<9","")))))) | H4026: =IF($B4026="","",IF($D4026>=100,"TIER 2",IF(OR(ISNUMBER(SEARCH("PSA 10",$B4026)),ISNUMBER(SEARCH("PSA 9.5",$B4026)),ISNUMBER(SEARCH("PSA 9",$B4026))),"TIER 3",IF(AND($D4026>20,N($E4026)>=15),"TIER 1","—")))) -> — | I4026: =IF($B4026="","",IF($D4026>=100,"Premium $100+ (auto)",IF(OR(ISNUMBER(SEARCH("PSA 10",$B4026)),ISNUMBER(SEARCH("PSA 9.5",$B4026)),ISNUMBER(SEARCH("PSA 9",$B4026))),"Graded PSA 9+ (auto)",IF(AND($D4026>20,N($E4026)>=15),"Hot: $20+ & "&$E4026&"/day",IF($D4026>20,"$20+ — needs velocity check","Below thresholds"))))) -> Below thresholds | J4026: =IF($B4026="","",IF(AND($D4026>20,$D4026<100,NOT(OR(ISNUMBER(SEARCH("PSA 10",$B4026)),ISNUMBER(SEARCH("PSA 9.5",$B4026)),ISNUMBER(SEARCH("PSA 9",$B4026)))),$E4026=""),"YES — pull CardHedger",""))
A4027: 227308339173 | B4027: 2025 Bowman Draft Ike Irish #PP-8 Chrome Prized Prospects Mojo Refractor Orioles | C4027: MISC-0002-00001-61747 | D4027: 1.99 | F4027: =IF($B4027="","",IF(ISNUMBER(SEARCH("PSA",$B4027)),"Yes","No")) -> No | G4027: =IF($B4027="","",IF(ISNUMBER(SEARCH("PSA 10",$B4027)),10,IF(ISNUMBER(SEARCH("PSA 9.5",$B4027)),9.5,IF(ISNUMBER(SEARCH("PSA 9",$B4027)),9,IF(ISNUMBER(SEARCH("PSA 8",$B4027)),8,IF(ISNUMBER(SEARCH("PSA",$B4027)),"<9","")))))) | H4027: =IF($B4027="","",IF($D4027>=100,"TIER 2",IF(OR(ISNUMBER(SEARCH("PSA 10",$B4027)),ISNUMBER(SEARCH("PSA 9.5",$B4027)),ISNUMBER(SEARCH("PSA 9",$B4027))),"TIER 3",IF(AND($D4027>20,N($E4027)>=15),"TIER 1","—")))) -> — | I4027: =IF($B4027="","",IF($D4027>=100,"Premium $100+ (auto)",IF(OR(ISNUMBER(SEARCH("PSA 10",$B4027)),ISNUMBER(SEARCH("PSA 9.5",$B4027)),ISNUMBER(SEARCH("PSA 9",$B4027))),"Graded PSA 9+ (auto)",IF(AND($D4027>20,N($E4027)>=15),"Hot: $20+ & "&$E4027&"/day",IF($D4027>20,"$20+ — needs velocity check","Below thresholds"))))) -> Below thresholds | J4027: =IF($B4027="","",IF(AND($D4027>20,$D4027<100,NOT(OR(ISNUMBER(SEARCH("PSA 10",$B4027)),ISNUMBER(SEARCH("PSA 9.5",$B4027)),ISNUMBER(SEARCH("PSA 9",$B4027)))),$E4027=""),"YES — pull CardHedger",""))
A4028: 227308339348 | B4028: 2026 Topps Collector's Kit Exclusive Francisco Lindor #MLB-4 Rainbow Foil | C4028: MISC-0002-00011-28533 | D4028: 1.99 | F4028: =IF($B4028="","",IF(ISNUMBER(SEARCH("PSA",$B4028)),"Yes","No")) -> No | G4028: =IF($B4028="","",IF(ISNUMBER(SEARCH("PSA 10",$B4028)),10,IF(ISNUMBER(SEARCH("PSA 9.5",$B4028)),9.5,IF(ISNUMBER(SEARCH("PSA 9",$B4028)),9,IF(ISNUMBER(SEARCH("PSA 8",$B4028)),8,IF(ISNUMBER(SEARCH("PSA",$B4028)),"<9","")))))) | H4028: =IF($B4028="","",IF($D4028>=100,"TIER 2",IF(OR(ISNUMBER(SEARCH("PSA 10",$B4028)),ISNUMBER(SEARCH("PSA 9.5",$B4028)),ISNUMBER(SEARCH("PSA 9",$B4028))),"TIER 3",IF(AND($D4028>20,N($E4028)>=15),"TIER 1","—")))) -> — | I4028: =IF($B4028="","",IF($D4028>=100,"Premium $100+ (auto)",IF(OR(ISNUMBER(SEARCH("PSA 10",$B4028)),ISNUMBER(SEARCH("PSA 9.5",$B4028)),ISNUMBER(SEARCH("PSA 9",$B4028))),"Graded PSA 9+ (auto)",IF(AND($D4028>20,N($E4028)>=15),"Hot: $20+ & "&$E4028&"/day",IF($D4028>20,"$20+ — needs velocity check","Below thresholds"))))) -> Below thresholds | J4028: =IF($B4028="","",IF(AND($D4028>20,$D4028<100,NOT(OR(ISNUMBER(SEARCH("PSA 10",$B4028)),ISNUMBER(SEARCH("PSA 9.5",$B4028)),ISNUMBER(SEARCH("PSA 9",$B4028)))),$E4028=""),"YES — pull CardHedger",""))
A4029: 227308339412 | B4029: 2025 Bowman Draft Jared Thomas #BDC-147 Chrome Yellow Geometric Refractor /75 | C4029: MISC-0002-00012-75919 | D4029: 8.99 | F4029: =IF($B4029="","",IF(ISNUMBER(SEARCH("PSA",$B4029)),"Yes","No")) -> No | G4029: =IF($B4029="","",IF(ISNUMBER(SEARCH("PSA 10",$B4029)),10,IF(ISNUMBER(SEARCH("PSA 9.5",$B4029)),9.5,IF(ISNUMBER(SEARCH("PSA 9",$B4029)),9,IF(ISNUMBER(SEARCH("PSA 8",$B4029)),8,IF(ISNUMBER(SEARCH("PSA",$B4029)),"<9","")))))) | H4029: =IF($B4029="","",IF($D4029>=100,"TIER 2",IF(OR(ISNUMBER(SEARCH("PSA 10",$B4029)),ISNUMBER(SEARCH("PSA 9.5",$B4029)),ISNUMBER(SEARCH("PSA 9",$B4029))),"TIER 3",IF(AND($D4029>20,N($E4029)>=15),"TIER 1","—")))) -> — | I4029: =IF($B4029="","",IF($D4029>=100,"Premium $100+ (auto)",IF(OR(ISNUMBER(SEARCH("PSA 10",$B4029)),ISNUMBER(SEARCH("PSA 9.5",$B4029)),ISNUMBER(SEARCH("PSA 9",$B4029))),"Graded PSA 9+ (auto)",IF(AND($D4029>20,N($E4029)>=15),"Hot: $20+ & "&$E4029&"/day",IF($D4029>20,"$20+ — needs velocity check","Below thresholds"))))) -> Below thresholds | J4029: =IF($B4029="","",IF(AND($D4029>20,$D4029<100,NOT(OR(ISNUMBER(SEARCH("PSA 10",$B4029)),ISNUMBER(SEARCH("PSA 9.5",$B4029)),ISNUMBER(SEARCH("PSA 9",$B4029)))),$E4029=""),"YES — pull CardHedger",""))
A4030: 227308339424 | B4030: 2025 Bowman's Best Christian Moore #TP-2 Top Prospects Refractor Angels | C4030: MISC-0002-00015-14735 | D4030: 2.49 | F4030: =IF($B4030="","",IF(ISNUMBER(SEARCH("PSA",$B4030)),"Yes","No")) -> No | G4030: =IF($B4030="","",IF(ISNUMBER(SEARCH("PSA 10",$B4030)),10,IF(ISNUMBER(SEARCH("PSA 9.5",$B4030)),9.5,IF(ISNUMBER(SEARCH("PSA 9",$B4030)),9,IF(ISNUMBER(SEARCH("PSA 8",$B4030)),8,IF(ISNUMBER(SEARCH("PSA",$B4030)),"<9","")))))) | H4030: =IF($B4030="","",IF($D4030>=100,"TIER 2",IF(OR(ISNUMBER(SEARCH("PSA 10",$B4030)),ISNUMBER(SEARCH("PSA 9.5",$B4030)),ISNUMBER(SEARCH("PSA 9",$B4030))),"TIER 3",IF(AND($D4030>20,N($E4030)>=15),"TIER 1","—")))) -> — | I4030: =IF($B4030="","",IF($D4030>=100,"Premium $100+ (auto)",IF(OR(ISNUMBER(SEARCH("PSA 10",$B4030)),ISNUMBER(SEARCH("PSA 9.5",$B4030)),ISNUMBER(SEARCH("PSA 9",$B4030))),"Graded PSA 9+ (auto)",IF(AND($D4030>20,N($E4030)>=15),"Hot: $20+ & "&$E4030&"/day",IF($D4030>20,"$20+ — needs velocity check","Below thresholds"))))) -> Below thresholds | J4030: =IF($B4030="","",IF(AND($D4030>20,$D4030<100,NOT(OR(ISNUMBER(SEARCH("PSA 10",$B4030)),ISNUMBER(SEARCH("PSA 9.5",$B4030)),ISNUMBER(SEARCH("PSA 9",$B4030)))),$E4030=""),"YES — pull CardHedger",""))
A4031: 227308339457 | B4031: 2025 Bowman's Best Luke Keaschall #70 Refractor RC Twins | C4031: MISC-0002-00014-39180 | D4031: 1.99 | F4031: =IF($B4031="","",IF(ISNUMBER(SEARCH("PSA",$B4031)),"Yes","No")) -> No | G4031: =IF($B4031="","",IF(ISNUMBER(SEARCH("PSA 10",$B4031)),10,IF(ISNUMBER(SEARCH("PSA 9.5",$B4031)),9.5,IF(ISNUMBER(SEARCH("PSA 9",$B4031)),9,IF(ISNUMBER(SEARCH("PSA 8",$B4031)),8,IF(ISNUMBER(SEARCH("PSA",$B4031)),"<9","")))))) | H4031: =IF($B4031="","",IF($D4031>=100,"TIER 2",IF(OR(ISNUMBER(SEARCH("PSA 10",$B4031)),ISNUMBER(SEARCH("PSA 9.5",$B4031)),ISNUMBER(SEARCH("PSA 9",$B4031))),"TIER 3",IF(AND($D4031>20,N($E4031)>=15),"TIER 1","—")))) -> — | I4031: =IF($B4031="","",IF($D4031>=100,"Premium $100+ (auto)",IF(OR(ISNUMBER(SEARCH("PSA 10",$B4031)),ISNUMBER(SEARCH("PSA 9.5",$B4031)),ISNUMBER(SEARCH("PSA 9",$B4031))),"Graded PSA 9+ (auto)",IF(AND($D4031>20,N($E4031)>=15),"Hot: $20+ & "&$E4031&"/day",IF($D4031>20,"$20+ — needs velocity check","Below thresholds"))))) -> Below thresholds | J4031: =IF($B4031="","",IF(AND($D4031>20,$D4031<100,NOT(OR(ISNUMBER(SEARCH("PSA 10",$B4031)),ISNUMBER(SEARCH("PSA 9.5",$B4031)),ISNUMBER(SEARCH("PSA 9",$B4031)))),$E4031=""),"YES — pull CardHedger",""))
A4032: 227308339490 | B4032: 2025 Bowman's Best Corbin Carroll #8 Aqua Refractor /199 Diamondbacks | C4032: MISC-0002-00004-49744 | D4032: 3.89 | F4032: =IF($B4032="","",IF(ISNUMBER(SEARCH("PSA",$B4032)),"Yes","No")) -> No | G4032: =IF($B4032="","",IF(ISNUMBER(SEARCH("PSA 10",$B4032)),10,IF(ISNUMBER(SEARCH("PSA 9.5",$B4032)),9.5,IF(ISNUMBER(SEARCH("PSA 9",$B4032)),9,IF(ISNUMBER(SEARCH("PSA 8",$B4032)),8,IF(ISNUMBER(SEARCH("PSA",$B4032)),"<9","")))))) | H4032: =IF($B4032="","",IF($D4032>=100,"TIER 2",IF(OR(ISNUMBER(SEARCH("PSA 10",$B4032)),ISNUMBER(SEARCH("PSA 9.5",$B4032)),ISNUMBER(SEARCH("PSA 9",$B4032))),"TIER 3",IF(AND($D4032>20,N($E4032)>=15),"TIER 1","—")))) -> — | I4032: =IF($B4032="","",IF($D4032>=100,"Premium $100+ (auto)",IF(OR(ISNUMBER(SEARCH("PSA 10",$B4032)),ISNUMBER(SEARCH("PSA 9.5",$B4032)),ISNUMBER(SEARCH("PSA 9",$B4032))),"Graded PSA 9+ (auto)",IF(AND($D4032>20,N($E4032)>=15),"Hot: $20+ & "&$E4032&"/day",IF($D4032>20,"$20+ — needs velocity check","Below thresholds"))))) -> Below thresholds | J4032: =IF($B4032="","",IF(AND($D4032>20,$D4032<100,NOT(OR(ISNUMBER(SEARCH("PSA 10",$B4032)),ISNUMBER(SEARCH("PSA 9.5",$B4032)),ISNUMBER(SEARCH("PSA 9",$B4032)))),$E4032=""),"YES — pull CardHedger",""))
A4033: 227308339492 | B4033: 2025 Bowman's Best Cam Smith #29 Purple Blue Refractor /250 RC Astros | C4033: MISC-0002-00006-95693 | D4033: 5.59 | F4033: =IF($B4033="","",IF(ISNUMBER(SEARCH("PSA",$B4033)),"Yes","No")) -> No | G4033: =IF($B4033="","",IF(ISNUMBER(SEARCH("PSA 10",$B4033)),10,IF(ISNUMBER(SEARCH("PSA 9.5",$B4033)),9.5,IF(ISNUMBER(SEARCH("PSA 9",$B4033)),9,IF(ISNUMBER(SEARCH("PSA 8",$B4033)),8,IF(ISNUMBER(SEARCH("PSA",$B4033)),"<9","")))))) | H4033: =IF($B4033="","",IF($D4033>=100,"TIER 2",IF(OR(ISNUMBER(SEARCH("PSA 10",$B4033)),ISNUMBER(SEARCH("PSA 9.5",$B4033)),ISNUMBER(SEARCH("PSA 9",$B4033))),"TIER 3",IF(AND($D4033>20,N($E4033)>=15),"TIER 1","—")))) -> — | I4033: =IF($B4033="","",IF($D4033>=100,"Premium $100+ (auto)",IF(OR(ISNUMBER(SEARCH("PSA 10",$B4033)),ISNUMBER(SEARCH("PSA 9.5",$B4033)),ISNUMBER(SEARCH("PSA 9",$B4033))),"Graded PSA 9+ (auto)",IF(AND($D4033>20,N($E4033)>=15),"Hot: $20+ & "&$E4033&"/day",IF($D4033>20,"$20+ — needs velocity check","Below thresholds"))))) -> Below thresholds | J4033: =IF($B4033="","",IF(AND($D4033>20,$D4033<100,NOT(OR(ISNUMBER(SEARCH("PSA 10",$B4033)),ISNUMBER(SEARCH("PSA 9.5",$B4033)),ISNUMBER(SEARCH("PSA 9",$B4033)))),$E4033=""),"YES — pull CardHedger",""))
A4034: 227308676759 | B4034: Leaf Exclusive Legends Double Lamine Yamal Lionel Messi Blue #/20 GMA 10 Mint | D4034: 175 | F4034: =IF($B4034="","",IF(ISNUMBER(SEARCH("PSA",$B4034)),"Yes","No")) -> No | G4034: =IF($B4034="","",IF(ISNUMBER(SEARCH("PSA 10",$B4034)),10,IF(ISNUMBER(SEARCH("PSA 9.5",$B4034)),9.5,IF(ISNUMBER(SEARCH("PSA 9",$B4034)),9,IF(ISNUMBER(SEARCH("PSA 8",$B4034)),8,IF(ISNUMBER(SEARCH("PSA",$B4034)),"<9","")))))) | H4034: =IF($B4034="","",IF($D4034>=100,"TIER 2",IF(OR(ISNUMBER(SEARCH("PSA 10",$B4034)),ISNUMBER(SEARCH("PSA 9.5",$B4034)),ISNUMBER(SEARCH("PSA 9",$B4034))),"TIER 3",IF(AND($D4034>20,N($E4034)>=15),"TIER 1","—")))) -> TIER 2 | I4034: =IF($B4034="","",IF($D4034>=100,"Premium $100+ (auto)",IF(OR(ISNUMBER(SEARCH("PSA 10",$B4034)),ISNUMBER(SEARCH("PSA 9.5",$B4034)),ISNUMBER(SEARCH("PSA 9",$B4034))),"Graded PSA 9+ (auto)",IF(AND($D4034>20,N($E4034)>=15),"Hot: $20+ & "&$E4034&"/day",IF($D4034>20,"$20+ — needs velocity check","Below thresholds"))))) -> Premium $100+ (auto) | J4034: =IF($B4034="","",IF(AND($D4034>20,$D4034<100,NOT(OR(ISNUMBER(SEARCH("PSA 10",$B4034)),ISNUMBER(SEARCH("PSA 9.5",$B4034)),ISNUMBER(SEARCH("PSA 9",$B4034)))),$E4034=""),"YES — pull CardHedger",""))
A4035: 227311375207 | B4035: 2025 Bowman Draft Billy Carlson #BDC-10 Chrome Mojo Refractor 1st Prospect | C4035: RB-0007-00005-45231 | D4035: 2.99 | F4035: =IF($B4035="","",IF(ISNUMBER(SEARCH("PSA",$B4035)),"Yes","No")) -> No | G4035: =IF($B4035="","",IF(ISNUMBER(SEARCH("PSA 10",$B4035)),10,IF(ISNUMBER(SEARCH("PSA 9.5",$B4035)),9.5,IF(ISNUMBER(SEARCH("PSA 9",$B4035)),9,IF(ISNUMBER(SEARCH("PSA 8",$B4035)),8,IF(ISNUMBER(SEARCH("PSA",$B4035)),"<9","")))))) | H4035: =IF($B4035="","",IF($D4035>=100,"TIER 2",IF(OR(ISNUMBER(SEARCH("PSA 10",$B4035)),ISNUMBER(SEARCH("PSA 9.5",$B4035)),ISNUMBER(SEARCH("PSA 9",$B4035))),"TIER 3",IF(AND($D4035>20,N($E4035)>=15),"TIER 1","—")))) -> — | I4035: =IF($B4035="","",IF($D4035>=100,"Premium $100+ (auto)",IF(OR(ISNUMBER(SEARCH("PSA 10",$B4035)),ISNUMBER(SEARCH("PSA 9.5",$B4035)),ISNUMBER(SEARCH("PSA 9",$B4035))),"Graded PSA 9+ (auto)",IF(AND($D4035>20,N($E4035)>=15),"Hot: $20+ & "&$E4035&"/day",IF($D4035>20,"$20+ — needs velocity check","Below thresholds"))))) -> Below thresholds | J4035: =IF($B4035="","",IF(AND($D4035>20,$D4035<100,NOT(OR(ISNUMBER(SEARCH("PSA 10",$B4035)),ISNUMBER(SEARCH("PSA 9.5",$B4035)),ISNUMBER(SEARCH("PSA 9",$B4035)))),$E4035=""),"YES — pull CardHedger",""))
A4036: 227311465983 | B4036: 2025-26 Topps Finest Cedric Coward #11 Common RC Grizzlies | C4036: RB-0007-00001-61805 | D4036: 1.99 | F4036: =IF($B4036="","",IF(ISNUMBER(SEARCH("PSA",$B4036)),"Yes","No")) -> No | G4036: =IF($B4036="","",IF(ISNUMBER(SEARCH("PSA 10",$B4036)),10,IF(ISNUMBER(SEARCH("PSA 9.5",$B4036)),9.5,IF(ISNUMBER(SEARCH("PSA 9",$B4036)),9,IF(ISNUMBER(SEARCH("PSA 8",$B4036)),8,IF(ISNUMBER(SEARCH("PSA",$B4036)),"<9","")))))) | H4036: =IF($B4036="","",IF($D4036>=100,"TIER 2",IF(OR(ISNUMBER(SEARCH("PSA 10",$B4036)),ISNUMBER(SEARCH("PSA 9.5",$B4036)),ISNUMBER(SEARCH("PSA 9",$B4036))),"TIER 3",IF(AND($D4036>20,N($E4036)>=15),"TIER 1","—")))) -> — | I4036: =IF($B4036="","",IF($D4036>=100,"Premium $100+ (auto)",IF(OR(ISNUMBER(SEARCH("PSA 10",$B4036)),ISNUMBER(SEARCH("PSA 9.5",$B4036)),ISNUMBER(SEARCH("PSA 9",$B4036))),"Graded PSA 9+ (auto)",IF(AND($D4036>20,N($E4036)>=15),"Hot: $20+ & "&$E4036&"/day",IF($D4036>20,"$20+ — needs velocity check","Below thresholds"))))) -> Below thresholds | J4036: =IF($B4036="","",IF(AND($D4036>20,$D4036<100,NOT(OR(ISNUMBER(SEARCH("PSA 10",$B4036)),ISNUMBER(SEARCH("PSA 9.5",$B4036)),ISNUMBER(SEARCH("PSA 9",$B4036)))),$E4036=""),"YES — pull CardHedger",""))
A4037: 227311465990 | B4037: 2025-26 Topps Chrome Egor Demin #SF-29 Sleek Finishers RC Nets | C4037: RB-0007-00027-26789 | D4037: 1.59 | F4037: =IF($B4037="","",IF(ISNUMBER(SEARCH("PSA",$B4037)),"Yes","No")) -> No | G4037: =IF($B4037="","",IF(ISNUMBER(SEARCH("PSA 10",$B4037)),10,IF(ISNUMBER(SEARCH("PSA 9.5",$B4037)),9.5,IF(ISNUMBER(SEARCH("PSA 9",$B4037)),9,IF(ISNUMBER(SEARCH("PSA 8",$B4037)),8,IF(ISNUMBER(SEARCH("PSA",$B4037)),"<9","")))))) | H4037: =IF($B4037="","",IF($D4037>=100,"TIER 2",IF(OR(ISNUMBER(SEARCH("PSA 10",$B4037)),ISNUMBER(SEARCH("PSA 9.5",$B4037)),ISNUMBER(SEARCH("PSA 9",$B4037))),"TIER 3",IF(AND($D4037>20,N($E4037)>=15),"TIER 1","—")))) -> — | I4037: =IF($B4037="","",IF($D4037>=100,"Premium $100+ (auto)",IF(OR(ISNUMBER(SEARCH("PSA 10",$B4037)),ISNUMBER(SEARCH("PSA 9.5",$B4037)),ISNUMBER(SEARCH("PSA 9",$B4037))),"Graded PSA 9+ (auto)",IF(AND($D4037>20,N($E4037)>=15),"Hot: $20+ & "&$E4037&"/day",IF($D4037>20,"$20+ — needs velocity check","Below thresholds"))))) -> Below thresholds | J4037: =IF($B4037="","",IF(AND($D4037>20,$D4037<100,NOT(OR(ISNUMBER(SEARCH("PSA 10",$B4037)),ISNUMBER(SEARCH("PSA 9.5",$B4037)),ISNUMBER(SEARCH("PSA 9",$B4037)))),$E4037=""),"YES — pull CardHedger",""))
A4038: 227311465994 | B4038: 2025-26 Topps Chrome Ben Saraf #276 RC Nets | C4038: RB-0007-00026-85645 | D4038: 1 | F4038: =IF($B4038="","",IF(ISNUMBER(SEARCH("PSA",$B4038)),"Yes","No")) -> No | G4038: =IF($B4038="","",IF(ISNUMBER(SEARCH("PSA 10",$B4038)),10,IF(ISNUMBER(SEARCH("PSA 9.5",$B4038)),9.5,IF(ISNUMBER(SEARCH("PSA 9",$B4038)),9,IF(ISNUMBER(SEARCH("PSA 8",$B4038)),8,IF(ISNUMBER(SEARCH("PSA",$B4038)),"<9","")))))) | H4038: =IF($B4038="","",IF($D4038>=100,"TIER 2",IF(OR(ISNUMBER(SEARCH("PSA 10",$B4038)),ISNUMBER(SEARCH("PSA 9.5",$B4038)),ISNUMBER(SEARCH("PSA 9",$B4038))),"TIER 3",IF(AND($D4038>20,N($E4038)>=15),"TIER 1","—")))) -> — | I4038: =IF($B4038="","",IF($D4038>=100,"Premium $100+ (auto)",IF(OR(ISNUMBER(SEARCH("PSA 10",$B4038)),ISNUMBER(SEARCH("PSA 9.5",$B4038)),ISNUMBER(SEARCH("PSA 9",$B4038))),"Graded PSA 9+ (auto)",IF(AND($D4038>20,N($E4038)>=15),"Hot: $20+ & "&$E4038&"/day",IF($D4038>20,"$20+ — needs velocity check","Below thresholds"))))) -> Below thresholds | J4038: =IF($B4038="","",IF(AND($D4038>20,$D4038<100,NOT(OR(ISNUMBER(SEARCH("PSA 10",$B4038)),ISNUMBER(SEARCH("PSA 9.5",$B4038)),ISNUMBER(SEARCH("PSA 9",$B4038)))),$E4038=""),"YES — pull CardHedger",""))
A4039: 227311465997 | B4039: 2025-26 Topps Finest Isaiah Collier #162 Uncommon Geometric Refractor Jazz | C4039: RB-0007-00022-09016 | D4039: 4 | F4039: =IF($B4039="","",IF(ISNUMBER(SEARCH("PSA",$B4039)),"Yes","No")) -> No | G4039: =IF($B4039="","",IF(ISNUMBER(SEARCH("PSA 10",$B4039)),10,IF(ISNUMBER(SEARCH("PSA 9.5",$B4039)),9.5,IF(ISNUMBER(SEARCH("PSA 9",$B4039)),9,IF(ISNUMBER(SEARCH("PSA 8",$B4039)),8,IF(ISNUMBER(SEARCH("PSA",$B4039)),"<9","")))))) | H4039: =IF($B4039="","",IF($D4039>=100,"TIER 2",IF(OR(ISNUMBER(SEARCH("PSA 10",$B4039)),ISNUMBER(SEARCH("PSA 9.5",$B4039)),ISNUMBER(SEARCH("PSA 9",$B4039))),"TIER 3",IF(AND($D4039>20,N($E4039)>=15),"TIER 1","—")))) -> — | I4039: =IF($B4039="","",IF($D4039>=100,"Premium $100+ (auto)",IF(OR(ISNUMBER(SEARCH("PSA 10",$B4039)),ISNUMBER(SEARCH("PSA 9.5",$B4039)),ISNUMBER(SEARCH("PSA 9",$B4039))),"Graded PSA 9+ (auto)",IF(AND($D4039>20,N($E4039)>=15),"Hot: $20+ & "&$E4039&"/day",IF($D4039>20,"$20+ — needs velocity check","Below thresholds"))))) -> Below thresholds | J4039: =IF($B4039="","",IF(AND($D4039>20,$D4039<100,NOT(OR(ISNUMBER(SEARCH("PSA 10",$B4039)),ISNUMBER(SEARCH("PSA 9.5",$B4039)),ISNUMBER(SEARCH("PSA 9",$B4039)))),$E4039=""),"YES — pull CardHedger",""))
A4040: 227311466014 | B4040: 2025-26 Topps Finest Kel'el Ware #51 Common Oil Spill Refractor Heat | C4040: RB-0007-00013-96995 | D4040: 7.99 | F4040: =IF($B4040="","",IF(ISNUMBER(SEARCH("PSA",$B4040)),"Yes","No")) -> No | G4040: =IF($B4040="","",IF(ISNUMBER(SEARCH("PSA 10",$B4040)),10,IF(ISNUMBER(SEARCH("PSA 9.5",$B4040)),9.5,IF(ISNUMBER(SEARCH("PSA 9",$B4040)),9,IF(ISNUMBER(SEARCH("PSA 8",$B4040)),8,IF(ISNUMBER(SEARCH("PSA",$B4040)),"<9","")))))) | H4040: =IF($B4040="","",IF($D4040>=100,"TIER 2",IF(OR(ISNUMBER(SEARCH("PSA 10",$B4040)),ISNUMBER(SEARCH("PSA 9.5",$B4040)),ISNUMBER(SEARCH("PSA 9",$B4040))),"TIER 3",IF(AND($D4040>20,N($E4040)>=15),"TIER 1","—")))) -> — | I4040: =IF($B4040="","",IF($D4040>=100,"Premium $100+ (auto)",IF(OR(ISNUMBER(SEARCH("PSA 10",$B4040)),ISNUMBER(SEARCH("PSA 9.5",$B4040)),ISNUMBER(SEARCH("PSA 9",$B4040))),"Graded PSA 9+ (auto)",IF(AND($D4040>20,N($E4040)>=15),"Hot: $20+ & "&$E4040&"/day",IF($D4040>20,"$20+ — needs velocity check","Below thresholds"))))) -> Below thresholds | J4040: =IF($B4040="","",IF(AND($D4040>20,$D4040<100,NOT(OR(ISNUMBER(SEARCH("PSA 10",$B4040)),ISNUMBER(SEARCH("PSA 9.5",$B4040)),ISNUMBER(SEARCH("PSA 9",$B4040)))),$E4040=""),"YES — pull CardHedger",""))
A4041: 227311466043 | B4041: 2025-26 Topps Finest Ray Allen #200 Uncommon Supersonics | C4041: RB-0007-00017-69839 | D4041: 4 | F4041: =IF($B4041="","",IF(ISNUMBER(SEARCH("PSA",$B4041)),"Yes","No")) -> No | G4041: =IF($B4041="","",IF(ISNUMBER(SEARCH("PSA 10",$B4041)),10,IF(ISNUMBER(SEARCH("PSA 9.5",$B4041)),9.5,IF(ISNUMBER(SEARCH("PSA 9",$B4041)),9,IF(ISNUMBER(SEARCH("PSA 8",$B4041)),8,IF(ISNUMBER(SEARCH("PSA",$B4041)),"<9","")))))) | H4041: =IF($B4041="","",IF($D4041>=100,"TIER 2",IF(OR(ISNUMBER(SEARCH("PSA 10",$B4041)),ISNUMBER(SEARCH("PSA 9.5",$B4041)),ISNUMBER(SEARCH("PSA 9",$B4041))),"TIER 3",IF(AND($D4041>20,N($E4041)>=15),"TIER 1","—")))) -> — | I4041: =IF($B4041="","",IF($D4041>=100,"Premium $100+ (auto)",IF(OR(ISNUMBER(SEARCH("PSA 10",$B4041)),ISNUMBER(SEARCH("PSA 9.5",$B4041)),ISNUMBER(SEARCH("PSA 9",$B4041))),"Graded PSA 9+ (auto)",IF(AND($D4041>20,N($E4041)>=15),"Hot: $20+ & "&$E4041&"/day",IF($D4041>20,"$20+ — needs velocity check","Below thresholds"))))) -> Below thresholds | J4041: =IF($B4041="","",IF(AND($D4041>20,$D4041<100,NOT(OR(ISNUMBER(SEARCH("PSA 10",$B4041)),ISNUMBER(SEARCH("PSA 9.5",$B4041)),ISNUMBER(SEARCH("PSA 9",$B4041)))),$E4041=""),"YES — pull CardHedger",""))
A4042: 227311466044 | B4042: 2025-26 Topps Finest Paul Pierce #M-14 Muse Refractor Celtics | C4042: RB-0007-00023-63320 | D4042: 5 | F4042: =IF($B4042="","",IF(ISNUMBER(SEARCH("PSA",$B4042)),"Yes","No")) -> No | G4042: =IF($B4042="","",IF(ISNUMBER(SEARCH("PSA 10",$B4042)),10,IF(ISNUMBER(SEARCH("PSA 9.5",$B4042)),9.5,IF(ISNUMBER(SEARCH("PSA 9",$B4042)),9,IF(ISNUMBER(SEARCH("PSA 8",$B4042)),8,IF(ISNUMBER(SEARCH("PSA",$B4042)),"<9","")))))) | H4042: =IF($B4042="","",IF($D4042>=100,"TIER 2",IF(OR(ISNUMBER(SEARCH("PSA 10",$B4042)),ISNUMBER(SEARCH("PSA 9.5",$B4042)),ISNUMBER(SEARCH("PSA 9",$B4042))),"TIER 3",IF(AND($D4042>20,N($E4042)>=15),"TIER 1","—")))) -> — | I4042: =IF($B4042="","",IF($D4042>=100,"Premium $100+ (auto)",IF(OR(ISNUMBER(SEARCH("PSA 10",$B4042)),ISNUMBER(SEARCH("PSA 9.5",$B4042)),ISNUMBER(SEARCH("PSA 9",$B4042))),"Graded PSA 9+ (auto)",IF(AND($D4042>20,N($E4042)>=15),"Hot: $20+ & "&$E4042&"/day",IF($D4042>20,"$20+ — needs velocity check","Below thresholds"))))) -> Below thresholds | J4042: =IF($B4042="","",IF(AND($D4042>20,$D4042<100,NOT(OR(ISNUMBER(SEARCH("PSA 10",$B4042)),ISNUMBER(SEARCH("PSA 9.5",$B4042)),ISNUMBER(SEARCH("PSA 9",$B4042)))),$E4042=""),"YES — pull CardHedger",""))
A4043: 227311466047 | B4043: 2025-26 Topps Finest Walter Clayton Jr. #18 Common RC Jazz | C4043: RB-0007-00012-77822 | D4043: 1 | F4043: =IF($B4043="","",IF(ISNUMBER(SEARCH("PSA",$B4043)),"Yes","No")) -> No | G4043: =IF($B4043="","",IF(ISNUMBER(SEARCH("PSA 10",$B4043)),10,IF(ISNUMBER(SEARCH("PSA 9.5",$B4043)),9.5,IF(ISNUMBER(SEARCH("PSA 9",$B4043)),9,IF(ISNUMBER(SEARCH("PSA 8",$B4043)),8,IF(ISNUMBER(SEARCH("PSA",$B4043)),"<9","")))))) | H4043: =IF($B4043="","",IF($D4043>=100,"TIER 2",IF(OR(ISNUMBER(SEARCH("PSA 10",$B4043)),ISNUMBER(SEARCH("PSA 9.5",$B4043)),ISNUMBER(SEARCH("PSA 9",$B4043))),"TIER 3",IF(AND($D4043>20,N($E4043)>=15),"TIER 1","—")))) -> — | I4043: =IF($B4043="","",IF($D4043>=100,"Premium $100+ (auto)",IF(OR(ISNUMBER(SEARCH("PSA 10",$B4043)),ISNUMBER(SEARCH("PSA 9.5",$B4043)),ISNUMBER(SEARCH("PSA 9",$B4043))),"Graded PSA 9+ (auto)",IF(AND($D4043>20,N($E4043)>=15),"Hot: $20+ & "&$E4043&"/day",IF($D4043>20,"$20+ — needs velocity check","Below thresholds"))))) -> Below thresholds | J4043: =IF($B4043="","",IF(AND($D4043>20,$D4043<100,NOT(OR(ISNUMBER(SEARCH("PSA 10",$B4043)),ISNUMBER(SEARCH("PSA 9.5",$B4043)),ISNUMBER(SEARCH("PSA 9",$B4043)))),$E4043=""),"YES — pull CardHedger",""))
A4044: 227311466060 | B4044: 2025-26 Topps Finest Nique Clifford #113 Uncommon RC Kings | C4044: RB-0007-00014-14672 | D4044: 3 | F4044: =IF($B4044="","",IF(ISNUMBER(SEARCH("PSA",$B4044)),"Yes","No")) -> No | G4044: =IF($B4044="","",IF(ISNUMBER(SEARCH("PSA 10",$B4044)),10,IF(ISNUMBER(SEARCH("PSA 9.5",$B4044)),9.5,IF(ISNUMBER(SEARCH("PSA 9",$B4044)),9,IF(ISNUMBER(SEARCH("PSA 8",$B4044)),8,IF(ISNUMBER(SEARCH("PSA",$B4044)),"<9","")))))) | H4044: =IF($B4044="","",IF($D4044>=100,"TIER 2",IF(OR(ISNUMBER(SEARCH("PSA 10",$B4044)),ISNUMBER(SEARCH("PSA 9.5",$B4044)),ISNUMBER(SEARCH("PSA 9",$B4044))),"TIER 3",IF(AND($D4044>20,N($E4044)>=15),"TIER 1","—")))) -> — | I4044: =IF($B4044="","",IF($D4044>=100,"Premium $100+ (auto)",IF(OR(ISNUMBER(SEARCH("PSA 10",$B4044)),ISNUMBER(SEARCH("PSA 9.5",$B4044)),ISNUMBER(SEARCH("PSA 9",$B4044))),"Graded PSA 9+ (auto)",IF(AND($D4044>20,N($E4044)>=15),"Hot: $20+ & "&$E4044&"/day",IF($D4044>20,"$20+ — needs velocity check","Below thresholds"))))) -> Below thresholds | J4044: =IF($B4044="","",IF(AND($D4044>20,$D4044<100,NOT(OR(ISNUMBER(SEARCH("PSA 10",$B4044)),ISNUMBER(SEARCH("PSA 9.5",$B4044)),ISNUMBER(SEARCH("PSA 9",$B4044)))),$E4044=""),"YES — pull CardHedger",""))
A4045: 227311466074 | B4045: 2025-26 Topps Finest Thomas Sorber #F-15 First RC Thunder | C4045: RB-0007-00010-48800 | D4045: 1.99 | F4045: =IF($B4045="","",IF(ISNUMBER(SEARCH("PSA",$B4045)),"Yes","No")) -> No | G4045: =IF($B4045="","",IF(ISNUMBER(SEARCH("PSA 10",$B4045)),10,IF(ISNUMBER(SEARCH("PSA 9.5",$B4045)),9.5,IF(ISNUMBER(SEARCH("PSA 9",$B4045)),9,IF(ISNUMBER(SEARCH("PSA 8",$B4045)),8,IF(ISNUMBER(SEARCH("PSA",$B4045)),"<9","")))))) | H4045: =IF($B4045="","",IF($D4045>=100,"TIER 2",IF(OR(ISNUMBER(SEARCH("PSA 10",$B4045)),ISNUMBER(SEARCH("PSA 9.5",$B4045)),ISNUMBER(SEARCH("PSA 9",$B4045))),"TIER 3",IF(AND($D4045>20,N($E4045)>=15),"TIER 1","—")))) -> — | I4045: =IF($B4045="","",IF($D4045>=100,"Premium $100+ (auto)",IF(OR(ISNUMBER(SEARCH("PSA 10",$B4045)),ISNUMBER(SEARCH("PSA 9.5",$B4045)),ISNUMBER(SEARCH("PSA 9",$B4045))),"Graded PSA 9+ (auto)",IF(AND($D4045>20,N($E4045)>=15),"Hot: $20+ & "&$E4045&"/day",IF($D4045>20,"$20+ — needs velocity check","Below thresholds"))))) -> Below thresholds | J4045: =IF($B4045="","",IF(AND($D4045>20,$D4045<100,NOT(OR(ISNUMBER(SEARCH("PSA 10",$B4045)),ISNUMBER(SEARCH("PSA 9.5",$B4045)),ISNUMBER(SEARCH("PSA 9",$B4045)))),$E4045=""),"YES — pull CardHedger",""))
A4046: 227311466078 | B4046: 2025-26 Topps Finest Kawhi Leonard #77 Common Oil Spill Refractor Clippers | C4046: RB-0007-00003-06246 | D4046: 1.99 | F4046: =IF($B4046="","",IF(ISNUMBER(SEARCH("PSA",$B4046)),"Yes","No")) -> No | G4046: =IF($B4046="","",IF(ISNUMBER(SEARCH("PSA 10",$B4046)),10,IF(ISNUMBER(SEARCH("PSA 9.5",$B4046)),9.5,IF(ISNUMBER(SEARCH("PSA 9",$B4046)),9,IF(ISNUMBER(SEARCH("PSA 8",$B4046)),8,IF(ISNUMBER(SEARCH("PSA",$B4046)),"<9","")))))) | H4046: =IF($B4046="","",IF($D4046>=100,"TIER 2",IF(OR(ISNUMBER(SEARCH("PSA 10",$B4046)),ISNUMBER(SEARCH("PSA 9.5",$B4046)),ISNUMBER(SEARCH("PSA 9",$B4046))),"TIER 3",IF(AND($D4046>20,N($E4046)>=15),"TIER 1","—")))) -> — | I4046: =IF($B4046="","",IF($D4046>=100,"Premium $100+ (auto)",IF(OR(ISNUMBER(SEARCH("PSA 10",$B4046)),ISNUMBER(SEARCH("PSA 9.5",$B4046)),ISNUMBER(SEARCH("PSA 9",$B4046))),"Graded PSA 9+ (auto)",IF(AND($D4046>20,N($E4046)>=15),"Hot: $20+ & "&$E4046&"/day",IF($D4046>20,"$20+ — needs velocity check","Below thresholds"))))) -> Below thresholds | J4046: =IF($B4046="","",IF(AND($D4046>20,$D4046<100,NOT(OR(ISNUMBER(SEARCH("PSA 10",$B4046)),ISNUMBER(SEARCH("PSA 9.5",$B4046)),ISNUMBER(SEARCH("PSA 9",$B4046)))),$E4046=""),"YES — pull CardHedger",""))
... A4114: 227317101667 | B4114: 2025 Panini Donruss Omarion Hampton #303 Optic Rated Rookie Preview Red Wave RC | C4114: DREAMRP-0001-00021-22968 | D4114: 1.99 | F4114: =IF($B4114="","",IF(ISNUMBER(SEARCH("PSA",$B4114)),"Yes","No")) -> No | G4114: =IF($B4114="","",IF(ISNUMBER(SEARCH("PSA 10",$B4114)),10,IF(ISNUMBER(SEARCH("PSA 9.5",$B4114)),9.5,IF(ISNUMBER(SEARCH("PSA 9",$B4114)),9,IF(ISNUMBER(SEARCH("PSA 8",$B4114)),8,IF(ISNUMBER(SEARCH("PSA",$B4114)),"<9","")))))) | H4114: =IF($B4114="","",IF($D4114>=100,"TIER 2",IF(OR(ISNUMBER(SEARCH("PSA 10",$B4114)),ISNUMBER(SEARCH("PSA 9.5",$B4114)),ISNUMBER(SEARCH("PSA 9",$B4114))),"TIER 3",IF(AND($D4114>20,N($E4114)>=15),"TIER 1","—")))) -> — | I4114: =IF($B4114="","",IF($D4114>=100,"Premium $100+ (auto)",IF(OR(ISNUMBER(SEARCH("PSA 10",$B4114)),ISNUMBER(SEARCH("PSA 9.5",$B4114)),ISNUMBER(SEARCH("PSA 9",$B4114))),"Graded PSA 9+ (auto)",IF(AND($D4114>20,N($E4114)>=15),"Hot: $20+ & "&$E4114&"/day",IF($D4114>20,"$20+ — needs velocity check","Below thresholds"))))) -> Below thresholds | J4114: =IF($B4114="","",IF(AND($D4114>20,$D4114<100,NOT(OR(ISNUMBER(SEARCH("PSA 10",$B4114)),ISNUMBER(SEARCH("PSA 9.5",$B4114)),ISNUMBER(SEARCH("PSA 9",$B4114)))),$E4114=""),"YES — pull CardHedger",""))
A4115: 227317129603 | B4115: Dave Winfield RC 1974 Topps #456 PSA 7 NM | D4115: 150 | F4115: =IF($B4115="","",IF(ISNUMBER(SEARCH("PSA",$B4115)),"Yes","No")) -> Yes | G4115: =IF($B4115="","",IF(ISNUMBER(SEARCH("PSA 10",$B4115)),10,IF(ISNUMBER(SEARCH("PSA 9.5",$B4115)),9.5,IF(ISNUMBER(SEARCH("PSA 9",$B4115)),9,IF(ISNUMBER(SEARCH("PSA 8",$B4115)),8,IF(ISNUMBER(SEARCH("PSA",$B4115)),"<9","")))))) -> <9 | H4115: =IF($B4115="","",IF($D4115>=100,"TIER 2",IF(OR(ISNUMBER(SEARCH("PSA 10",$B4115)),ISNUMBER(SEARCH("PSA 9.5",$B4115)),ISNUMBER(SEARCH("PSA 9",$B4115))),"TIER 3",IF(AND($D4115>20,N($E4115)>=15),"TIER 1","—")))) -> TIER 2 | I4115: =IF($B4115="","",IF($D4115>=100,"Premium $100+ (auto)",IF(OR(ISNUMBER(SEARCH("PSA 10",$B4115)),ISNUMBER(SEARCH("PSA 9.5",$B4115)),ISNUMBER(SEARCH("PSA 9",$B4115))),"Graded PSA 9+ (auto)",IF(AND($D4115>20,N($E4115)>=15),"Hot: $20+ & "&$E4115&"/day",IF($D4115>20,"$20+ — needs velocity check","Below thresholds"))))) -> Premium $100+ (auto) | J4115: =IF($B4115="","",IF(AND($D4115>20,$D4115<100,NOT(OR(ISNUMBER(SEARCH("PSA 10",$B4115)),ISNUMBER(SEARCH("PSA 9.5",$B4115)),ISNUMBER(SEARCH("PSA 9",$B4115)))),$E4115=""),"YES — pull CardHedger",""))
A4116: 227318949277 | B4116: 2024 Topps Triple Threads Nolan Ryan #25 Amber 46/199 Angels | C4116: DREAMRP-0001-00003-04829 | D4116: 8 | F4116: =IF($B4116="","",IF(ISNUMBER(SEARCH("PSA",$B4116)),"Yes","No")) -> No | G4116: =IF($B4116="","",IF(ISNUMBER(SEARCH("PSA 10",$B4116)),10,IF(ISNUMBER(SEARCH("PSA 9.5",$B4116)),9.5,IF(ISNUMBER(SEARCH("PSA 9",$B4116)),9,IF(ISNUMBER(SEARCH("PSA 8",$B4116)),8,IF(ISNUMBER(SEARCH("PSA",$B4116)),"<9","")))))) | H4116: =IF($B4116="","",IF($D4116>=100,"TIER 2",IF(OR(ISNUMBER(SEARCH("PSA 10",$B4116)),ISNUMBER(SEARCH("PSA 9.5",$B4116)),ISNUMBER(SEARCH("PSA 9",$B4116))),"TIER 3",IF(AND($D4116>20,N($E4116)>=15),"TIER 1","—")))) -> — | I4116: =IF($B4116="","",IF($D4116>=100,"Premium $100+ (auto)",IF(OR(ISNUMBER(SEARCH("PSA 10",$B4116)),ISNUMBER(SEARCH("PSA 9.5",$B4116)),ISNUMBER(SEARCH("PSA 9",$B4116))),"Graded PSA 9+ (auto)",IF(AND($D4116>20,N($E4116)>=15),"Hot: $20+ & "&$E4116&"/day",IF($D4116>20,"$20+ — needs velocity check","Below thresholds"))))) -> Below thresholds | J4116: =IF($B4116="","",IF(AND($D4116>20,$D4116<100,NOT(OR(ISNUMBER(SEARCH("PSA 10",$B4116)),ISNUMBER(SEARCH("PSA 9.5",$B4116)),ISNUMBER(SEARCH("PSA 9",$B4116)))),$E4116=""),"YES — pull CardHedger",""))
A4117: 227318949287 | B4117: 2021 Panini National Treasures Cade Cunningham #RMR-CCM Rookie MEM /99 MEM RC | C4117: DREAMRP-0001-00002-36681 | D4117: 199 | F4117: =IF($B4117="","",IF(ISNUMBER(SEARCH("PSA",$B4117)),"Yes","No")) -> No | G4117: =IF($B4117="","",IF(ISNUMBER(SEARCH("PSA 10",$B4117)),10,IF(ISNUMBER(SEARCH("PSA 9.5",$B4117)),9.5,IF(ISNUMBER(SEARCH("PSA 9",$B4117)),9,IF(ISNUMBER(SEARCH("PSA 8",$B4117)),8,IF(ISNUMBER(SEARCH("PSA",$B4117)),"<9","")))))) | H4117: =IF($B4117="","",IF($D4117>=100,"TIER 2",IF(OR(ISNUMBER(SEARCH("PSA 10",$B4117)),ISNUMBER(SEARCH("PSA 9.5",$B4117)),ISNUMBER(SEARCH("PSA 9",$B4117))),"TIER 3",IF(AND($D4117>20,N($E4117)>=15),"TIER 1","—")))) -> TIER 2 | I4117: =IF($B4117="","",IF($D4117>=100,"Premium $100+ (auto)",IF(OR(ISNUMBER(SEARCH("PSA 10",$B4117)),ISNUMBER(SEARCH("PSA 9.5",$B4117)),ISNUMBER(SEARCH("PSA 9",$B4117))),"Graded PSA 9+ (auto)",IF(AND($D4117>20,N($E4117)>=15),"Hot: $20+ & "&$E4117&"/day",IF($D4117>20,"$20+ — needs velocity check","Below thresholds"))))) -> Premium $100+ (auto) | J4117: =IF($B4117="","",IF(AND($D4117>20,$D4117<100,NOT(OR(ISNUMBER(SEARCH("PSA 10",$B4117)),ISNUMBER(SEARCH("PSA 9.5",$B4117)),ISNUMBER(SEARCH("PSA 9",$B4117)))),$E4117=""),"YES — pull CardHedger",""))
A4118: 227318949343 | B4118: 2024 Panini Immaculate Collection Nick Van Exel #2 2023-24 Virtuoso Auto /99 | C4118: DREAMRP-0001-00001-21829 | D4118: 34 | F4118: =IF($B4118="","",IF(ISNUMBER(SEARCH("PSA",$B4118)),"Yes","No")) -> No | G4118: =IF($B4118="","",IF(ISNUMBER(SEARCH("PSA 10",$B4118)),10,IF(ISNUMBER(SEARCH("PSA 9.5",$B4118)),9.5,IF(ISNUMBER(SEARCH("PSA 9",$B4118)),9,IF(ISNUMBER(SEARCH("PSA 8",$B4118)),8,IF(ISNUMBER(SEARCH("PSA",$B4118)),"<9","")))))) | H4118: =IF($B4118="","",IF($D4118>=100,"TIER 2",IF(OR(ISNUMBER(SEARCH("PSA 10",$B4118)),ISNUMBER(SEARCH("PSA 9.5",$B4118)),ISNUMBER(SEARCH("PSA 9",$B4118))),"TIER 3",IF(AND($D4118>20,N($E4118)>=15),"TIER 1","—")))) -> — | I4118: =IF($B4118="","",IF($D4118>=100,"Premium $100+ (auto)",IF(OR(ISNUMBER(SEARCH("PSA 10",$B4118)),ISNUMBER(SEARCH("PSA 9.5",$B4118)),ISNUMBER(SEARCH("PSA 9",$B4118))),"Graded PSA 9+ (auto)",IF(AND($D4118>20,N($E4118)>=15),"Hot: $20+ & "&$E4118&"/day",IF($D4118>20,"$20+ — needs velocity check","Below thresholds"))))) -> $20+ — needs velocity check | J4118: =IF($B4118="","",IF(AND($D4118>20,$D4118<100,NOT(OR(ISNUMBER(SEARCH("PSA 10",$B4118)),ISNUMBER(SEARCH("PSA 9.5",$B4118)),ISNUMBER(SEARCH("PSA 9",$B4118)))),$E4118=""),"YES — pull CardHedger","")) -> YES — pull CardHedger
A4119: 227319141536 | B4119: 2025-26 Bowman Alijah Martin #BCV-40 Chrome RC Raptors | C4119: Chromebox-0001-00016-66075 | D4119: 1.5 | F4119: =IF($B4119="","",IF(ISNUMBER(SEARCH("PSA",$B4119)),"Yes","No")) -> No | G4119: =IF($B4119="","",IF(ISNUMBER(SEARCH("PSA 10",$B4119)),10,IF(ISNUMBER(SEARCH("PSA 9.5",$B4119)),9.5,IF(ISNUMBER(SEARCH("PSA 9",$B4119)),9,IF(ISNUMBER(SEARCH("PSA 8",$B4119)),8,IF(ISNUMBER(SEARCH("PSA",$B4119)),"<9","")))))) | H4119: =IF($B4119="","",IF($D4119>=100,"TIER 2",IF(OR(ISNUMBER(SEARCH("PSA 10",$B4119)),ISNUMBER(SEARCH("PSA 9.5",$B4119)),ISNUMBER(SEARCH("PSA 9",$B4119))),"TIER 3",IF(AND($D4119>20,N($E4119)>=15),"TIER 1","—")))) -> — | I4119: =IF($B4119="","",IF($D4119>=100,"Premium $100+ (auto)",IF(OR(ISNUMBER(SEARCH("PSA 10",$B4119)),ISNUMBER(SEARCH("PSA 9.5",$B4119)),ISNUMBER(SEARCH("PSA 9",$B4119))),"Graded PSA 9+ (auto)",IF(AND($D4119>20,N($E4119)>=15),"Hot: $20+ & "&$E4119&"/day",IF($D4119>20,"$20+ — needs velocity check","Below thresholds"))))) -> Below thresholds | J4119: =IF($B4119="","",IF(AND($D4119>20,$D4119<100,NOT(OR(ISNUMBER(SEARCH("PSA 10",$B4119)),ISNUMBER(SEARCH("PSA 9.5",$B4119)),ISNUMBER(SEARCH("PSA 9",$B4119)))),$E4119=""),"YES — pull CardHedger",""))
A4120: 227319141546 | B4120: 2025-26 Bowman Emilee Skinner #BCP-85 Chrome 1st Prospect Blue Devils | C4120: Chromebox-0001-00017-51428 | D4120: 1.5 | F4120: =IF($B4120="","",IF(ISNUMBER(SEARCH("PSA",$B4120)),"Yes","No")) -> No | G4120: =IF($B4120="","",IF(ISNUMBER(SEARCH("PSA 10",$B4120)),10,IF(ISNUMBER(SEARCH("PSA 9.5",$B4120)),9.5,IF(ISNUMBER(SEARCH("PSA 9",$B4120)),9,IF(ISNUMBER(SEARCH("PSA 8",$B4120)),8,IF(ISNUMBER(SEARCH("PSA",$B4120)),"<9","")))))) | H4120: =IF($B4120="","",IF($D4120>=100,"TIER 2",IF(OR(ISNUMBER(SEARCH("PSA 10",$B4120)),ISNUMBER(SEARCH("PSA 9.5",$B4120)),ISNUMBER(SEARCH("PSA 9",$B4120))),"TIER 3",IF(AND($D4120>20,N($E4120)>=15),"TIER 1","—")))) -> — | I4120: =IF($B4120="","",IF($D4120>=100,"Premium $100+ (auto)",IF(OR(ISNUMBER(SEARCH("PSA 10",$B4120)),ISNUMBER(SEARCH("PSA 9.5",$B4120)),ISNUMBER(SEARCH("PSA 9",$B4120))),"Graded PSA 9+ (auto)",IF(AND($D4120>20,N($E4120)>=15),"Hot: $20+ & "&$E4120&"/day",IF($D4120>20,"$20+ — needs velocity check","Below thresholds"))))) -> Below thresholds | J4120: =IF($B4120="","",IF(AND($D4120>20,$D4120<100,NOT(OR(ISNUMBER(SEARCH("PSA 10",$B4120)),ISNUMBER(SEARCH("PSA 9.5",$B4120)),ISNUMBER(SEARCH("PSA 9",$B4120)))),$E4120=""),"YES — pull CardHedger",""))
A4121: 227319141569 | B4121: 2025-26 Bowman Ace Flagg #BCP-91 Chrome Reptilian Refractor 1st Prospect Bears | C4121: Chromebox-0001-00001-14880 | D4121: 5.99 | F4121: =IF($B4121="","",IF(ISNUMBER(SEARCH("PSA",$B4121)),"Yes","No")) -> No | G4121: =IF($B4121="","",IF(ISNUMBER(SEARCH("PSA 10",$B4121)),10,IF(ISNUMBER(SEARCH("PSA 9.5",$B4121)),9.5,IF(ISNUMBER(SEARCH("PSA 9",$B4121)),9,IF(ISNUMBER(SEARCH("PSA 8",$B4121)),8,IF(ISNUMBER(SEARCH("PSA",$B4121)),"<9","")))))) | H4121: =IF($B4121="","",IF($D4121>=100,"TIER 2",IF(OR(ISNUMBER(SEARCH("PSA 10",$B4121)),ISNUMBER(SEARCH("PSA 9.5",$B4121)),ISNUMBER(SEARCH("PSA 9",$B4121))),"TIER 3",IF(AND($D4121>20,N($E4121)>=15),"TIER 1","—")))) -> — | I4121: =IF($B4121="","",IF($D4121>=100,"Premium $100+ (auto)",IF(OR(ISNUMBER(SEARCH("PSA 10",$B4121)),ISNUMBER(SEARCH("PSA 9.5",$B4121)),ISNUMBER(SEARCH("PSA 9",$B4121))),"Graded PSA 9+ (auto)",IF(AND($D4121>20,N($E4121)>=15),"Hot: $20+ & "&$E4121&"/day",IF($D4121>20,"$20+ — needs velocity check","Below thresholds"))))) -> Below thresholds | J4121: =IF($B4121="","",IF(AND($D4121>20,$D4121<100,NOT(OR(ISNUMBER(SEARCH("PSA 10",$B4121)),ISNUMBER(SEARCH("PSA 9.5",$B4121)),ISNUMBER(SEARCH("PSA 9",$B4121)))),$E4121=""),"YES — pull CardHedger",""))
A4122: 227319141589 | B4122: 2025-26 Bowman Ryan Kalkbrenner #BCV-34 Chrome RC Hornets | C4122: Chromebox-0001-00003-52786 | D4122: 2.99 | F4122: =IF($B4122="","",IF(ISNUMBER(SEARCH("PSA",$B4122)),"Yes","No")) -> No | G4122: =IF($B4122="","",IF(ISNUMBER(SEARCH("PSA 10",$B4122)),10,IF(ISNUMBER(SEARCH("PSA 9.5",$B4122)),9.5,IF(ISNUMBER(SEARCH("PSA 9",$B4122)),9,IF(ISNUMBER(SEARCH("PSA 8",$B4122)),8,IF(ISNUMBER(SEARCH("PSA",$B4122)),"<9","")))))) | H4122: =IF($B4122="","",IF($D4122>=100,"TIER 2",IF(OR(ISNUMBER(SEARCH("PSA 10",$B4122)),ISNUMBER(SEARCH("PSA 9.5",$B4122)),ISNUMBER(SEARCH("PSA 9",$B4122))),"TIER 3",IF(AND($D4122>20,N($E4122)>=15),"TIER 1","—")))) -> — | I4122: =IF($B4122="","",IF($D4122>=100,"Premium $100+ (auto)",IF(OR(ISNUMBER(SEARCH("PSA 10",$B4122)),ISNUMBER(SEARCH("PSA 9.5",$B4122)),ISNUMBER(SEARCH("PSA 9",$B4122))),"Graded PSA 9+ (auto)",IF(AND($D4122>20,N($E4122)>=15),"Hot: $20+ & "&$E4122&"/day",IF($D4122>20,"$20+ — needs velocity check","Below thresholds"))))) -> Below thresholds | J4122: =IF($B4122="","",IF(AND($D4122>20,$D4122<100,NOT(OR(ISNUMBER(SEARCH("PSA 10",$B4122)),ISNUMBER(SEARCH("PSA 9.5",$B4122)),ISNUMBER(SEARCH("PSA 9",$B4122)))),$E4122=""),"YES — pull CardHedger",""))
A4123: 227319141654 | B4123: 2025-26 Bowman Tyrese Maxey #BCV-66 Chrome 76ers | C4123: Chromebox-0001-00019-81084 | D4123: 2.99 | F4123: =IF($B4123="","",IF(ISNUMBER(SEARCH("PSA",$B4123)),"Yes","No")) -> No | G4123: =IF($B4123="","",IF(ISNUMBER(SEARCH("PSA 10",$B4123)),10,IF(ISNUMBER(SEARCH("PSA 9.5",$B4123)),9.5,IF(ISNUMBER(SEARCH("PSA 9",$B4123)),9,IF(ISNUMBER(SEARCH("PSA 8",$B4123)),8,IF(ISNUMBER(SEARCH("PSA",$B4123)),"<9","")))))) | H4123: =IF($B4123="","",IF($D4123>=100,"TIER 2",IF(OR(ISNUMBER(SEARCH("PSA 10",$B4123)),ISNUMBER(SEARCH("PSA 9.5",$B4123)),ISNUMBER(SEARCH("PSA 9",$B4123))),"TIER 3",IF(AND($D4123>20,N($E4123)>=15),"TIER 1","—")))) -> — | I4123: =IF($B4123="","",IF($D4123>=100,"Premium $100+ (auto)",IF(OR(ISNUMBER(SEARCH("PSA 10",$B4123)),ISNUMBER(SEARCH("PSA 9.5",$B4123)),ISNUMBER(SEARCH("PSA 9",$B4123))),"Graded PSA 9+ (auto)",IF(AND($D4123>20,N($E4123)>=15),"Hot: $20+ & "&$E4123&"/day",IF($D4123>20,"$20+ — needs velocity check","Below thresholds"))))) -> Below thresholds | J4123: =IF($B4123="","",IF(AND($D4123>20,$D4123<100,NOT(OR(ISNUMBER(SEARCH("PSA 10",$B4123)),ISNUMBER(SEARCH("PSA 9.5",$B4123)),ISNUMBER(SEARCH("PSA 9",$B4123)))),$E4123=""),"YES — pull CardHedger",""))
A4124: 227319141679 | B4124: 2025-26 Bowman Caleb Wilson #BCP-83 Chrome 1st Prospect Tar Heels | C4124: Chromebox-0001-00002-60219 | D4124: 4.49 | F4124: =IF($B4124="","",IF(ISNUMBER(SEARCH("PSA",$B4124)),"Yes","No")) -> No | G4124: =IF($B4124="","",IF(ISNUMBER(SEARCH("PSA 10",$B4124)),10,IF(ISNUMBER(SEARCH("PSA 9.5",$B4124)),9.5,IF(ISNUMBER(SEARCH("PSA 9",$B4124)),9,IF(ISNUMBER(SEARCH("PSA 8",$B4124)),8,IF(ISNUMBER(SEARCH("PSA",$B4124)),"<9","")))))) | H4124: =IF($B4124="","",IF($D4124>=100,"TIER 2",IF(OR(ISNUMBER(SEARCH("PSA 10",$B4124)),ISNUMBER(SEARCH("PSA 9.5",$B4124)),ISNUMBER(SEARCH("PSA 9",$B4124))),"TIER 3",IF(AND($D4124>20,N($E4124)>=15),"TIER 1","—")))) -> — | I4124: =IF($B4124="","",IF($D4124>=100,"Premium $100+ (auto)",IF(OR(ISNUMBER(SEARCH("PSA 10",$B4124)),ISNUMBER(SEARCH("PSA 9.5",$B4124)),ISNUMBER(SEARCH("PSA 9",$B4124))),"Graded PSA 9+ (auto)",IF(AND($D4124>20,N($E4124)>=15),"Hot: $20+ & "&$E4124&"/day",IF($D4124>20,"$20+ — needs velocity check","Below thresholds"))))) -> Below thresholds | J4124: =IF($B4124="","",IF(AND($D4124>20,$D4124<100,NOT(OR(ISNUMBER(SEARCH("PSA 10",$B4124)),ISNUMBER(SEARCH("PSA 9.5",$B4124)),ISNUMBER(SEARCH("PSA 9",$B4124)))),$E4124=""),"YES — pull CardHedger",""))
A4125: 227319141711 | B4125: 2025-26 Bowman Nick Martinelli #BCP-62 Chrome 1st Prospect Wildcats | C4125: Chromebox-0001-00008-80129 | D4125: 1.25 | F4125: =IF($B4125="","",IF(ISNUMBER(SEARCH("PSA",$B4125)),"Yes","No")) -> No | G4125: =IF($B4125="","",IF(ISNUMBER(SEARCH("PSA 10",$B4125)),10,IF(ISNUMBER(SEARCH("PSA 9.5",$B4125)),9.5,IF(ISNUMBER(SEARCH("PSA 9",$B4125)),9,IF(ISNUMBER(SEARCH("PSA 8",$B4125)),8,IF(ISNUMBER(SEARCH("PSA",$B4125)),"<9","")))))) | H4125: =IF($B4125="","",IF($D4125>=100,"TIER 2",IF(OR(ISNUMBER(SEARCH("PSA 10",$B4125)),ISNUMBER(SEARCH("PSA 9.5",$B4125)),ISNUMBER(SEARCH("PSA 9",$B4125))),"TIER 3",IF(AND($D4125>20,N($E4125)>=15),"TIER 1","—")))) -> — | I4125: =IF($B4125="","",IF($D4125>=100,"Premium $100+ (auto)",IF(OR(ISNUMBER(SEARCH("PSA 10",$B4125)),ISNUMBER(SEARCH("PSA 9.5",$B4125)),ISNUMBER(SEARCH("PSA 9",$B4125))),"Graded PSA 9+ (auto)",IF(AND($D4125>20,N($E4125)>=15),"Hot: $20+ & "&$E4125&"/day",IF($D4125>20,"$20+ — needs velocity check","Below thresholds"))))) -> Below thresholds | J4125: =IF($B4125="","",IF(AND($D4125>20,$D4125<100,NOT(OR(ISNUMBER(SEARCH("PSA 10",$B4125)),ISNUMBER(SEARCH("PSA 9.5",$B4125)),ISNUMBER(SEARCH("PSA 9",$B4125)))),$E4125=""),"YES — pull CardHedger",""))
A4126: 227319141760 | B4126: 2025-26 Bowman Jared McCain #BCV-65 Chrome Reptilian Refractor 76ers | C4126: Chromebox-0001-00011-70215 | D4126: 2.5 | F4126: =IF($B4126="","",IF(ISNUMBER(SEARCH("PSA",$B4126)),"Yes","No")) -> No | G4126: =IF($B4126="","",IF(ISNUMBER(SEARCH("PSA 10",$B4126)),10,IF(ISNUMBER(SEARCH("PSA 9.5",$B4126)),9.5,IF(ISNUMBER(SEARCH("PSA 9",$B4126)),9,IF(ISNUMBER(SEARCH("PSA 8",$B4126)),8,IF(ISNUMBER(SEARCH("PSA",$B4126)),"<9","")))))) | H4126: =IF($B4126="","",IF($D4126>=100,"TIER 2",IF(OR(ISNUMBER(SEARCH("PSA 10",$B4126)),ISNUMBER(SEARCH("PSA 9.5",$B4126)),ISNUMBER(SEARCH("PSA 9",$B4126))),"TIER 3",IF(AND($D4126>20,N($E4126)>=15),"TIER 1","—")))) -> — | I4126: =IF($B4126="","",IF($D4126>=100,"Premium $100+ (auto)",IF(OR(ISNUMBER(SEARCH("PSA 10",$B4126)),ISNUMBER(SEARCH("PSA 9.5",$B4126)),ISNUMBER(SEARCH("PSA 9",$B4126))),"Graded PSA 9+ (auto)",IF(AND($D4126>20,N($E4126)>=15),"Hot: $20+ & "&$E4126&"/day",IF($D4126>20,"$20+ — needs velocity check","Below thresholds"))))) -> Below thresholds | J4126: =IF($B4126="","",IF(AND($D4126>20,$D4126<100,NOT(OR(ISNUMBER(SEARCH("PSA 10",$B4126)),ISNUMBER(SEARCH("PSA 9.5",$B4126)),ISNUMBER(SEARCH("PSA 9",$B4126)))),$E4126=""),"YES — pull CardHedger",""))
A4127: 227319141787 | B4127: 2025-26 Bowman Alexandra Eschmeyer #BCP-75 Chrome 1st Prospect Cardinal | C4127: Chromebox-0001-00005-56793 | D4127: 1.25 | F4127: =IF($B4127="","",IF(ISNUMBER(SEARCH("PSA",$B4127)),"Yes","No")) -> No | G4127: =IF($B4127="","",IF(ISNUMBER(SEARCH("PSA 10",$B4127)),10,IF(ISNUMBER(SEARCH("PSA 9.5",$B4127)),9.5,IF(ISNUMBER(SEARCH("PSA 9",$B4127)),9,IF(ISNUMBER(SEARCH("PSA 8",$B4127)),8,IF(ISNUMBER(SEARCH("PSA",$B4127)),"<9","")))))) | H4127: =IF($B4127="","",IF($D4127>=100,"TIER 2",IF(OR(ISNUMBER(SEARCH("PSA 10",$B4127)),ISNUMBER(SEARCH("PSA 9.5",$B4127)),ISNUMBER(SEARCH("PSA 9",$B4127))),"TIER 3",IF(AND($D4127>20,N($E4127)>=15),"TIER 1","—")))) -> — | I4127: =IF($B4127="","",IF($D4127>=100,"Premium $100+ (auto)",IF(OR(ISNUMBER(SEARCH("PSA 10",$B4127)),ISNUMBER(SEARCH("PSA 9.5",$B4127)),ISNUMBER(SEARCH("PSA 9",$B4127))),"Graded PSA 9+ (auto)",IF(AND($D4127>20,N($E4127)>=15),"Hot: $20+ & "&$E4127&"/day",IF($D4127>20,"$20+ — needs velocity check","Below thresholds"))))) -> Below thresholds | J4127: =IF($B4127="","",IF(AND($D4127>20,$D4127<100,NOT(OR(ISNUMBER(SEARCH("PSA 10",$B4127)),ISNUMBER(SEARCH("PSA 9.5",$B4127)),ISNUMBER(SEARCH("PSA 9",$B4127)))),$E4127=""),"YES — pull CardHedger",""))
... A4176: 227319250025 | B4176: 2019 Bowman Kyle Tucker #94 RC Astros | C4176: Ebayrefresh-0002-00033-48324 | D4176: 1.99 | F4176: =IF($B4176="","",IF(ISNUMBER(SEARCH("PSA",$B4176)),"Yes","No")) -> No | G4176: =IF($B4176="","",IF(ISNUMBER(SEARCH("PSA 10",$B4176)),10,IF(ISNUMBER(SEARCH("PSA 9.5",$B4176)),9.5,IF(ISNUMBER(SEARCH("PSA 9",$B4176)),9,IF(ISNUMBER(SEARCH("PSA 8",$B4176)),8,IF(ISNUMBER(SEARCH("PSA",$B4176)),"<9","")))))) | H4176: =IF($B4176="","",IF($D4176>=100,"TIER 2",IF(OR(ISNUMBER(SEARCH("PSA 10",$B4176)),ISNUMBER(SEARCH("PSA 9.5",$B4176)),ISNUMBER(SEARCH("PSA 9",$B4176))),"TIER 3",IF(AND($D4176>20,N($E4176)>=15),"TIER 1","—")))) -> — | I4176: =IF($B4176="","",IF($D4176>=100,"Premium $100+ (auto)",IF(OR(ISNUMBER(SEARCH("PSA 10",$B4176)),ISNUMBER(SEARCH("PSA 9.5",$B4176)),ISNUMBER(SEARCH("PSA 9",$B4176))),"Graded PSA 9+ (auto)",IF(AND($D4176>20,N($E4176)>=15),"Hot: $20+ & "&$E4176&"/day",IF($D4176>20,"$20+ — needs velocity check","Below thresholds"))))) -> Below thresholds | J4176: =IF($B4176="","",IF(AND($D4176>20,$D4176<100,NOT(OR(ISNUMBER(SEARCH("PSA 10",$B4176)),ISNUMBER(SEARCH("PSA 9.5",$B4176)),ISNUMBER(SEARCH("PSA 9",$B4176)))),$E4176=""),"YES — pull CardHedger",""))
A4177: 227319291347 | B4177: 2022 Panini Prizm - Illumination Mike Trout #IL-10 Blue Mojo Prizm /199 Angels | D4177: 36 | F4177: =IF($B4177="","",IF(ISNUMBER(SEARCH("PSA",$B4177)),"Yes","No")) -> No | G4177: =IF($B4177="","",IF(ISNUMBER(SEARCH("PSA 10",$B4177)),10,IF(ISNUMBER(SEARCH("PSA 9.5",$B4177)),9.5,IF(ISNUMBER(SEARCH("PSA 9",$B4177)),9,IF(ISNUMBER(SEARCH("PSA 8",$B4177)),8,IF(ISNUMBER(SEARCH("PSA",$B4177)),"<9","")))))) | H4177: =IF($B4177="","",IF($D4177>=100,"TIER 2",IF(OR(ISNUMBER(SEARCH("PSA 10",$B4177)),ISNUMBER(SEARCH("PSA 9.5",$B4177)),ISNUMBER(SEARCH("PSA 9",$B4177))),"TIER 3",IF(AND($D4177>20,N($E4177)>=15),"TIER 1","—")))) -> — | I4177: =IF($B4177="","",IF($D4177>=100,"Premium $100+ (auto)",IF(OR(ISNUMBER(SEARCH("PSA 10",$B4177)),ISNUMBER(SEARCH("PSA 9.5",$B4177)),ISNUMBER(SEARCH("PSA 9",$B4177))),"Graded PSA 9+ (auto)",IF(AND($D4177>20,N($E4177)>=15),"Hot: $20+ & "&$E4177&"/day",IF($D4177>20,"$20+ — needs velocity check","Below thresholds"))))) -> $20+ — needs velocity check | J4177: =IF($B4177="","",IF(AND($D4177>20,$D4177<100,NOT(OR(ISNUMBER(SEARCH("PSA 10",$B4177)),ISNUMBER(SEARCH("PSA 9.5",$B4177)),ISNUMBER(SEARCH("PSA 9",$B4177)))),$E4177=""),"YES — pull CardHedger","")) -> YES — pull CardHedger
A4178: 227319343555 | B4178: 2025-26 Topps Chrome Cooper Flagg #251 RC Mavericks ROTY!! | C4178: BBA-000001-00001-92910 | D4178: 30 | F4178: =IF($B4178="","",IF(ISNUMBER(SEARCH("PSA",$B4178)),"Yes","No")) -> No | G4178: =IF($B4178="","",IF(ISNUMBER(SEARCH("PSA 10",$B4178)),10,IF(ISNUMBER(SEARCH("PSA 9.5",$B4178)),9.5,IF(ISNUMBER(SEARCH("PSA 9",$B4178)),9,IF(ISNUMBER(SEARCH("PSA 8",$B4178)),8,IF(ISNUMBER(SEARCH("PSA",$B4178)),"<9","")))))) | H4178: =IF($B4178="","",IF($D4178>=100,"TIER 2",IF(OR(ISNUMBER(SEARCH("PSA 10",$B4178)),ISNUMBER(SEARCH("PSA 9.5",$B4178)),ISNUMBER(SEARCH("PSA 9",$B4178))),"TIER 3",IF(AND($D4178>20,N($E4178)>=15),"TIER 1","—")))) -> — | I4178: =IF($B4178="","",IF($D4178>=100,"Premium $100+ (auto)",IF(OR(ISNUMBER(SEARCH("PSA 10",$B4178)),ISNUMBER(SEARCH("PSA 9.5",$B4178)),ISNUMBER(SEARCH("PSA 9",$B4178))),"Graded PSA 9+ (auto)",IF(AND($D4178>20,N($E4178)>=15),"Hot: $20+ & "&$E4178&"/day",IF($D4178>20,"$20+ — needs velocity check","Below thresholds"))))) -> $20+ — needs velocity check | J4178: =IF($B4178="","",IF(AND($D4178>20,$D4178<100,NOT(OR(ISNUMBER(SEARCH("PSA 10",$B4178)),ISNUMBER(SEARCH("PSA 9.5",$B4178)),ISNUMBER(SEARCH("PSA 9",$B4178)))),$E4178=""),"YES — pull CardHedger","")) -> YES — pull CardHedger
A4179: 227321059154 | B4179: 2025 Topps Chrome McDonald's All-American Jordan Speiser #75 Purple /150 | C4179: KKSC-0001-00014-42870 | D4179: 6.35 | F4179: =IF($B4179="","",IF(ISNUMBER(SEARCH("PSA",$B4179)),"Yes","No")) -> No | G4179: =IF($B4179="","",IF(ISNUMBER(SEARCH("PSA 10",$B4179)),10,IF(ISNUMBER(SEARCH("PSA 9.5",$B4179)),9.5,IF(ISNUMBER(SEARCH("PSA 9",$B4179)),9,IF(ISNUMBER(SEARCH("PSA 8",$B4179)),8,IF(ISNUMBER(SEARCH("PSA",$B4179)),"<9","")))))) | H4179: =IF($B4179="","",IF($D4179>=100,"TIER 2",IF(OR(ISNUMBER(SEARCH("PSA 10",$B4179)),ISNUMBER(SEARCH("PSA 9.5",$B4179)),ISNUMBER(SEARCH("PSA 9",$B4179))),"TIER 3",IF(AND($D4179>20,N($E4179)>=15),"TIER 1","—")))) -> — | I4179: =IF($B4179="","",IF($D4179>=100,"Premium $100+ (auto)",IF(OR(ISNUMBER(SEARCH("PSA 10",$B4179)),ISNUMBER(SEARCH("PSA 9.5",$B4179)),ISNUMBER(SEARCH("PSA 9",$B4179))),"Graded PSA 9+ (auto)",IF(AND($D4179>20,N($E4179)>=15),"Hot: $20+ & "&$E4179&"/day",IF($D4179>20,"$20+ — needs velocity check","Below thresholds"))))) -> Below thresholds | J4179: =IF($B4179="","",IF(AND($D4179>20,$D4179<100,NOT(OR(ISNUMBER(SEARCH("PSA 10",$B4179)),ISNUMBER(SEARCH("PSA 9.5",$B4179)),ISNUMBER(SEARCH("PSA 9",$B4179)))),$E4179=""),"YES — pull CardHedger",""))
A4180: 227321059169 | B4180: 2025 Topps Chrome McDonald's All-American Chris Cenac Jr. #11 Aqua Wave /199 | C4180: KKSC-0001-00005-89064 | D4180: 4.99 | F4180: =IF($B4180="","",IF(ISNUMBER(SEARCH("PSA",$B4180)),"Yes","No")) -> No | G4180: =IF($B4180="","",IF(ISNUMBER(SEARCH("PSA 10",$B4180)),10,IF(ISNUMBER(SEARCH("PSA 9.5",$B4180)),9.5,IF(ISNUMBER(SEARCH("PSA 9",$B4180)),9,IF(ISNUMBER(SEARCH("PSA 8",$B4180)),8,IF(ISNUMBER(SEARCH("PSA",$B4180)),"<9","")))))) | H4180: =IF($B4180="","",IF($D4180>=100,"TIER 2",IF(OR(ISNUMBER(SEARCH("PSA 10",$B4180)),ISNUMBER(SEARCH("PSA 9.5",$B4180)),ISNUMBER(SEARCH("PSA 9",$B4180))),"TIER 3",IF(AND($D4180>20,N($E4180)>=15),"TIER 1","—")))) -> — | I4180: =IF($B4180="","",IF($D4180>=100,"Premium $100+ (auto)",IF(OR(ISNUMBER(SEARCH("PSA 10",$B4180)),ISNUMBER(SEARCH("PSA 9.5",$B4180)),ISNUMBER(SEARCH("PSA 9",$B4180))),"Graded PSA 9+ (auto)",IF(AND($D4180>20,N($E4180)>=15),"Hot: $20+ & "&$E4180&"/day",IF($D4180>20,"$20+ — needs velocity check","Below thresholds"))))) -> Below thresholds | J4180: =IF($B4180="","",IF(AND($D4180>20,$D4180<100,NOT(OR(ISNUMBER(SEARCH("PSA 10",$B4180)),ISNUMBER(SEARCH("PSA 9.5",$B4180)),ISNUMBER(SEARCH("PSA 9",$B4180)))),$E4180=""),"YES — pull CardHedger",""))
A4181: 227321059283 | B4181: 2025 Upper Deck Series 1 Jeremy Lauzon #93 Clear Cut Predators | C4181: KKSC-0001-00007-65226 | D4181: 1.5 | F4181: =IF($B4181="","",IF(ISNUMBER(SEARCH("PSA",$B4181)),"Yes","No")) -> No | G4181: =IF($B4181="","",IF(ISNUMBER(SEARCH("PSA 10",$B4181)),10,IF(ISNUMBER(SEARCH("PSA 9.5",$B4181)),9.5,IF(ISNUMBER(SEARCH("PSA 9",$B4181)),9,IF(ISNUMBER(SEARCH("PSA 8",$B4181)),8,IF(ISNUMBER(SEARCH("PSA",$B4181)),"<9","")))))) | H4181: =IF($B4181="","",IF($D4181>=100,"TIER 2",IF(OR(ISNUMBER(SEARCH("PSA 10",$B4181)),ISNUMBER(SEARCH("PSA 9.5",$B4181)),ISNUMBER(SEARCH("PSA 9",$B4181))),"TIER 3",IF(AND($D4181>20,N($E4181)>=15),"TIER 1","—")))) -> — | I4181: =IF($B4181="","",IF($D4181>=100,"Premium $100+ (auto)",IF(OR(ISNUMBER(SEARCH("PSA 10",$B4181)),ISNUMBER(SEARCH("PSA 9.5",$B4181)),ISNUMBER(SEARCH("PSA 9",$B4181))),"Graded PSA 9+ (auto)",IF(AND($D4181>20,N($E4181)>=15),"Hot: $20+ & "&$E4181&"/day",IF($D4181>20,"$20+ — needs velocity check","Below thresholds"))))) -> Below thresholds | J4181: =IF($B4181="","",IF(AND($D4181>20,$D4181<100,NOT(OR(ISNUMBER(SEARCH("PSA 10",$B4181)),ISNUMBER(SEARCH("PSA 9.5",$B4181)),ISNUMBER(SEARCH("PSA 9",$B4181)))),$E4181=""),"YES — pull CardHedger",""))
A4182: 227321059384 | B4182: 2025 Topps Chrome McDonald's All-American Zai Harwell #5 Aqua Wave /199 | C4182: KKSC-0001-00011-75904 | D4182: 3.99 | F4182: =IF($B4182="","",IF(ISNUMBER(SEARCH("PSA",$B4182)),"Yes","No")) -> No | G4182: =IF($B4182="","",IF(ISNUMBER(SEARCH("PSA 10",$B4182)),10,IF(ISNUMBER(SEARCH("PSA 9.5",$B4182)),9.5,IF(ISNUMBER(SEARCH("PSA 9",$B4182)),9,IF(ISNUMBER(SEARCH("PSA 8",$B4182)),8,IF(ISNUMBER(SEARCH("PSA",$B4182)),"<9","")))))) | H4182: =IF($B4182="","",IF($D4182>=100,"TIER 2",IF(OR(ISNUMBER(SEARCH("PSA 10",$B4182)),ISNUMBER(SEARCH("PSA 9.5",$B4182)),ISNUMBER(SEARCH("PSA 9",$B4182))),"TIER 3",IF(AND($D4182>20,N($E4182)>=15),"TIER 1","—")))) -> — | I4182: =IF($B4182="","",IF($D4182>=100,"Premium $100+ (auto)",IF(OR(ISNUMBER(SEARCH("PSA 10",$B4182)),ISNUMBER(SEARCH("PSA 9.5",$B4182)),ISNUMBER(SEARCH("PSA 9",$B4182))),"Graded PSA 9+ (auto)",IF(AND($D4182>20,N($E4182)>=15),"Hot: $20+ & "&$E4182&"/day",IF($D4182>20,"$20+ — needs velocity check","Below thresholds"))))) -> Below thresholds | J4182: =IF($B4182="","",IF(AND($D4182>20,$D4182<100,NOT(OR(ISNUMBER(SEARCH("PSA 10",$B4182)),ISNUMBER(SEARCH("PSA 9.5",$B4182)),ISNUMBER(SEARCH("PSA 9",$B4182)))),$E4182=""),"YES — pull CardHedger",""))
A4183: 227321059473 | B4183: 2025 Topps Chrome McDonald's All-American Eric Reibe #44 Aqua Wave Ref /199 | C4183: KKSC-0001-00004-62290 | D4183: 1 | F4183: =IF($B4183="","",IF(ISNUMBER(SEARCH("PSA",$B4183)),"Yes","No")) -> No | G4183: =IF($B4183="","",IF(ISNUMBER(SEARCH("PSA 10",$B4183)),10,IF(ISNUMBER(SEARCH("PSA 9.5",$B4183)),9.5,IF(ISNUMBER(SEARCH("PSA 9",$B4183)),9,IF(ISNUMBER(SEARCH("PSA 8",$B4183)),8,IF(ISNUMBER(SEARCH("PSA",$B4183)),"<9","")))))) | H4183: =IF($B4183="","",IF($D4183>=100,"TIER 2",IF(OR(ISNUMBER(SEARCH("PSA 10",$B4183)),ISNUMBER(SEARCH("PSA 9.5",$B4183)),ISNUMBER(SEARCH("PSA 9",$B4183))),"TIER 3",IF(AND($D4183>20,N($E4183)>=15),"TIER 1","—")))) -> — | I4183: =IF($B4183="","",IF($D4183>=100,"Premium $100+ (auto)",IF(OR(ISNUMBER(SEARCH("PSA 10",$B4183)),ISNUMBER(SEARCH("PSA 9.5",$B4183)),ISNUMBER(SEARCH("PSA 9",$B4183))),"Graded PSA 9+ (auto)",IF(AND($D4183>20,N($E4183)>=15),"Hot: $20+ & "&$E4183&"/day",IF($D4183>20,"$20+ — needs velocity check","Below thresholds"))))) -> Below thresholds | J4183: =IF($B4183="","",IF(AND($D4183>20,$D4183<100,NOT(OR(ISNUMBER(SEARCH("PSA 10",$B4183)),ISNUMBER(SEARCH("PSA 9.5",$B4183)),ISNUMBER(SEARCH("PSA 9",$B4183)))),$E4183=""),"YES — pull CardHedger",""))
A4184: 227321059575 | B4184: 2025 Topps Chrome McDonald's All-American Jaren Jackson Jr. #95 Logo Refractor | C4184: KKSC-0001-00012-03782 | D4184: 4.95 | F4184: =IF($B4184="","",IF(ISNUMBER(SEARCH("PSA",$B4184)),"Yes","No")) -> No | G4184: =IF($B4184="","",IF(ISNUMBER(SEARCH("PSA 10",$B4184)),10,IF(ISNUMBER(SEARCH("PSA 9.5",$B4184)),9.5,IF(ISNUMBER(SEARCH("PSA 9",$B4184)),9,IF(ISNUMBER(SEARCH("PSA 8",$B4184)),8,IF(ISNUMBER(SEARCH("PSA",$B4184)),"<9","")))))) | H4184: =IF($B4184="","",IF($D4184>=100,"TIER 2",IF(OR(ISNUMBER(SEARCH("PSA 10",$B4184)),ISNUMBER(SEARCH("PSA 9.5",$B4184)),ISNUMBER(SEARCH("PSA 9",$B4184))),"TIER 3",IF(AND($D4184>20,N($E4184)>=15),"TIER 1","—")))) -> — | I4184: =IF($B4184="","",IF($D4184>=100,"Premium $100+ (auto)",IF(OR(ISNUMBER(SEARCH("PSA 10",$B4184)),ISNUMBER(SEARCH("PSA 9.5",$B4184)),ISNUMBER(SEARCH("PSA 9",$B4184))),"Graded PSA 9+ (auto)",IF(AND($D4184>20,N($E4184)>=15),"Hot: $20+ & "&$E4184&"/day",IF($D4184>20,"$20+ — needs velocity check","Below thresholds"))))) -> Below thresholds | J4184: =IF($B4184="","",IF(AND($D4184>20,$D4184<100,NOT(OR(ISNUMBER(SEARCH("PSA 10",$B4184)),ISNUMBER(SEARCH("PSA 9.5",$B4184)),ISNUMBER(SEARCH("PSA 9",$B4184)))),$E4184=""),"YES — pull CardHedger",""))
A4185: 227321059606 | B4185: 2024-25 Upper Deck Allure Sergei Bobrovsky #PI-7 Protectors of the Ice Panthers | C4185: KKSC-0001-00006-81442 | D4185: 1.99 | F4185: =IF($B4185="","",IF(ISNUMBER(SEARCH("PSA",$B4185)),"Yes","No")) -> No | G4185: =IF($B4185="","",IF(ISNUMBER(SEARCH("PSA 10",$B4185)),10,IF(ISNUMBER(SEARCH("PSA 9.5",$B4185)),9.5,IF(ISNUMBER(SEARCH("PSA 9",$B4185)),9,IF(ISNUMBER(SEARCH("PSA 8",$B4185)),8,IF(ISNUMBER(SEARCH("PSA",$B4185)),"<9","")))))) | H4185: =IF($B4185="","",IF($D4185>=100,"TIER 2",IF(OR(ISNUMBER(SEARCH("PSA 10",$B4185)),ISNUMBER(SEARCH("PSA 9.5",$B4185)),ISNUMBER(SEARCH("PSA 9",$B4185))),"TIER 3",IF(AND($D4185>20,N($E4185)>=15),"TIER 1","—")))) -> — | I4185: =IF($B4185="","",IF($D4185>=100,"Premium $100+ (auto)",IF(OR(ISNUMBER(SEARCH("PSA 10",$B4185)),ISNUMBER(SEARCH("PSA 9.5",$B4185)),ISNUMBER(SEARCH("PSA 9",$B4185))),"Graded PSA 9+ (auto)",IF(AND($D4185>20,N($E4185)>=15),"Hot: $20+ & "&$E4185&"/day",IF($D4185>20,"$20+ — needs velocity check","Below thresholds"))))) -> Below thresholds | J4185: =IF($B4185="","",IF(AND($D4185>20,$D4185<100,NOT(OR(ISNUMBER(SEARCH("PSA 10",$B4185)),ISNUMBER(SEARCH("PSA 9.5",$B4185)),ISNUMBER(SEARCH("PSA 9",$B4185)))),$E4185=""),"YES — pull CardHedger",""))
A4186: 227321059662 | B4186: 2024-25 Upper Deck Allure Emil Lilleberg #116 RC Lightning | C4186: KKSC-0001-00009-69291 | D4186: 1.25 | F4186: =IF($B4186="","",IF(ISNUMBER(SEARCH("PSA",$B4186)),"Yes","No")) -> No | G4186: =IF($B4186="","",IF(ISNUMBER(SEARCH("PSA 10",$B4186)),10,IF(ISNUMBER(SEARCH("PSA 9.5",$B4186)),9.5,IF(ISNUMBER(SEARCH("PSA 9",$B4186)),9,IF(ISNUMBER(SEARCH("PSA 8",$B4186)),8,IF(ISNUMBER(SEARCH("PSA",$B4186)),"<9","")))))) | H4186: =IF($B4186="","",IF($D4186>=100,"TIER 2",IF(OR(ISNUMBER(SEARCH("PSA 10",$B4186)),ISNUMBER(SEARCH("PSA 9.5",$B4186)),ISNUMBER(SEARCH("PSA 9",$B4186))),"TIER 3",IF(AND($D4186>20,N($E4186)>=15),"TIER 1","—")))) -> — | I4186: =IF($B4186="","",IF($D4186>=100,"Premium $100+ (auto)",IF(OR(ISNUMBER(SEARCH("PSA 10",$B4186)),ISNUMBER(SEARCH("PSA 9.5",$B4186)),ISNUMBER(SEARCH("PSA 9",$B4186))),"Graded PSA 9+ (auto)",IF(AND($D4186>20,N($E4186)>=15),"Hot: $20+ & "&$E4186&"/day",IF($D4186>20,"$20+ — needs velocity check","Below thresholds"))))) -> Below thresholds | J4186: =IF($B4186="","",IF(AND($D4186>20,$D4186<100,NOT(OR(ISNUMBER(SEARCH("PSA 10",$B4186)),ISNUMBER(SEARCH("PSA 9.5",$B4186)),ISNUMBER(SEARCH("PSA 9",$B4186)))),$E4186=""),"YES — pull CardHedger",""))
A4187: 227321059667 | B4187: 2025 Topps Chrome McDonald's All-American Jaliya Davis #59 Aqua Wave Ref /199 | C4187: KKSC-0001-00002-58312 | D4187: 2 | F4187: =IF($B4187="","",IF(ISNUMBER(SEARCH("PSA",$B4187)),"Yes","No")) -> No | G4187: =IF($B4187="","",IF(ISNUMBER(SEARCH("PSA 10",$B4187)),10,IF(ISNUMBER(SEARCH("PSA 9.5",$B4187)),9.5,IF(ISNUMBER(SEARCH("PSA 9",$B4187)),9,IF(ISNUMBER(SEARCH("PSA 8",$B4187)),8,IF(ISNUMBER(SEARCH("PSA",$B4187)),"<9","")))))) | H4187: =IF($B4187="","",IF($D4187>=100,"TIER 2",IF(OR(ISNUMBER(SEARCH("PSA 10",$B4187)),ISNUMBER(SEARCH("PSA 9.5",$B4187)),ISNUMBER(SEARCH("PSA 9",$B4187))),"TIER 3",IF(AND($D4187>20,N($E4187)>=15),"TIER 1","—")))) -> — | I4187: =IF($B4187="","",IF($D4187>=100,"Premium $100+ (auto)",IF(OR(ISNUMBER(SEARCH("PSA 10",$B4187)),ISNUMBER(SEARCH("PSA 9.5",$B4187)),ISNUMBER(SEARCH("PSA 9",$B4187))),"Graded PSA 9+ (auto)",IF(AND($D4187>20,N($E4187)>=15),"Hot: $20+ & "&$E4187&"/day",IF($D4187>20,"$20+ — needs velocity check","Below thresholds"))))) -> Below thresholds | J4187: =IF($B4187="","",IF(AND($D4187>20,$D4187<100,NOT(OR(ISNUMBER(SEARCH("PSA 10",$B4187)),ISNUMBER(SEARCH("PSA 9.5",$B4187)),ISNUMBER(SEARCH("PSA 9",$B4187)))),$E4187=""),"YES — pull CardHedger",""))
A4188: 227321059725 | B4188: 2025 Panini Prizm Trey Amos #400 Orange 169/249 RC Commanders | C4188: KKSC-0001-00013-15723 | D4188: 3 | F4188: =IF($B4188="","",IF(ISNUMBER(SEARCH("PSA",$B4188)),"Yes","No")) -> No | G4188: =IF($B4188="","",IF(ISNUMBER(SEARCH("PSA 10",$B4188)),10,IF(ISNUMBER(SEARCH("PSA 9.5",$B4188)),9.5,IF(ISNUMBER(SEARCH("PSA 9",$B4188)),9,IF(ISNUMBER(SEARCH("PSA 8",$B4188)),8,IF(ISNUMBER(SEARCH("PSA",$B4188)),"<9","")))))) | H4188: =IF($B4188="","",IF($D4188>=100,"TIER 2",IF(OR(ISNUMBER(SEARCH("PSA 10",$B4188)),ISNUMBER(SEARCH("PSA 9.5",$B4188)),ISNUMBER(SEARCH("PSA 9",$B4188))),"TIER 3",IF(AND($D4188>20,N($E4188)>=15),"TIER 1","—")))) -> — | I4188: =IF($B4188="","",IF($D4188>=100,"Premium $100+ (auto)",IF(OR(ISNUMBER(SEARCH("PSA 10",$B4188)),ISNUMBER(SEARCH("PSA 9.5",$B4188)),ISNUMBER(SEARCH("PSA 9",$B4188))),"Graded PSA 9+ (auto)",IF(AND($D4188>20,N($E4188)>=15),"Hot: $20+ & "&$E4188&"/day",IF($D4188>20,"$20+ — needs velocity check","Below thresholds"))))) -> Below thresholds | J4188: =IF($B4188="","",IF(AND($D4188>20,$D4188<100,NOT(OR(ISNUMBER(SEARCH("PSA 10",$B4188)),ISNUMBER(SEARCH("PSA 9.5",$B4188)),ISNUMBER(SEARCH("PSA 9",$B4188)))),$E4188=""),"YES — pull CardHedger",""))
A4189: 227321059745 | B4189: 2024-25 Upper Deck Allure Marco Rossi #CFL-31 Color Flow Red-Orange Wild | C4189: KKSC-0001-00008-39136 | D4189: 1.99 | F4189: =IF($B4189="","",IF(ISNUMBER(SEARCH("PSA",$B4189)),"Yes","No")) -> No | G4189: =IF($B4189="","",IF(ISNUMBER(SEARCH("PSA 10",$B4189)),10,IF(ISNUMBER(SEARCH("PSA 9.5",$B4189)),9.5,IF(ISNUMBER(SEARCH("PSA 9",$B4189)),9,IF(ISNUMBER(SEARCH("PSA 8",$B4189)),8,IF(ISNUMBER(SEARCH("PSA",$B4189)),"<9","")))))) | H4189: =IF($B4189="","",IF($D4189>=100,"TIER 2",IF(OR(ISNUMBER(SEARCH("PSA 10",$B4189)),ISNUMBER(SEARCH("PSA 9.5",$B4189)),ISNUMBER(SEARCH("PSA 9",$B4189))),"TIER 3",IF(AND($D4189>20,N($E4189)>=15),"TIER 1","—")))) -> — | I4189: =IF($B4189="","",IF($D4189>=100,"Premium $100+ (auto)",IF(OR(ISNUMBER(SEARCH("PSA 10",$B4189)),ISNUMBER(SEARCH("PSA 9.5",$B4189)),ISNUMBER(SEARCH("PSA 9",$B4189))),"Graded PSA 9+ (auto)",IF(AND($D4189>20,N($E4189)>=15),"Hot: $20+ & "&$E4189&"/day",IF($D4189>20,"$20+ — needs velocity check","Below thresholds"))))) -> Below thresholds | J4189: =IF($B4189="","",IF(AND($D4189>20,$D4189<100,NOT(OR(ISNUMBER(SEARCH("PSA 10",$B4189)),ISNUMBER(SEARCH("PSA 9.5",$B4189)),ISNUMBER(SEARCH("PSA 9",$B4189)))),$E4189=""),"YES — pull CardHedger",""))
... A4421: 227345870380 | B4421: 2025-26 Topps Finest Ace Bailey #5 Common RC Jazz | C4421: RB-0007-00002-55169 | D4421: 1.5 | F4421: =IF($B4421="","",IF(ISNUMBER(SEARCH("PSA",$B4421)),"Yes","No")) -> No | G4421: =IF($B4421="","",IF(ISNUMBER(SEARCH("PSA 10",$B4421)),10,IF(ISNUMBER(SEARCH("PSA 9.5",$B4421)),9.5,IF(ISNUMBER(SEARCH("PSA 9",$B4421)),9,IF(ISNUMBER(SEARCH("PSA 8",$B4421)),8,IF(ISNUMBER(SEARCH("PSA",$B4421)),"<9","")))))) | H4421: =IF($B4421="","",IF($D4421>=100,"TIER 2",IF(OR(ISNUMBER(SEARCH("PSA 10",$B4421)),ISNUMBER(SEARCH("PSA 9.5",$B4421)),ISNUMBER(SEARCH("PSA 9",$B4421))),"TIER 3",IF(AND($D4421>20,N($E4421)>=15),"TIER 1","—")))) -> — | I4421: =IF($B4421="","",IF($D4421>=100,"Premium $100+ (auto)",IF(OR(ISNUMBER(SEARCH("PSA 10",$B4421)),ISNUMBER(SEARCH("PSA 9.5",$B4421)),ISNUMBER(SEARCH("PSA 9",$B4421))),"Graded PSA 9+ (auto)",IF(AND($D4421>20,N($E4421)>=15),"Hot: $20+ & "&$E4421&"/day",IF($D4421>20,"$20+ — needs velocity check","Below thresholds"))))) -> Below thresholds | J4421: =IF($B4421="","",IF(AND($D4421>20,$D4421<100,NOT(OR(ISNUMBER(SEARCH("PSA 10",$B4421)),ISNUMBER(SEARCH("PSA 9.5",$B4421)),ISNUMBER(SEARCH("PSA 9",$B4421)))),$E4421=""),"YES — pull CardHedger",""))
A4422: 227346782972 | B4422: 2024 Topps Black and White AARON JUDGE /49 Blue Parallel SP Yankees #7 PSA 10 | D4422: 225 | F4422: =IF($B4422="","",IF(ISNUMBER(SEARCH("PSA",$B4422)),"Yes","No")) -> Yes | G4422: =IF($B4422="","",IF(ISNUMBER(SEARCH("PSA 10",$B4422)),10,IF(ISNUMBER(SEARCH("PSA 9.5",$B4422)),9.5,IF(ISNUMBER(SEARCH("PSA 9",$B4422)),9,IF(ISNUMBER(SEARCH("PSA 8",$B4422)),8,IF(ISNUMBER(SEARCH("PSA",$B4422)),"<9","")))))) -> 10 | H4422: =IF($B4422="","",IF($D4422>=100,"TIER 2",IF(OR(ISNUMBER(SEARCH("PSA 10",$B4422)),ISNUMBER(SEARCH("PSA 9.5",$B4422)),ISNUMBER(SEARCH("PSA 9",$B4422))),"TIER 3",IF(AND($D4422>20,N($E4422)>=15),"TIER 1","—")))) -> TIER 2 | I4422: =IF($B4422="","",IF($D4422>=100,"Premium $100+ (auto)",IF(OR(ISNUMBER(SEARCH("PSA 10",$B4422)),ISNUMBER(SEARCH("PSA 9.5",$B4422)),ISNUMBER(SEARCH("PSA 9",$B4422))),"Graded PSA 9+ (auto)",IF(AND($D4422>20,N($E4422)>=15),"Hot: $20+ & "&$E4422&"/day",IF($D4422>20,"$20+ — needs velocity check","Below thresholds"))))) -> Premium $100+ (auto) | J4422: =IF($B4422="","",IF(AND($D4422>20,$D4422<100,NOT(OR(ISNUMBER(SEARCH("PSA 10",$B4422)),ISNUMBER(SEARCH("PSA 9.5",$B4422)),ISNUMBER(SEARCH("PSA 9",$B4422)))),$E4422=""),"YES — pull CardHedger",""))
A4423: 227346792685 | B4423: 2022 Topps Chrome Ronald Acuna Jr. PSA 9 Braves | D4423: 75 | F4423: =IF($B4423="","",IF(ISNUMBER(SEARCH("PSA",$B4423)),"Yes","No")) -> Yes | G4423: =IF($B4423="","",IF(ISNUMBER(SEARCH("PSA 10",$B4423)),10,IF(ISNUMBER(SEARCH("PSA 9.5",$B4423)),9.5,IF(ISNUMBER(SEARCH("PSA 9",$B4423)),9,IF(ISNUMBER(SEARCH("PSA 8",$B4423)),8,IF(ISNUMBER(SEARCH("PSA",$B4423)),"<9","")))))) -> 9 | H4423: =IF($B4423="","",IF($D4423>=100,"TIER 2",IF(OR(ISNUMBER(SEARCH("PSA 10",$B4423)),ISNUMBER(SEARCH("PSA 9.5",$B4423)),ISNUMBER(SEARCH("PSA 9",$B4423))),"TIER 3",IF(AND($D4423>20,N($E4423)>=15),"TIER 1","—")))) -> TIER 3 | I4423: =IF($B4423="","",IF($D4423>=100,"Premium $100+ (auto)",IF(OR(ISNUMBER(SEARCH("PSA 10",$B4423)),ISNUMBER(SEARCH("PSA 9.5",$B4423)),ISNUMBER(SEARCH("PSA 9",$B4423))),"Graded PSA 9+ (auto)",IF(AND($D4423>20,N($E4423)>=15),"Hot: $20+ & "&$E4423&"/day",IF($D4423>20,"$20+ — needs velocity check","Below thresholds"))))) -> Graded PSA 9+ (auto) | J4423: =IF($B4423="","",IF(AND($D4423>20,$D4423<100,NOT(OR(ISNUMBER(SEARCH("PSA 10",$B4423)),ISNUMBER(SEARCH("PSA 9.5",$B4423)),ISNUMBER(SEARCH("PSA 9",$B4423)))),$E4423=""),"YES — pull CardHedger",""))
A4424: 227352908116 | B4424: 2025 Bowman Chrome JOSUAR GONZALEZ #BCP-153 1st Prospect Giants | C4424: RBBB5-0001-00113-17495 | D4424: 3.25 | F4424: =IF($B4424="","",IF(ISNUMBER(SEARCH("PSA",$B4424)),"Yes","No")) -> No | G4424: =IF($B4424="","",IF(ISNUMBER(SEARCH("PSA 10",$B4424)),10,IF(ISNUMBER(SEARCH("PSA 9.5",$B4424)),9.5,IF(ISNUMBER(SEARCH("PSA 9",$B4424)),9,IF(ISNUMBER(SEARCH("PSA 8",$B4424)),8,IF(ISNUMBER(SEARCH("PSA",$B4424)),"<9","")))))) | H4424: =IF($B4424="","",IF($D4424>=100,"TIER 2",IF(OR(ISNUMBER(SEARCH("PSA 10",$B4424)),ISNUMBER(SEARCH("PSA 9.5",$B4424)),ISNUMBER(SEARCH("PSA 9",$B4424))),"TIER 3",IF(AND($D4424>20,N($E4424)>=15),"TIER 1","—")))) -> — | I4424: =IF($B4424="","",IF($D4424>=100,"Premium $100+ (auto)",IF(OR(ISNUMBER(SEARCH("PSA 10",$B4424)),ISNUMBER(SEARCH("PSA 9.5",$B4424)),ISNUMBER(SEARCH("PSA 9",$B4424))),"Graded PSA 9+ (auto)",IF(AND($D4424>20,N($E4424)>=15),"Hot: $20+ & "&$E4424&"/day",IF($D4424>20,"$20+ — needs velocity check","Below thresholds"))))) -> Below thresholds | J4424: =IF($B4424="","",IF(AND($D4424>20,$D4424<100,NOT(OR(ISNUMBER(SEARCH("PSA 10",$B4424)),ISNUMBER(SEARCH("PSA 9.5",$B4424)),ISNUMBER(SEARCH("PSA 9",$B4424)))),$E4424=""),"YES — pull CardHedger",""))
A4425: 227354649411 | B4425: 2025 Bowman Draft Sapphire BRADEN MONTGOMERY #BDC-18 Chrome White Sox | C4425: POOKIEWHT-0001-00008-19642 | D4425: 2 | F4425: =IF($B4425="","",IF(ISNUMBER(SEARCH("PSA",$B4425)),"Yes","No")) -> No | G4425: =IF($B4425="","",IF(ISNUMBER(SEARCH("PSA 10",$B4425)),10,IF(ISNUMBER(SEARCH("PSA 9.5",$B4425)),9.5,IF(ISNUMBER(SEARCH("PSA 9",$B4425)),9,IF(ISNUMBER(SEARCH("PSA 8",$B4425)),8,IF(ISNUMBER(SEARCH("PSA",$B4425)),"<9","")))))) | H4425: =IF($B4425="","",IF($D4425>=100,"TIER 2",IF(OR(ISNUMBER(SEARCH("PSA 10",$B4425)),ISNUMBER(SEARCH("PSA 9.5",$B4425)),ISNUMBER(SEARCH("PSA 9",$B4425))),"TIER 3",IF(AND($D4425>20,N($E4425)>=15),"TIER 1","—")))) -> — | I4425: =IF($B4425="","",IF($D4425>=100,"Premium $100+ (auto)",IF(OR(ISNUMBER(SEARCH("PSA 10",$B4425)),ISNUMBER(SEARCH("PSA 9.5",$B4425)),ISNUMBER(SEARCH("PSA 9",$B4425))),"Graded PSA 9+ (auto)",IF(AND($D4425>20,N($E4425)>=15),"Hot: $20+ & "&$E4425&"/day",IF($D4425>20,"$20+ — needs velocity check","Below thresholds"))))) -> Below thresholds | J4425: =IF($B4425="","",IF(AND($D4425>20,$D4425<100,NOT(OR(ISNUMBER(SEARCH("PSA 10",$B4425)),ISNUMBER(SEARCH("PSA 9.5",$B4425)),ISNUMBER(SEARCH("PSA 9",$B4425)))),$E4425=""),"YES — pull CardHedger",""))
A4426: 227354649435 | B4426: 2025 Bowman Draft Sapphire YOLFRAN CASTILLO #BDC-107 Chrome Rangers | C4426: POOKIEWHT-0001-00029-43928 | D4426: 2.5 | F4426: =IF($B4426="","",IF(ISNUMBER(SEARCH("PSA",$B4426)),"Yes","No")) -> No | G4426: =IF($B4426="","",IF(ISNUMBER(SEARCH("PSA 10",$B4426)),10,IF(ISNUMBER(SEARCH("PSA 9.5",$B4426)),9.5,IF(ISNUMBER(SEARCH("PSA 9",$B4426)),9,IF(ISNUMBER(SEARCH("PSA 8",$B4426)),8,IF(ISNUMBER(SEARCH("PSA",$B4426)),"<9","")))))) | H4426: =IF($B4426="","",IF($D4426>=100,"TIER 2",IF(OR(ISNUMBER(SEARCH("PSA 10",$B4426)),ISNUMBER(SEARCH("PSA 9.5",$B4426)),ISNUMBER(SEARCH("PSA 9",$B4426))),"TIER 3",IF(AND($D4426>20,N($E4426)>=15),"TIER 1","—")))) -> — | I4426: =IF($B4426="","",IF($D4426>=100,"Premium $100+ (auto)",IF(OR(ISNUMBER(SEARCH("PSA 10",$B4426)),ISNUMBER(SEARCH("PSA 9.5",$B4426)),ISNUMBER(SEARCH("PSA 9",$B4426))),"Graded PSA 9+ (auto)",IF(AND($D4426>20,N($E4426)>=15),"Hot: $20+ & "&$E4426&"/day",IF($D4426>20,"$20+ — needs velocity check","Below thresholds"))))) -> Below thresholds | J4426: =IF($B4426="","",IF(AND($D4426>20,$D4426<100,NOT(OR(ISNUMBER(SEARCH("PSA 10",$B4426)),ISNUMBER(SEARCH("PSA 9.5",$B4426)),ISNUMBER(SEARCH("PSA 9",$B4426)))),$E4426=""),"YES — pull CardHedger",""))
A4427: 227354649546 | B4427: 2025 Bowman Chrome DYLAN CREWS #3 Geometric Refractor /499 RC Nationals | C4427: POOKIEWHT-0001-00026-42273 | D4427: 5 | F4427: =IF($B4427="","",IF(ISNUMBER(SEARCH("PSA",$B4427)),"Yes","No")) -> No | G4427: =IF($B4427="","",IF(ISNUMBER(SEARCH("PSA 10",$B4427)),10,IF(ISNUMBER(SEARCH("PSA 9.5",$B4427)),9.5,IF(ISNUMBER(SEARCH("PSA 9",$B4427)),9,IF(ISNUMBER(SEARCH("PSA 8",$B4427)),8,IF(ISNUMBER(SEARCH("PSA",$B4427)),"<9","")))))) | H4427: =IF($B4427="","",IF($D4427>=100,"TIER 2",IF(OR(ISNUMBER(SEARCH("PSA 10",$B4427)),ISNUMBER(SEARCH("PSA 9.5",$B4427)),ISNUMBER(SEARCH("PSA 9",$B4427))),"TIER 3",IF(AND($D4427>20,N($E4427)>=15),"TIER 1","—")))) -> — | I4427: =IF($B4427="","",IF($D4427>=100,"Premium $100+ (auto)",IF(OR(ISNUMBER(SEARCH("PSA 10",$B4427)),ISNUMBER(SEARCH("PSA 9.5",$B4427)),ISNUMBER(SEARCH("PSA 9",$B4427))),"Graded PSA 9+ (auto)",IF(AND($D4427>20,N($E4427)>=15),"Hot: $20+ & "&$E4427&"/day",IF($D4427>20,"$20+ — needs velocity check","Below thresholds"))))) -> Below thresholds | J4427: =IF($B4427="","",IF(AND($D4427>20,$D4427<100,NOT(OR(ISNUMBER(SEARCH("PSA 10",$B4427)),ISNUMBER(SEARCH("PSA 9.5",$B4427)),ISNUMBER(SEARCH("PSA 9",$B4427)))),$E4427=""),"YES — pull CardHedger",""))
A4428: 227354649583 | B4428: 2025 Bowman Draft LANDON HODGE #BDC-93 Chrome Refractor 1st Prospect White Sox | C4428: POOKIEWHT-0001-00025-11521 | D4428: 1 | F4428: =IF($B4428="","",IF(ISNUMBER(SEARCH("PSA",$B4428)),"Yes","No")) -> No | G4428: =IF($B4428="","",IF(ISNUMBER(SEARCH("PSA 10",$B4428)),10,IF(ISNUMBER(SEARCH("PSA 9.5",$B4428)),9.5,IF(ISNUMBER(SEARCH("PSA 9",$B4428)),9,IF(ISNUMBER(SEARCH("PSA 8",$B4428)),8,IF(ISNUMBER(SEARCH("PSA",$B4428)),"<9","")))))) | H4428: =IF($B4428="","",IF($D4428>=100,"TIER 2",IF(OR(ISNUMBER(SEARCH("PSA 10",$B4428)),ISNUMBER(SEARCH("PSA 9.5",$B4428)),ISNUMBER(SEARCH("PSA 9",$B4428))),"TIER 3",IF(AND($D4428>20,N($E4428)>=15),"TIER 1","—")))) -> — | I4428: =IF($B4428="","",IF($D4428>=100,"Premium $100+ (auto)",IF(OR(ISNUMBER(SEARCH("PSA 10",$B4428)),ISNUMBER(SEARCH("PSA 9.5",$B4428)),ISNUMBER(SEARCH("PSA 9",$B4428))),"Graded PSA 9+ (auto)",IF(AND($D4428>20,N($E4428)>=15),"Hot: $20+ & "&$E4428&"/day",IF($D4428>20,"$20+ — needs velocity check","Below thresholds"))))) -> Below thresholds | J4428: =IF($B4428="","",IF(AND($D4428>20,$D4428<100,NOT(OR(ISNUMBER(SEARCH("PSA 10",$B4428)),ISNUMBER(SEARCH("PSA 9.5",$B4428)),ISNUMBER(SEARCH("PSA 9",$B4428)))),$E4428=""),"YES — pull CardHedger",""))
A4429: 227354649638 | B4429: 2025 Bowman Draft Sapphire JARED THOMAS #BDC-147 Chrome Rockies | C4429: POOKIEWHT-0001-00007-43100 | D4429: 3 | F4429: =IF($B4429="","",IF(ISNUMBER(SEARCH("PSA",$B4429)),"Yes","No")) -> No | G4429: =IF($B4429="","",IF(ISNUMBER(SEARCH("PSA 10",$B4429)),10,IF(ISNUMBER(SEARCH("PSA 9.5",$B4429)),9.5,IF(ISNUMBER(SEARCH("PSA 9",$B4429)),9,IF(ISNUMBER(SEARCH("PSA 8",$B4429)),8,IF(ISNUMBER(SEARCH("PSA",$B4429)),"<9","")))))) | H4429: =IF($B4429="","",IF($D4429>=100,"TIER 2",IF(OR(ISNUMBER(SEARCH("PSA 10",$B4429)),ISNUMBER(SEARCH("PSA 9.5",$B4429)),ISNUMBER(SEARCH("PSA 9",$B4429))),"TIER 3",IF(AND($D4429>20,N($E4429)>=15),"TIER 1","—")))) -> — | I4429: =IF($B4429="","",IF($D4429>=100,"Premium $100+ (auto)",IF(OR(ISNUMBER(SEARCH("PSA 10",$B4429)),ISNUMBER(SEARCH("PSA 9.5",$B4429)),ISNUMBER(SEARCH("PSA 9",$B4429))),"Graded PSA 9+ (auto)",IF(AND($D4429>20,N($E4429)>=15),"Hot: $20+ & "&$E4429&"/day",IF($D4429>20,"$20+ — needs velocity check","Below thresholds"))))) -> Below thresholds | J4429: =IF($B4429="","",IF(AND($D4429>20,$D4429<100,NOT(OR(ISNUMBER(SEARCH("PSA 10",$B4429)),ISNUMBER(SEARCH("PSA 9.5",$B4429)),ISNUMBER(SEARCH("PSA 9",$B4429)))),$E4429=""),"YES — pull CardHedger",""))
A4430: 227354649666 | B4430: 2025 Bowman Draft Sapphire DEAN MOSS #BDC-114 Chrome Rays | C4430: POOKIEWHT-0001-00009-30465 | D4430: 3 | F4430: =IF($B4430="","",IF(ISNUMBER(SEARCH("PSA",$B4430)),"Yes","No")) -> No | G4430: =IF($B4430="","",IF(ISNUMBER(SEARCH("PSA 10",$B4430)),10,IF(ISNUMBER(SEARCH("PSA 9.5",$B4430)),9.5,IF(ISNUMBER(SEARCH("PSA 9",$B4430)),9,IF(ISNUMBER(SEARCH("PSA 8",$B4430)),8,IF(ISNUMBER(SEARCH("PSA",$B4430)),"<9","")))))) | H4430: =IF($B4430="","",IF($D4430>=100,"TIER 2",IF(OR(ISNUMBER(SEARCH("PSA 10",$B4430)),ISNUMBER(SEARCH("PSA 9.5",$B4430)),ISNUMBER(SEARCH("PSA 9",$B4430))),"TIER 3",IF(AND($D4430>20,N($E4430)>=15),"TIER 1","—")))) -> — | I4430: =IF($B4430="","",IF($D4430>=100,"Premium $100+ (auto)",IF(OR(ISNUMBER(SEARCH("PSA 10",$B4430)),ISNUMBER(SEARCH("PSA 9.5",$B4430)),ISNUMBER(SEARCH("PSA 9",$B4430))),"Graded PSA 9+ (auto)",IF(AND($D4430>20,N($E4430)>=15),"Hot: $20+ & "&$E4430&"/day",IF($D4430>20,"$20+ — needs velocity check","Below thresholds"))))) -> Below thresholds | J4430: =IF($B4430="","",IF(AND($D4430>20,$D4430<100,NOT(OR(ISNUMBER(SEARCH("PSA 10",$B4430)),ISNUMBER(SEARCH("PSA 9.5",$B4430)),ISNUMBER(SEARCH("PSA 9",$B4430)))),$E4430=""),"YES — pull CardHedger",""))
A4431: 227354649733 | B4431: 2025 Bowman Draft Sapphire MICHAEL OLIVETO #BDC-156 Chrome 1st Prospect Tigers | C4431: POOKIEWHT-0001-00006-26635 | D4431: 5.5 | F4431: =IF($B4431="","",IF(ISNUMBER(SEARCH("PSA",$B4431)),"Yes","No")) -> No | G4431: =IF($B4431="","",IF(ISNUMBER(SEARCH("PSA 10",$B4431)),10,IF(ISNUMBER(SEARCH("PSA 9.5",$B4431)),9.5,IF(ISNUMBER(SEARCH("PSA 9",$B4431)),9,IF(ISNUMBER(SEARCH("PSA 8",$B4431)),8,IF(ISNUMBER(SEARCH("PSA",$B4431)),"<9","")))))) | H4431: =IF($B4431="","",IF($D4431>=100,"TIER 2",IF(OR(ISNUMBER(SEARCH("PSA 10",$B4431)),ISNUMBER(SEARCH("PSA 9.5",$B4431)),ISNUMBER(SEARCH("PSA 9",$B4431))),"TIER 3",IF(AND($D4431>20,N($E4431)>=15),"TIER 1","—")))) -> — | I4431: =IF($B4431="","",IF($D4431>=100,"Premium $100+ (auto)",IF(OR(ISNUMBER(SEARCH("PSA 10",$B4431)),ISNUMBER(SEARCH("PSA 9.5",$B4431)),ISNUMBER(SEARCH("PSA 9",$B4431))),"Graded PSA 9+ (auto)",IF(AND($D4431>20,N($E4431)>=15),"Hot: $20+ & "&$E4431&"/day",IF($D4431>20,"$20+ — needs velocity check","Below thresholds"))))) -> Below thresholds | J4431: =IF($B4431="","",IF(AND($D4431>20,$D4431<100,NOT(OR(ISNUMBER(SEARCH("PSA 10",$B4431)),ISNUMBER(SEARCH("PSA 9.5",$B4431)),ISNUMBER(SEARCH("PSA 9",$B4431)))),$E4431=""),"YES — pull CardHedger",""))
A4432: 227354649748 | B4432: 2025 Bowman Draft Sapphire KANE KEPLEY #BDC-200 Chrome 1st Prospect Cubs | C4432: POOKIEWHT-0001-00002-42708 | D4432: 7 | F4432: =IF($B4432="","",IF(ISNUMBER(SEARCH("PSA",$B4432)),"Yes","No")) -> No | G4432: =IF($B4432="","",IF(ISNUMBER(SEARCH("PSA 10",$B4432)),10,IF(ISNUMBER(SEARCH("PSA 9.5",$B4432)),9.5,IF(ISNUMBER(SEARCH("PSA 9",$B4432)),9,IF(ISNUMBER(SEARCH("PSA 8",$B4432)),8,IF(ISNUMBER(SEARCH("PSA",$B4432)),"<9","")))))) | H4432: =IF($B4432="","",IF($D4432>=100,"TIER 2",IF(OR(ISNUMBER(SEARCH("PSA 10",$B4432)),ISNUMBER(SEARCH("PSA 9.5",$B4432)),ISNUMBER(SEARCH("PSA 9",$B4432))),"TIER 3",IF(AND($D4432>20,N($E4432)>=15),"TIER 1","—")))) -> — | I4432: =IF($B4432="","",IF($D4432>=100,"Premium $100+ (auto)",IF(OR(ISNUMBER(SEARCH("PSA 10",$B4432)),ISNUMBER(SEARCH("PSA 9.5",$B4432)),ISNUMBER(SEARCH("PSA 9",$B4432))),"Graded PSA 9+ (auto)",IF(AND($D4432>20,N($E4432)>=15),"Hot: $20+ & "&$E4432&"/day",IF($D4432>20,"$20+ — needs velocity check","Below thresholds"))))) -> Below thresholds | J4432: =IF($B4432="","",IF(AND($D4432>20,$D4432<100,NOT(OR(ISNUMBER(SEARCH("PSA 10",$B4432)),ISNUMBER(SEARCH("PSA 9.5",$B4432)),ISNUMBER(SEARCH("PSA 9",$B4432)))),$E4432=""),"YES — pull CardHedger",""))
A4433: 227354649836 | B4433: 2025 Bowman Draft Sapphire SEBASTIAN WALCOTT #BDC-169 Chrome Rangers | C4433: POOKIEWHT-0001-00013-11739 | D4433: 2 | F4433: =IF($B4433="","",IF(ISNUMBER(SEARCH("PSA",$B4433)),"Yes","No")) -> No | G4433: =IF($B4433="","",IF(ISNUMBER(SEARCH("PSA 10",$B4433)),10,IF(ISNUMBER(SEARCH("PSA 9.5",$B4433)),9.5,IF(ISNUMBER(SEARCH("PSA 9",$B4433)),9,IF(ISNUMBER(SEARCH("PSA 8",$B4433)),8,IF(ISNUMBER(SEARCH("PSA",$B4433)),"<9","")))))) | H4433: =IF($B4433="","",IF($D4433>=100,"TIER 2",IF(OR(ISNUMBER(SEARCH("PSA 10",$B4433)),ISNUMBER(SEARCH("PSA 9.5",$B4433)),ISNUMBER(SEARCH("PSA 9",$B4433))),"TIER 3",IF(AND($D4433>20,N($E4433)>=15),"TIER 1","—")))) -> — | I4433: =IF($B4433="","",IF($D4433>=100,"Premium $100+ (auto)",IF(OR(ISNUMBER(SEARCH("PSA 10",$B4433)),ISNUMBER(SEARCH("PSA 9.5",$B4433)),ISNUMBER(SEARCH("PSA 9",$B4433))),"Graded PSA 9+ (auto)",IF(AND($D4433>20,N($E4433)>=15),"Hot: $20+ & "&$E4433&"/day",IF($D4433>20,"$20+ — needs velocity check","Below thresholds"))))) -> Below thresholds | J4433: =IF($B4433="","",IF(AND($D4433>20,$D4433<100,NOT(OR(ISNUMBER(SEARCH("PSA 10",$B4433)),ISNUMBER(SEARCH("PSA 9.5",$B4433)),ISNUMBER(SEARCH("PSA 9",$B4433)))),$E4433=""),"YES — pull CardHedger",""))
A4434: 227354649885 | B4434: 2025 Bowman Draft THOMAS WHITE #BDC-26 Chrome Sparkle Refractor Marlins | C4434: POOKIEWHT-0001-00021-59118 | D4434: 2 | F4434: =IF($B4434="","",IF(ISNUMBER(SEARCH("PSA",$B4434)),"Yes","No")) -> No | G4434: =IF($B4434="","",IF(ISNUMBER(SEARCH("PSA 10",$B4434)),10,IF(ISNUMBER(SEARCH("PSA 9.5",$B4434)),9.5,IF(ISNUMBER(SEARCH("PSA 9",$B4434)),9,IF(ISNUMBER(SEARCH("PSA 8",$B4434)),8,IF(ISNUMBER(SEARCH("PSA",$B4434)),"<9","")))))) | H4434: =IF($B4434="","",IF($D4434>=100,"TIER 2",IF(OR(ISNUMBER(SEARCH("PSA 10",$B4434)),ISNUMBER(SEARCH("PSA 9.5",$B4434)),ISNUMBER(SEARCH("PSA 9",$B4434))),"TIER 3",IF(AND($D4434>20,N($E4434)>=15),"TIER 1","—")))) -> — | I4434: =IF($B4434="","",IF($D4434>=100,"Premium $100+ (auto)",IF(OR(ISNUMBER(SEARCH("PSA 10",$B4434)),ISNUMBER(SEARCH("PSA 9.5",$B4434)),ISNUMBER(SEARCH("PSA 9",$B4434))),"Graded PSA 9+ (auto)",IF(AND($D4434>20,N($E4434)>=15),"Hot: $20+ & "&$E4434&"/day",IF($D4434>20,"$20+ — needs velocity check","Below thresholds"))))) -> Below thresholds | J4434: =IF($B4434="","",IF(AND($D4434>20,$D4434<100,NOT(OR(ISNUMBER(SEARCH("PSA 10",$B4434)),ISNUMBER(SEARCH("PSA 9.5",$B4434)),ISNUMBER(SEARCH("PSA 9",$B4434)))),$E4434=""),"YES — pull CardHedger",""))
A4435: 227354649903 | B4435: 2025 Bowman Draft Sapphire Mason McConnaughey #BDC-117 Chrome 1st Prospect | C4435: POOKIEWHT-0001-00018-04041 | D4435: 2 | F4435: =IF($B4435="","",IF(ISNUMBER(SEARCH("PSA",$B4435)),"Yes","No")) -> No | G4435: =IF($B4435="","",IF(ISNUMBER(SEARCH("PSA 10",$B4435)),10,IF(ISNUMBER(SEARCH("PSA 9.5",$B4435)),9.5,IF(ISNUMBER(SEARCH("PSA 9",$B4435)),9,IF(ISNUMBER(SEARCH("PSA 8",$B4435)),8,IF(ISNUMBER(SEARCH("PSA",$B4435)),"<9","")))))) | H4435: =IF($B4435="","",IF($D4435>=100,"TIER 2",IF(OR(ISNUMBER(SEARCH("PSA 10",$B4435)),ISNUMBER(SEARCH("PSA 9.5",$B4435)),ISNUMBER(SEARCH("PSA 9",$B4435))),"TIER 3",IF(AND($D4435>20,N($E4435)>=15),"TIER 1","—")))) -> — | I4435: =IF($B4435="","",IF($D4435>=100,"Premium $100+ (auto)",IF(OR(ISNUMBER(SEARCH("PSA 10",$B4435)),ISNUMBER(SEARCH("PSA 9.5",$B4435)),ISNUMBER(SEARCH("PSA 9",$B4435))),"Graded PSA 9+ (auto)",IF(AND($D4435>20,N($E4435)>=15),"Hot: $20+ & "&$E4435&"/day",IF($D4435>20,"$20+ — needs velocity check","Below thresholds"))))) -> Below thresholds | J4435: =IF($B4435="","",IF(AND($D4435>20,$D4435<100,NOT(OR(ISNUMBER(SEARCH("PSA 10",$B4435)),ISNUMBER(SEARCH("PSA 9.5",$B4435)),ISNUMBER(SEARCH("PSA 9",$B4435)))),$E4435=""),"YES — pull CardHedger",""))
... A4484: 227355873692 | B4484: 2026 Bowman Daniel Pierce #CPA-DP Chrome Auto Yellow Refractor /75 1st Prospect | C4484: CARDSHQBK-0001-00034-06853 | D4484: 799.99 | F4484: =IF($B4484="","",IF(ISNUMBER(SEARCH("PSA",$B4484)),"Yes","No")) -> No | G4484: =IF($B4484="","",IF(ISNUMBER(SEARCH("PSA 10",$B4484)),10,IF(ISNUMBER(SEARCH("PSA 9.5",$B4484)),9.5,IF(ISNUMBER(SEARCH("PSA 9",$B4484)),9,IF(ISNUMBER(SEARCH("PSA 8",$B4484)),8,IF(ISNUMBER(SEARCH("PSA",$B4484)),"<9","")))))) | H4484: =IF($B4484="","",IF($D4484>=100,"TIER 2",IF(OR(ISNUMBER(SEARCH("PSA 10",$B4484)),ISNUMBER(SEARCH("PSA 9.5",$B4484)),ISNUMBER(SEARCH("PSA 9",$B4484))),"TIER 3",IF(AND($D4484>20,N($E4484)>=15),"TIER 1","—")))) -> TIER 2 | I4484: =IF($B4484="","",IF($D4484>=100,"Premium $100+ (auto)",IF(OR(ISNUMBER(SEARCH("PSA 10",$B4484)),ISNUMBER(SEARCH("PSA 9.5",$B4484)),ISNUMBER(SEARCH("PSA 9",$B4484))),"Graded PSA 9+ (auto)",IF(AND($D4484>20,N($E4484)>=15),"Hot: $20+ & "&$E4484&"/day",IF($D4484>20,"$20+ — needs velocity check","Below thresholds"))))) -> Premium $100+ (auto) | J4484: =IF($B4484="","",IF(AND($D4484>20,$D4484<100,NOT(OR(ISNUMBER(SEARCH("PSA 10",$B4484)),ISNUMBER(SEARCH("PSA 9.5",$B4484)),ISNUMBER(SEARCH("PSA 9",$B4484)))),$E4484=""),"YES — pull CardHedger",""))
F4485: =IF($B4485="","",IF(ISNUMBER(SEARCH("PSA",$B4485)),"Yes","No")) | G4485: =IF($B4485="","",IF(ISNUMBER(SEARCH("PSA 10",$B4485)),10,IF(ISNUMBER(SEARCH("PSA 9.5",$B4485)),9.5,IF(ISNUMBER(SEARCH("PSA 9",$B4485)),9,IF(ISNUMBER(SEARCH("PSA 8",$B4485)),8,IF(ISNUMBER(SEARCH("PSA",$B4485)),"<9","")))))) | H4485: =IF($B4485="","",IF($D4485>=100,"TIER 2",IF(OR(ISNUMBER(SEARCH("PSA 10",$B4485)),ISNUMBER(SEARCH("PSA 9.5",$B4485)),ISNUMBER(SEARCH("PSA 9",$B4485))),"TIER 3",IF(AND($D4485>20,N($E4485)>=15),"TIER 1","—")))) | I4485: =IF($B4485="","",IF($D4485>=100,"Premium $100+ (auto)",IF(OR(ISNUMBER(SEARCH("PSA 10",$B4485)),ISNUMBER(SEARCH("PSA 9.5",$B4485)),ISNUMBER(SEARCH("PSA 9",$B4485))),"Graded PSA 9+ (auto)",IF(AND($D4485>20,N($E4485)>=15),"Hot: $20+ & "&$E4485&"/day",IF($D4485>20,"$20+ — needs velocity check","Below thresholds"))))) | J4485: =IF($B4485="","",IF(AND($D4485>20,$D4485<100,NOT(OR(ISNUMBER(SEARCH("PSA 10",$B4485)),ISNUMBER(SEARCH("PSA 9.5",$B4485)),ISNUMBER(SEARCH("PSA 9",$B4485)))),$E4485=""),"YES — pull CardHedger",""))
F4486: =IF($B4486="","",IF(ISNUMBER(SEARCH("PSA",$B4486)),"Yes","No")) | G4486: =IF($B4486="","",IF(ISNUMBER(SEARCH("PSA 10",$B4486)),10,IF(ISNUMBER(SEARCH("PSA 9.5",$B4486)),9.5,IF(ISNUMBER(SEARCH("PSA 9",$B4486)),9,IF(ISNUMBER(SEARCH("PSA 8",$B4486)),8,IF(ISNUMBER(SEARCH("PSA",$B4486)),"<9","")))))) | H4486: =IF($B4486="","",IF($D4486>=100,"TIER 2",IF(OR(ISNUMBER(SEARCH("PSA 10",$B4486)),ISNUMBER(SEARCH("PSA 9.5",$B4486)),ISNUMBER(SEARCH("PSA 9",$B4486))),"TIER 3",IF(AND($D4486>20,N($E4486)>=15),"TIER 1","—")))) | I4486: =IF($B4486="","",IF($D4486>=100,"Premium $100+ (auto)",IF(OR(ISNUMBER(SEARCH("PSA 10",$B4486)),ISNUMBER(SEARCH("PSA 9.5",$B4486)),ISNUMBER(SEARCH("PSA 9",$B4486))),"Graded PSA 9+ (auto)",IF(AND($D4486>20,N($E4486)>=15),"Hot: $20+ & "&$E4486&"/day",IF($D4486>20,"$20+ — needs velocity check","Below thresholds"))))) | J4486: =IF($B4486="","",IF(AND($D4486>20,$D4486<100,NOT(OR(ISNUMBER(SEARCH("PSA 10",$B4486)),ISNUMBER(SEARCH("PSA 9.5",$B4486)),ISNUMBER(SEARCH("PSA 9",$B4486)))),$E4486=""),"YES — pull CardHedger",""))
F4487: =IF($B4487="","",IF(ISNUMBER(SEARCH("PSA",$B4487)),"Yes","No")) | G4487: =IF($B4487="","",IF(ISNUMBER(SEARCH("PSA 10",$B4487)),10,IF(ISNUMBER(SEARCH("PSA 9.5",$B4487)),9.5,IF(ISNUMBER(SEARCH("PSA 9",$B4487)),9,IF(ISNUMBER(SEARCH("PSA 8",$B4487)),8,IF(ISNUMBER(SEARCH("PSA",$B4487)),"<9","")))))) | H4487: =IF($B4487="","",IF($D4487>=100,"TIER 2",IF(OR(ISNUMBER(SEARCH("PSA 10",$B4487)),ISNUMBER(SEARCH("PSA 9.5",$B4487)),ISNUMBER(SEARCH("PSA 9",$B4487))),"TIER 3",IF(AND($D4487>20,N($E4487)>=15),"TIER 1","—")))) | I4487: =IF($B4487="","",IF($D4487>=100,"Premium $100+ (auto)",IF(OR(ISNUMBER(SEARCH("PSA 10",$B4487)),ISNUMBER(SEARCH("PSA 9.5",$B4487)),ISNUMBER(SEARCH("PSA 9",$B4487))),"Graded PSA 9+ (auto)",IF(AND($D4487>20,N($E4487)>=15),"Hot: $20+ & "&$E4487&"/day",IF($D4487>20,"$20+ — needs velocity check","Below thresholds"))))) | J4487: =IF($B4487="","",IF(AND($D4487>20,$D4487<100,NOT(OR(ISNUMBER(SEARCH("PSA 10",$B4487)),ISNUMBER(SEARCH("PSA 9.5",$B4487)),ISNUMBER(SEARCH("PSA 9",$B4487)))),$E4487=""),"YES — pull CardHedger",""))
F4488: =IF($B4488="","",IF(ISNUMBER(SEARCH("PSA",$B4488)),"Yes","No")) | G4488: =IF($B4488="","",IF(ISNUMBER(SEARCH("PSA 10",$B4488)),10,IF(ISNUMBER(SEARCH("PSA 9.5",$B4488)),9.5,IF(ISNUMBER(SEARCH("PSA 9",$B4488)),9,IF(ISNUMBER(SEARCH("PSA 8",$B4488)),8,IF(ISNUMBER(SEARCH("PSA",$B4488)),"<9","")))))) | H4488: =IF($B4488="","",IF($D4488>=100,"TIER 2",IF(OR(ISNUMBER(SEARCH("PSA 10",$B4488)),ISNUMBER(SEARCH("PSA 9.5",$B4488)),ISNUMBER(SEARCH("PSA 9",$B4488))),"TIER 3",IF(AND($D4488>20,N($E4488)>=15),"TIER 1","—")))) | I4488: =IF($B4488="","",IF($D4488>=100,"Premium $100+ (auto)",IF(OR(ISNUMBER(SEARCH("PSA 10",$B4488)),ISNUMBER(SEARCH("PSA 9.5",$B4488)),ISNUMBER(SEARCH("PSA 9",$B4488))),"Graded PSA 9+ (auto)",IF(AND($D4488>20,N($E4488)>=15),"Hot: $20+ & "&$E4488&"/day",IF($D4488>20,"$20+ — needs velocity check","Below thresholds"))))) | J4488: =IF($B4488="","",IF(AND($D4488>20,$D4488<100,NOT(OR(ISNUMBER(SEARCH("PSA 10",$B4488)),ISNUMBER(SEARCH("PSA 9.5",$B4488)),ISNUMBER(SEARCH("PSA 9",$B4488)))),$E4488=""),"YES — pull CardHedger",""))
F4489: =IF($B4489="","",IF(ISNUMBER(SEARCH("PSA",$B4489)),"Yes","No")) | G4489: =IF($B4489="","",IF(ISNUMBER(SEARCH("PSA 10",$B4489)),10,IF(ISNUMBER(SEARCH("PSA 9.5",$B4489)),9.5,IF(ISNUMBER(SEARCH("PSA 9",$B4489)),9,IF(ISNUMBER(SEARCH("PSA 8",$B4489)),8,IF(ISNUMBER(SEARCH("PSA",$B4489)),"<9","")))))) | H4489: =IF($B4489="","",IF($D4489>=100,"TIER 2",IF(OR(ISNUMBER(SEARCH("PSA 10",$B4489)),ISNUMBER(SEARCH("PSA 9.5",$B4489)),ISNUMBER(SEARCH("PSA 9",$B4489))),"TIER 3",IF(AND($D4489>20,N($E4489)>=15),"TIER 1","—")))) | I4489: =IF($B4489="","",IF($D4489>=100,"Premium $100+ (auto)",IF(OR(ISNUMBER(SEARCH("PSA 10",$B4489)),ISNUMBER(SEARCH("PSA 9.5",$B4489)),ISNUMBER(SEARCH("PSA 9",$B4489))),"Graded PSA 9+ (auto)",IF(AND($D4489>20,N($E4489)>=15),"Hot: $20+ & "&$E4489&"/day",IF($D4489>20,"$20+ — needs velocity check","Below thresholds"))))) | J4489: =IF($B4489="","",IF(AND($D4489>20,$D4489<100,NOT(OR(ISNUMBER(SEARCH("PSA 10",$B4489)),ISNUMBER(SEARCH("PSA 9.5",$B4489)),ISNUMBER(SEARCH("PSA 9",$B4489)))),$E4489=""),"YES — pull CardHedger",""))
F4490: =IF($B4490="","",IF(ISNUMBER(SEARCH("PSA",$B4490)),"Yes","No")) | G4490: =IF($B4490="","",IF(ISNUMBER(SEARCH("PSA 10",$B4490)),10,IF(ISNUMBER(SEARCH("PSA 9.5",$B4490)),9.5,IF(ISNUMBER(SEARCH("PSA 9",$B4490)),9,IF(ISNUMBER(SEARCH("PSA 8",$B4490)),8,IF(ISNUMBER(SEARCH("PSA",$B4490)),"<9","")))))) | H4490: =IF($B4490="","",IF($D4490>=100,"TIER 2",IF(OR(ISNUMBER(SEARCH("PSA 10",$B4490)),ISNUMBER(SEARCH("PSA 9.5",$B4490)),ISNUMBER(SEARCH("PSA 9",$B4490))),"TIER 3",IF(AND($D4490>20,N($E4490)>=15),"TIER 1","—")))) | I4490: =IF($B4490="","",IF($D4490>=100,"Premium $100+ (auto)",IF(OR(ISNUMBER(SEARCH("PSA 10",$B4490)),ISNUMBER(SEARCH("PSA 9.5",$B4490)),ISNUMBER(SEARCH("PSA 9",$B4490))),"Graded PSA 9+ (auto)",IF(AND($D4490>20,N($E4490)>=15),"Hot: $20+ & "&$E4490&"/day",IF($D4490>20,"$20+ — needs velocity check","Below thresholds"))))) | J4490: =IF($B4490="","",IF(AND($D4490>20,$D4490<100,NOT(OR(ISNUMBER(SEARCH("PSA 10",$B4490)),ISNUMBER(SEARCH("PSA 9.5",$B4490)),ISNUMBER(SEARCH("PSA 9",$B4490)))),$E4490=""),"YES — pull CardHedger",""))
F4491: =IF($B4491="","",IF(ISNUMBER(SEARCH("PSA",$B4491)),"Yes","No")) | G4491: =IF($B4491="","",IF(ISNUMBER(SEARCH("PSA 10",$B4491)),10,IF(ISNUMBER(SEARCH("PSA 9.5",$B4491)),9.5,IF(ISNUMBER(SEARCH("PSA 9",$B4491)),9,IF(ISNUMBER(SEARCH("PSA 8",$B4491)),8,IF(ISNUMBER(SEARCH("PSA",$B4491)),"<9","")))))) | H4491: =IF($B4491="","",IF($D4491>=100,"TIER 2",IF(OR(ISNUMBER(SEARCH("PSA 10",$B4491)),ISNUMBER(SEARCH("PSA 9.5",$B4491)),ISNUMBER(SEARCH("PSA 9",$B4491))),"TIER 3",IF(AND($D4491>20,N($E4491)>=15),"TIER 1","—")))) | I4491: =IF($B4491="","",IF($D4491>=100,"Premium $100+ (auto)",IF(OR(ISNUMBER(SEARCH("PSA 10",$B4491)),ISNUMBER(SEARCH("PSA 9.5",$B4491)),ISNUMBER(SEARCH("PSA 9",$B4491))),"Graded PSA 9+ (auto)",IF(AND($D4491>20,N($E4491)>=15),"Hot: $20+ & "&$E4491&"/day",IF($D4491>20,"$20+ — needs velocity check","Below thresholds"))))) | J4491: =IF($B4491="","",IF(AND($D4491>20,$D4491<100,NOT(OR(ISNUMBER(SEARCH("PSA 10",$B4491)),ISNUMBER(SEARCH("PSA 9.5",$B4491)),ISNUMBER(SEARCH("PSA 9",$B4491)))),$E4491=""),"YES — pull CardHedger",""))
F4492: =IF($B4492="","",IF(ISNUMBER(SEARCH("PSA",$B4492)),"Yes","No")) | G4492: =IF($B4492="","",IF(ISNUMBER(SEARCH("PSA 10",$B4492)),10,IF(ISNUMBER(SEARCH("PSA 9.5",$B4492)),9.5,IF(ISNUMBER(SEARCH("PSA 9",$B4492)),9,IF(ISNUMBER(SEARCH("PSA 8",$B4492)),8,IF(ISNUMBER(SEARCH("PSA",$B4492)),"<9","")))))) | H4492: =IF($B4492="","",IF($D4492>=100,"TIER 2",IF(OR(ISNUMBER(SEARCH("PSA 10",$B4492)),ISNUMBER(SEARCH("PSA 9.5",$B4492)),ISNUMBER(SEARCH("PSA 9",$B4492))),"TIER 3",IF(AND($D4492>20,N($E4492)>=15),"TIER 1","—")))) | I4492: =IF($B4492="","",IF($D4492>=100,"Premium $100+ (auto)",IF(OR(ISNUMBER(SEARCH("PSA 10",$B4492)),ISNUMBER(SEARCH("PSA 9.5",$B4492)),ISNUMBER(SEARCH("PSA 9",$B4492))),"Graded PSA 9+ (auto)",IF(AND($D4492>20,N($E4492)>=15),"Hot: $20+ & "&$E4492&"/day",IF($D4492>20,"$20+ — needs velocity check","Below thresholds"))))) | J4492: =IF($B4492="","",IF(AND($D4492>20,$D4492<100,NOT(OR(ISNUMBER(SEARCH("PSA 10",$B4492)),ISNUMBER(SEARCH("PSA 9.5",$B4492)),ISNUMBER(SEARCH("PSA 9",$B4492)))),$E4492=""),"YES — pull CardHedger",""))
F4493: =IF($B4493="","",IF(ISNUMBER(SEARCH("PSA",$B4493)),"Yes","No")) | G4493: =IF($B4493="","",IF(ISNUMBER(SEARCH("PSA 10",$B4493)),10,IF(ISNUMBER(SEARCH("PSA 9.5",$B4493)),9.5,IF(ISNUMBER(SEARCH("PSA 9",$B4493)),9,IF(ISNUMBER(SEARCH("PSA 8",$B4493)),8,IF(ISNUMBER(SEARCH("PSA",$B4493)),"<9","")))))) | H4493: =IF($B4493="","",IF($D4493>=100,"TIER 2",IF(OR(ISNUMBER(SEARCH("PSA 10",$B4493)),ISNUMBER(SEARCH("PSA 9.5",$B4493)),ISNUMBER(SEARCH("PSA 9",$B4493))),"TIER 3",IF(AND($D4493>20,N($E4493)>=15),"TIER 1","—")))) | I4493: =IF($B4493="","",IF($D4493>=100,"Premium $100+ (auto)",IF(OR(ISNUMBER(SEARCH("PSA 10",$B4493)),ISNUMBER(SEARCH("PSA 9.5",$B4493)),ISNUMBER(SEARCH("PSA 9",$B4493))),"Graded PSA 9+ (auto)",IF(AND($D4493>20,N($E4493)>=15),"Hot: $20+ & "&$E4493&"/day",IF($D4493>20,"$20+ — needs velocity check","Below thresholds"))))) | J4493: =IF($B4493="","",IF(AND($D4493>20,$D4493<100,NOT(OR(ISNUMBER(SEARCH("PSA 10",$B4493)),ISNUMBER(SEARCH("PSA 9.5",$B4493)),ISNUMBER(SEARCH("PSA 9",$B4493)))),$E4493=""),"YES — pull CardHedger",""))
F4494: =IF($B4494="","",IF(ISNUMBER(SEARCH("PSA",$B4494)),"Yes","No")) | G4494: =IF($B4494="","",IF(ISNUMBER(SEARCH("PSA 10",$B4494)),10,IF(ISNUMBER(SEARCH("PSA 9.5",$B4494)),9.5,IF(ISNUMBER(SEARCH("PSA 9",$B4494)),9,IF(ISNUMBER(SEARCH("PSA 8",$B4494)),8,IF(ISNUMBER(SEARCH("PSA",$B4494)),"<9","")))))) | H4494: =IF($B4494="","",IF($D4494>=100,"TIER 2",IF(OR(ISNUMBER(SEARCH("PSA 10",$B4494)),ISNUMBER(SEARCH("PSA 9.5",$B4494)),ISNUMBER(SEARCH("PSA 9",$B4494))),"TIER 3",IF(AND($D4494>20,N($E4494)>=15),"TIER 1","—")))) | I4494: =IF($B4494="","",IF($D4494>=100,"Premium $100+ (auto)",IF(OR(ISNUMBER(SEARCH("PSA 10",$B4494)),ISNUMBER(SEARCH("PSA 9.5",$B4494)),ISNUMBER(SEARCH("PSA 9",$B4494))),"Graded PSA 9+ (auto)",IF(AND($D4494>20,N($E4494)>=15),"Hot: $20+ & "&$E4494&"/day",IF($D4494>20,"$20+ — needs velocity check","Below thresholds"))))) | J4494: =IF($B4494="","",IF(AND($D4494>20,$D4494<100,NOT(OR(ISNUMBER(SEARCH("PSA 10",$B4494)),ISNUMBER(SEARCH("PSA 9.5",$B4494)),ISNUMBER(SEARCH("PSA 9",$B4494)))),$E4494=""),"YES — pull CardHedger",""))
F4495: =IF($B4495="","",IF(ISNUMBER(SEARCH("PSA",$B4495)),"Yes","No")) | G4495: =IF($B4495="","",IF(ISNUMBER(SEARCH("PSA 10",$B4495)),10,IF(ISNUMBER(SEARCH("PSA 9.5",$B4495)),9.5,IF(ISNUMBER(SEARCH("PSA 9",$B4495)),9,IF(ISNUMBER(SEARCH("PSA 8",$B4495)),8,IF(ISNUMBER(SEARCH("PSA",$B4495)),"<9","")))))) | H4495: =IF($B4495="","",IF($D4495>=100,"TIER 2",IF(OR(ISNUMBER(SEARCH("PSA 10",$B4495)),ISNUMBER(SEARCH("PSA 9.5",$B4495)),ISNUMBER(SEARCH("PSA 9",$B4495))),"TIER 3",IF(AND($D4495>20,N($E4495)>=15),"TIER 1","—")))) | I4495: =IF($B4495="","",IF($D4495>=100,"Premium $100+ (auto)",IF(OR(ISNUMBER(SEARCH("PSA 10",$B4495)),ISNUMBER(SEARCH("PSA 9.5",$B4495)),ISNUMBER(SEARCH("PSA 9",$B4495))),"Graded PSA 9+ (auto)",IF(AND($D4495>20,N($E4495)>=15),"Hot: $20+ & "&$E4495&"/day",IF($D4495>20,"$20+ — needs velocity check","Below thresholds"))))) | J4495: =IF($B4495="","",IF(AND($D4495>20,$D4495<100,NOT(OR(ISNUMBER(SEARCH("PSA 10",$B4495)),ISNUMBER(SEARCH("PSA 9.5",$B4495)),ISNUMBER(SEARCH("PSA 9",$B4495)))),$E4495=""),"YES — pull CardHedger",""))
F4496: =IF($B4496="","",IF(ISNUMBER(SEARCH("PSA",$B4496)),"Yes","No")) | G4496: =IF($B4496="","",IF(ISNUMBER(SEARCH("PSA 10",$B4496)),10,IF(ISNUMBER(SEARCH("PSA 9.5",$B4496)),9.5,IF(ISNUMBER(SEARCH("PSA 9",$B4496)),9,IF(ISNUMBER(SEARCH("PSA 8",$B4496)),8,IF(ISNUMBER(SEARCH("PSA",$B4496)),"<9","")))))) | H4496: =IF($B4496="","",IF($D4496>=100,"TIER 2",IF(OR(ISNUMBER(SEARCH("PSA 10",$B4496)),ISNUMBER(SEARCH("PSA 9.5",$B4496)),ISNUMBER(SEARCH("PSA 9",$B4496))),"TIER 3",IF(AND($D4496>20,N($E4496)>=15),"TIER 1","—")))) | I4496: =IF($B4496="","",IF($D4496>=100,"Premium $100+ (auto)",IF(OR(ISNUMBER(SEARCH("PSA 10",$B4496)),ISNUMBER(SEARCH("PSA 9.5",$B4496)),ISNUMBER(SEARCH("PSA 9",$B4496))),"Graded PSA 9+ (auto)",IF(AND($D4496>20,N($E4496)>=15),"Hot: $20+ & "&$E4496&"/day",IF($D4496>20,"$20+ — needs velocity check","Below thresholds"))))) | J4496: =IF($B4496="","",IF(AND($D4496>20,$D4496<100,NOT(OR(ISNUMBER(SEARCH("PSA 10",$B4496)),ISNUMBER(SEARCH("PSA 9.5",$B4496)),ISNUMBER(SEARCH("PSA 9",$B4496)))),$E4496=""),"YES — pull CardHedger",""))
... F4600: =IF($B4600="","",IF(ISNUMBER(SEARCH("PSA",$B4600)),"Yes","No")) | G4600: =IF($B4600="","",IF(ISNUMBER(SEARCH("PSA 10",$B4600)),10,IF(ISNUMBER(SEARCH("PSA 9.5",$B4600)),9.5,IF(ISNUMBER(SEARCH("PSA 9",$B4600)),9,IF(ISNUMBER(SEARCH("PSA 8",$B4600)),8,IF(ISNUMBER(SEARCH("PSA",$B4600)),"<9","")))))) | H4600: =IF($B4600="","",IF($D4600>=100,"TIER 2",IF(OR(ISNUMBER(SEARCH("PSA 10",$B4600)),ISNUMBER(SEARCH("PSA 9.5",$B4600)),ISNUMBER(SEARCH("PSA 9",$B4600))),"TIER 3",IF(AND($D4600>20,N($E4600)>=15),"TIER 1","—")))) | I4600: =IF($B4600="","",IF($D4600>=100,"Premium $100+ (auto)",IF(OR(ISNUMBER(SEARCH("PSA 10",$B4600)),ISNUMBER(SEARCH("PSA 9.5",$B4600)),ISNUMBER(SEARCH("PSA 9",$B4600))),"Graded PSA 9+ (auto)",IF(AND($D4600>20,N($E4600)>=15),"Hot: $20+ & "&$E4600&"/day",IF($D4600>20,"$20+ — needs velocity check","Below thresholds"))))) | J4600: =IF($B4600="","",IF(AND($D4600>20,$D4600<100,NOT(OR(ISNUMBER(SEARCH("PSA 10",$B4600)),ISNUMBER(SEARCH("PSA 9.5",$B4600)),ISNUMBER(SEARCH("PSA 9",$B4600)))),$E4600=""),"YES — pull CardHedger",""))

Sheet Lot Evaluator
A1: 🏠 Start Here
A2: Run this BEFORE every lot buying decision. Input comp total + target margin → max offer.
A4: INPUTS (edit blue cells) | E4: CALCULATIONS & MAX OFFER
B5: Total comp value of lot ($) | C5: 1000 | E5: Expected gross proceeds ($) | F5: =C5*C6 -> 750
B6: Expected sell-through rate (%) | C6: 0.75 | E6: Expected fees ($) | F6: =F5*C7 -> 101.25
B7: Your average fee rate (%) | C7: 0.135 | E7: Expected shipping cost ($) | F7: =C8*C10*C6 -> 84.375
B8: Avg shipping cost / sale ($) | C8: 4.5 | E8: Expected supplies cost ($) | F8: =C9*C10 -> 18.75
B9: Avg supplies cost / sale ($) | C9: 0.75 | E9: Net before COGS ($) | F9: =F5-F6-F7-F8 -> 545.625
B10: Estimated # cards | C10: 25 | E10: Dollar margin target on net ($) | F10: =F9*C11 -> 190.96875
B11: Your target NET margin (%) | C11: 0.35 | E11: MAX OFFER for lot ($) | F11: =F9-F10 -> 354.65625
A14: DECISION RULE
A15: • If ASKING PRICE ≤ MAX OFFER → BUY. You will hit your target margin.
A16: • If ASKING PRICE is 10-15% above MAX OFFER → counter-offer at MAX OFFER × 0.95 and walk if rejected.
A17: • If ASKING PRICE is >15% above MAX OFFER → WALK. The deal doesn't math — don't let FOMO override the model.
A18: • If lot includes uncertain raw high-grade cards, discount comp total by 20% to reflect grading risk before running.

Sheet Channel Fees
A1: 🏠 Start Here
A2: Live calculator + price-point table + routing rules. Verified fees as of April 2026.
A4: LIVE CALCULATOR — Enter a sale price, see net at each channel
B5: Sale price ($) | C5: 100 | D5: ← Change this cell to model any sale price
B7: Channel | C7: Commission % | D7: Per-Order Fee | E7: Pmt Processing % | F7: Total Fees ($) | G7: Net to You ($) | H7: Effective Fee %
B8: eBay (standard) | C8: 0.136 | D8: 0.4 | E8: 0 | F8: =$C$5*C8+D8+$C$5*E8 -> 14 | G8: =$C$5-F8 -> 86 | H8: =IFERROR(F8/$C$5,"") -> 0.14 | I8: Default — broadest buyer pool
B9: eBay (singles $1,000+) | C9: 0.068 | D9: 0.4 | E9: 0 | F9: =$C$5*C9+D9+$C$5*E9 -> 7.2 | G9: =$C$5-F9 -> 92.8 | H9: =IFERROR(F9/$C$5,"") -> 0.072 | I9: Auto-applied promo on $1k+ singles
B10: Whatnot | C10: 0.08 | D10: 0.3 | E10: 0.029 | F10: =$C$5*C10+D10+$C$5*E10 -> 11.2 | G10: =$C$5-F10 -> 88.8 | H10: =IFERROR(F10/$C$5,"") -> 0.112 | I10: Cap on commission >$1,500 of single sale
B11: COLLX | C11: 0.1 | D11: 0 | E11: 0 | F11: =$C$5*C11+D11+$C$5*E11 -> 10 | G11: =$C$5-F11 -> 90 | H11: =IFERROR(F11/$C$5,"") -> 0.1 | I11: Fee includes processing
B12: FB Marketplace (online ship) | C12: 0.05 | D12: 0 | E12: 0 | F12: =$C$5*C12+D12+$C$5*E12 -> 5 | G12: =$C$5-F12 -> 95 | H12: =IFERROR(F12/$C$5,"") -> 0.05 | I12: Estimate — varies by transaction
B13: FB Marketplace (local cash) | C13: 0 | D13: 0 | E13: 0 | F13: =$C$5*C13+D13+$C$5*E13 -> 0 | G13: =$C$5-F13 -> 100 | H13: =IFERROR(F13/$C$5,"") -> 0 | I13: Zero fees, but limited buyer pool
B14: DcSports87 (consignment) | C14: 0.18 | D14: 0 | E14: 0 | F14: =$C$5*C14+D14+$C$5*E14 -> 18 | G14: =$C$5-F14 -> 82 | H14: =IFERROR(F14/$C$5,"") -> 0.18 | I14: Verify your actual rate per agreement
B15: Probstein (consignment) | C15: 0.2 | D15: 0 | E15: 0 | F15: =$C$5*C15+D15+$C$5*E15 -> 20 | G15: =$C$5-F15 -> 80 | H15: =IFERROR(F15/$C$5,"") -> 0.2 | I15: Tiered — verify actual
B16: PWCC (vault auction est.) | C16: 0.2 | D16: 0 | E16: 0 | F16: =$C$5*C16+D16+$C$5*E16 -> 20 | G16: =$C$5-F16 -> 80 | H16: =IFERROR(F16/$C$5,"") -> 0.2 | I16: Plus storage fees if vaulted
A19: NET TO YOU AT COMMON PRICE POINTS
B21: Channel | C21: $10 | D21: $25 | E21: $50 | F21: $100 | G21: $200 | H21: $500 | I21: $1000
B22: eBay (standard) | C22: =10-(10*$C$8+$D$8+10*$E$8) -> 8.24 | D22: =25-(25*$C$8+$D$8+25*$E$8) -> 21.2 | E22: =50-(50*$C$8+$D$8+50*$E$8) -> 42.8 | F22: =100-(100*$C$8+$D$8+100*$E$8) -> 86 | G22: =200-(200*$C$8+$D$8+200*$E$8) -> 172.4 | H22: =500-(500*$C$8+$D$8+500*$E$8) -> 431.6 | I22: =1000-(1000*$C$8+$D$8+1000*$E$8) -> 863.6
B23: eBay (singles $1,000+) | C23: =10-(10*$C$9+$D$9+10*$E$9) -> 8.92 | D23: =25-(25*$C$9+$D$9+25*$E$9) -> 22.9 | E23: =50-(50*$C$9+$D$9+50*$E$9) -> 46.2 | F23: =100-(100*$C$9+$D$9+100*$E$9) -> 92.8 | G23: =200-(200*$C$9+$D$9+200*$E$9) -> 186 | H23: =500-(500*$C$9+$D$9+500*$E$9) -> 465.6 | I23: =1000-(1000*$C$9+$D$9+1000*$E$9) -> 931.6
B24: Whatnot | C24: =10-(10*$C$10+$D$10+10*$E$10) -> 8.61 | D24: =25-(25*$C$10+$D$10+25*$E$10) -> 21.975 | E24: =50-(50*$C$10+$D$10+50*$E$10) -> 44.25 | F24: =100-(100*$C$10+$D$10+100*$E$10) -> 88.8 | G24: =200-(200*$C$10+$D$10+200*$E$10) -> 177.9 | H24: =500-(500*$C$10+$D$10+500*$E$10) -> 445.2 | I24: =1000-(1000*$C$10+$D$10+1000*$E$10) -> 890.7
B25: COLLX | C25: =10-(10*$C$11+$D$11+10*$E$11) -> 9 | D25: =25-(25*$C$11+$D$11+25*$E$11) -> 22.5 | E25: =50-(50*$C$11+$D$11+50*$E$11) -> 45 | F25: =100-(100*$C$11+$D$11+100*$E$11) -> 90 | G25: =200-(200*$C$11+$D$11+200*$E$11) -> 180 | H25: =500-(500*$C$11+$D$11+500*$E$11) -> 450 | I25: =1000-(1000*$C$11+$D$11+1000*$E$11) -> 900
B26: FB Marketplace (online ship) | C26: =10-(10*$C$12+$D$12+10*$E$12) -> 9.5 | D26: =25-(25*$C$12+$D$12+25*$E$12) -> 23.75 | E26: =50-(50*$C$12+$D$12+50*$E$12) -> 47.5 | F26: =100-(100*$C$12+$D$12+100*$E$12) -> 95 | G26: =200-(200*$C$12+$D$12+200*$E$12) -> 190 | H26: =500-(500*$C$12+$D$12+500*$E$12) -> 475 | I26: =1000-(1000*$C$12+$D$12+1000*$E$12) -> 950
B27: FB Marketplace (local cash) | C27: =10-(10*$C$13+$D$13+10*$E$13) -> 10 | D27: =25-(25*$C$13+$D$13+25*$E$13) -> 25 | E27: =50-(50*$C$13+$D$13+50*$E$13) -> 50 | F27: =100-(100*$C$13+$D$13+100*$E$13) -> 100 | G27: =200-(200*$C$13+$D$13+200*$E$13) -> 200 | H27: =500-(500*$C$13+$D$13+500*$E$13) -> 500 | I27: =1000-(1000*$C$13+$D$13+1000*$E$13) -> 1000
B28: DcSports87 (consignment) | C28: =10-(10*$C$14+$D$14+10*$E$14) -> 8.2 | D28: =25-(25*$C$14+$D$14+25*$E$14) -> 20.5 | E28: =50-(50*$C$14+$D$14+50*$E$14) -> 41 | F28: =100-(100*$C$14+$D$14+100*$E$14) -> 82 | G28: =200-(200*$C$14+$D$14+200*$E$14) -> 164 | H28: =500-(500*$C$14+$D$14+500*$E$14) -> 410 | I28: =1000-(1000*$C$14+$D$14+1000*$E$14) -> 820
B29: Probstein (consignment) | C29: =10-(10*$C$15+$D$15+10*$E$15) -> 8 | D29: =25-(25*$C$15+$D$15+25*$E$15) -> 20 | E29: =50-(50*$C$15+$D$15+50*$E$15) -> 40 | F29: =100-(100*$C$15+$D$15+100*$E$15) -> 80 | G29: =200-(200*$C$15+$D$15+200*$E$15) -> 160 | H29: =500-(500*$C$15+$D$15+500*$E$15) -> 400 | I29: =1000-(1000*$C$15+$D$15+1000*$E$15) -> 800
B30: PWCC (vault auction est.) | C30: =10-(10*$C$16+$D$16+10*$E$16) -> 8 | D30: =25-(25*$C$16+$D$16+25*$E$16) -> 20 | E30: =50-(50*$C$16+$D$16+50*$E$16) -> 40 | F30: =100-(100*$C$16+$D$16+100*$E$16) -> 80 | G30: =200-(200*$C$16+$D$16+200*$E$16) -> 160 | H30: =500-(500*$C$16+$D$16+500*$E$16) -> 400 | I30: =1000-(1000*$C$16+$D$16+1000*$E$16) -> 800
A33: ROUTING DECISION RULES — which channel for which card
B35: Card Type | E35: Best Primary Channel | G35: Why | I35: Backup
B36: Hot modern rookies / chase autos ($50-500) | E36: eBay | G36: Broad buyer pool, fast price discovery, buyers will pay premium despite fees | I36: Whatnot auction if hot player
B37: Mid-tier modern singles ($15-150) | E37: COLLX (primary), eBay (secondary) | G37: COLLX 10% all-in vs eBay ~14%; ~3-4 pts of margin saved on this volume tier | I37: eBay if no movement in 14d
B38: Vintage HOF graded ($500+) | E38: PWCC / Probstein auction | G38: Premium buyer base; auction format extracts max value | I38: eBay BIN with promotion
B39: Bulk lots / commons (50+ cards) | E39: FB Marketplace (local) or COLLX bulk | G39: eBay fees crush low-margin bulk; local cash = zero fees | I39: Whatnot lot break
B40: Quick-cash / time-sensitive | E40: Whatnot live auction | G40: Real-time price discovery, immediate sale | I40: eBay Best Offer accepted
B41: Stale 60+ day inventory | E41: DcSports87 + rotate | G41: Already trained channel; consignment frees capital + your hands | I41: Probstein for variety
B42: Low-confidence sourcing (uncertain comp) | E42: Whatnot or COLLX auction | G42: Market sets price; you don't have to guess | I42: —
B43: Personal pickup deals (>$50/card) | E43: COLLX direct message | G43: Strong collector community; lower fees on direct deals | I43: Local meet via FB
A46: BOTTOM-LINE TAKEAWAY
A47: • COLLX saves ~3-4 percentage points on direct-sale fees vs eBay. At $80k/mo gross, routing 30% to COLLX = ~$700-1,200/mo straight to net.
A48: • COLLX's tradeoff is a smaller buyer base — sell-through is slower (typical: 1-3 weeks vs eBay 3-10 days for hot cards). Use COLLX for cards where you can wait.
A49: • DON'T abandon eBay for hot/high-velocity cards — eBay's ~13.6% fee is more than offset by the price premium buyers pay there for in-demand items.
A50: • Cross-listing tools (Vendoo, List Perfectly) increasingly support COLLX — list once, route to multiple. Worth the $30-50/mo subscription at your scale.
A51: • On singles $1,000+, eBay's 50% fee discount makes eBay competitive again with COLLX — verify before routing premium cards.

Sheet Capital Velocity
A1: 🏠 Start Here
A2: How fast your working capital is cycling, and what it implies for net profit.
A4: CURRENT STATE — editable blue inputs
B5: Working capital ($) | C5: 20000
B6: Avg net margin % | C6: 0.3
B7: Current monthly turns | C7: 2
B8: Implied monthly gross ($) | C8: =C5*C7 -> 40000
B9: Implied monthly net ($) | C9: =C8*C6 -> 12000
A11: SCENARIO GRID — Monthly net at different (margin × turns)
B12: Turns / month → | C12: 1.5 | D12: 2 | E12: 2.5 | F12: 3 | G12: 3.5
B13: 0.2 | C13: =$C$5*1.5*0.2 -> 6000 | D13: =$C$5*2*0.2 -> 8000 | E13: =$C$5*2.5*0.2 -> 10000 | F13: =$C$5*3*0.2 -> 12000 | G13: =$C$5*3.5*0.2 -> 14000
B14: 0.25 | C14: =$C$5*1.5*0.25 -> 7500 | D14: =$C$5*2*0.25 -> 10000 | E14: =$C$5*2.5*0.25 -> 12500 | F14: =$C$5*3*0.25 -> 15000 | G14: =$C$5*3.5*0.25 -> 17500
B15: 0.3 | C15: =$C$5*1.5*0.3 -> 9000 | D15: =$C$5*2*0.3 -> 12000 | E15: =$C$5*2.5*0.3 -> 15000 | F15: =$C$5*3*0.3 -> 18000 | G15: =$C$5*3.5*0.3 -> 21000
B16: 0.35 | C16: =$C$5*1.5*0.35 -> 10500 | D16: =$C$5*2*0.35 -> 14000 | E16: =$C$5*2.5*0.35 -> 17500 | F16: =$C$5*3*0.35 -> 21000 | G16: =$C$5*3.5*0.35 -> 24500
B17: 0.4 | C17: =$C$5*1.5*0.4 -> 12000 | D17: =$C$5*2*0.4 -> 16000 | E17: =$C$5*2.5*0.4 -> 20000 | F17: =$C$5*3*0.4 -> 24000 | G17: =$C$5*3.5*0.4 -> 28000
B18: 0.45 | C18: =$C$5*1.5*0.45 -> 13500 | D18: =$C$5*2*0.45 -> 18000 | E18: =$C$5*2.5*0.45 -> 22500 | F18: =$C$5*3*0.45 -> 27000 | G18: =$C$5*3.5*0.45 -> 31500
B21: Target: $40,000/mo net. Find that dollar value in the grid above. To hit $40k with $20k capital, you need either 2.5x turns @ 40% margin OR 3.5x turns @ 30% margin. Either requires the consignment pivot + capital growth over 6 months.

Sheet Helper ROI
A1: 🏠 Start Here
A2: Quantifies the hiring decision. Change blue inputs; model recalculates.
A4: INPUTS — edit blue cells | E4: OUTPUTS
B5: Hours per week | C5: 10 | E5: Weekly cost ($) | F5: =C5*C6 -> 150
B6: Hourly rate ($) | C6: 15 | E6: Monthly cost ($) | F6: =F5*C10 -> 645
B7: Listings per hour (helper avg) | C7: 15 | E7: Weekly listings produced | F7: =C5*C7 -> 150
B8: Your avg net per direct-sale card ($) | C8: 4 | E8: Monthly listings | F8: =F7*C10 -> 645
B9: Sell-through rate (%) | C9: 0.6 | E9: Expected sales per month | F9: =F8*C9 -> 387
B10: Weeks per month | C10: 4.3 | E10: Expected net revenue / month ($) | F10: =F9*C8 -> 1548
B11: Ramp-up factor (month 1 only, %) | C11: 0.6 | E11: NET CONTRIBUTION / month (ongoing) | F11: =F10-F6 -> 903
E12: NET CONTRIBUTION / month (month 1) | F12: =(F10*C11)-F6 -> 283.8
E13: ROI multiple (ongoing) | F13: =IFERROR(F10/F6,"") -> 2.4
A15: DECISION RULE
A16: • If NET CONTRIBUTION (ongoing) > $1,500/mo → hire immediately. Your time is worth more than the wage.
A17: • If NET CONTRIBUTION < $500/mo → re-examine: are your listings/hour assumption or avg net too low?
A18: • Start at 10 hrs/wk with weekly QA. Scale to 15–20 hrs/wk once SOP is proven (Month 2+).
A19: • Budget separately for shipping/packing helper (3–4 hrs/wk) once listing throughput exceeds 150 cards/wk.

Sheet Path to $40k
A1: 🏠 Start Here
A2: Month-by-month projection with adjustable assumptions.
B4: Assumption | C4: Month 1 | D4: Month 2 | E4: Month 3 | F4: Month 4 | G4: Month 5 | H4: Month 6 | I4: Month 7 | J4: Month 8 | K4: Month 9
B5: Working capital (start of month, $) | C5: 20000 | D5: 22000 | E5: 25000 | F5: 29000 | G5: 33000 | H5: 37000 | I5: 41000 | J5: 45000 | K5: 48000
B6: Monthly turns | C6: 2 | D6: 2.2 | E6: 2.5 | F6: 2.8 | G6: 3 | H6: 3.2 | I6: 3.3 | J6: 3.4 | K6: 3.5
B7: Avg net margin % | C7: 0.3 | D7: 0.31 | E7: 0.32 | F7: 0.34 | G7: 0.36 | H7: 0.38 | I7: 0.39 | J7: 0.4 | K7: 0.4
B8: Projected monthly gross ($) | C8: =C5*C6 -> 40000 | D8: =D5*D6 -> 48400 | E8: =E5*E6 -> 62500 | F8: =F5*F6 -> 81200 | G8: =G5*G6 -> 99000 | H8: =H5*H6 -> 118400 | I8: =I5*I6 -> 135300 | J8: =J5*J6 -> 153000 | K8: =K5*K6 -> 168000
B9: Projected monthly NET ($) | C9: =C8*C7 -> 12000 | D9: =D8*D7 -> 15004 | E9: =E8*E7 -> 20000 | F9: =F8*F7 -> 27608 | G9: =G8*G7 -> 35640 | H9: =H8*H7 -> 44992 | I9: =I8*I7 -> 52767 | J9: =J8*J7 -> 61200 | K9: =K8*K7 -> 67200
B10: Gap to $40k target ($) | C10: =40000-C9 -> 28000 | D10: =40000-D9 -> 24996 | E10: =40000-E9 -> 20000 | F10: =40000-F9 -> 12392 | G10: =40000-G9 -> 4360 | H10: =40000-H9 -> -4992 | I10: =40000-I9 -> -12767 | J10: =40000-J9 -> -21200 | K10: =40000-K9 -> -27200
B11: % of $40k target achieved | C11: =C9/40000 -> 0.3 | D11: =D9/40000 -> 0.3751 | E11: =E9/40000 -> 0.5 | F11: =F9/40000 -> 0.6902 | G11: =G9/40000 -> 0.891 | H11: =H9/40000 -> 1.1248 | I11: =I9/40000 -> 1.319175 | J11: =J9/40000 -> 1.53 | K11: =K9/40000 -> 1.68
A13: Milestones (Month-End)
B14: Cards listed / week (helper + you) | C14: 200 | D14: 275 | E14: 350 | F14: 450 | G14: 525 | H14: 600 | I14: 700 | J14: 775 | K14: 850
B15: Cards consigned / week (all houses) | C15: 25 | D15: 35 | E15: 45 | F15: 55 | G15: 65 | H15: 75 | I15: 85 | J15: 95 | K15: 100
B16: Avg cost basis / card ($) | C16: 8 | D16: 10 | E16: 13 | F16: 16 | G16: 18 | H16: 20 | I16: 22 | J16: 24 | K16: 25
B17: % of gross from mid+premium tier | C17: 0.2 | D17: 0.26 | E17: 0.33 | F17: 0.4 | G17: 0.45 | H17: 0.5 | I17: 0.53 | J17: 0.56 | K17: 0.58
B19: HOW TO USE THIS MODEL
B20: • The three YELLOW-highlighted rows (working capital, turns, margin) drive the whole model. Adjust any of them to see impact.
B21: • Working capital grows via 60% net reinvestment — if you reinvest less, slow the row 5 progression.
B22: • If you're behind target in any month, the first lever to pull is TURNS (consignment-heavy). Margin takes longer to move.
B23: • Month 6-7 is the realistic earliest window to cross $40k/mo NET at this starting capital and with strict reinvestment.
B24: • If a capital injection happens (partner, loan, mentor buyout purchase), update row 5 and the whole model reflects it.

Sheet Stale Action — Market Comps
A1: 🏠 Start Here
A2: Research Date: May 3, 2026 | Goal: Clear aging inventory this week to make room for new arrivals | Bold = IMMEDIATE ACTION
A3: 🔴 DROP NOW | C3: 🟠 OVERPRICED | E3: 🟡 FAIR / STUCK | G3: 🟢 UNDERPRICED | I3: 🔵 CONSIGN DC87 | K3: ⚪ HOLD
A4: Card Description | B4: Listed $ | C4: Days Listed | D4: Comp Range (Sold) | E4: Market Verdict | F4: Status | G4: Fast-Sell Price | H4: Channel | I4: Action Priority | J4: Notes

Sheet PSA Fee Schedule
A1: PSA Grading Fee Schedule — 2025
A3: Tier | B3: Turnaround | C3: Fee ($) | D3: eBay Fee (13.25%) | E3: Notes
A4: Value Bulk | B4: ~75 days | C4: 32.99 | D4: =C4*0.1325 -> 4.371175 | E4: Non-membership
A5: Value Plus | B5: ~45 days | C5: 49.99 | D5: =C5*0.1325 -> 6.623675 | E5: Non-membership
A6: Value Max | B6: ~35 days | C6: 64.99 | D6: =C6*0.1325 -> 8.611175 | E6: Non-membership
A7: Regular | B7: ~25 days | C7: 79.99 | D7: =C7*0.1325 -> 10.598675 | E7: Non-membership
A8: Express | B8: ~15 days | C8: 149 | D8: =C8*0.1325 -> 19.7425 | E8: Non-membership
A9: Super Express | B9: ~7 days | C9: 299 | D9: =C9*0.1325 -> 39.6175 | E9: Non-membership
A10: Walk-Through | B10: ~7 days ($10k insured) | C10: 599 | D10: =C10*0.1325 -> 79.3675 | E10: Non-membership
A11: eBay final value fee: 13.25% of sale price

Sheet Grading ROI Calculator
A1: Grading ROI Calculator
A2: INPUTS
A4: Raw Buy Price ($) | B4: 50
A5: PSA Tier | B5: Value Bulk
A6: PSA Fee ($) | B6: 32.99 | C6: Enter fee from "PSA Fee Schedule" tab
A7: Gem Rate (%) | B7: 50
A8: PSA 10 Avg Price ($) | B8: 0
A9: ROI Target (×) | B9: 4
A11: OUTPUTS
A12: eBay Fee ($) | B12: =B8*0.1325 -> 0
A13: Target PSA 10 Price ($) | B13: =(B4*B9+B6)/(1-0.1325) -> 268.57637
A14: Est. Net Profit ($) | B14: =B8*(1-0.1325)-B6-B4 -> -82.99
A15: Est. ROI (%) | B15: =IF(B4>0,(B14/B4)*100,0) -> -165.98
A16: GO / NO-GO | B16: =IF(B7<40,"❌ NO-GO — Gem rate below 40% floor",IF(B8>=B13,"✅ GO — Clears target price","❌ NO-GO — Price below target")) -> ❌ NO-GO — Price below target
A18: 4× ROI formula: (Raw Cost × ROI Target + PSA Fee) ÷ (1 − 0.1325)

Sheet Grading Tracker
A1: Grading Tracker — PSA Submission Log
A2: Date Added | B2: Card Description | C2: Year | D2: Set | E2: Parallel | F2: Raw Buy ($) | G2: PSA Tier | H2: PSA Fee ($) | I2: PSA 10 Avg ($) | J2: Target Price ($) | K2: Gem Rate (%) | L2: GO/NO-GO | M2: Est. Net ($) | N2: Est. ROI | O2: Date Submitted | P2: Status | Q2: Grade Returned | R2: Actual Sell ($) | S2: Actual Net ($) | T2: Actual ROI | U2: Notes
A3: 46113 | B3: 2024 Panini Prizm Patrick Mahomes RC Base #168 | C3: 2024 | D3: Panini Prizm | E3: Base Silver | F3: 18 | G3: Value Bulk | H3: 32.99 | I3: 120 | J3: =(F3+G3*H3)/(1-0.1325) -> #VALUE! | K3: 55 | L3: =IF(E3<40,"❌ NO-GO",IF(I3>=J3,"✅ GO","❌ NO-GO")) -> #VALUE! | M3: =I3*(1-0.1325)-H3-F3 -> 53.11 | N3: =IF(F3>0,(M3/F3)*100,0) -> 295.05556 | P3: Queued
A4: 46117 | B4: 2023 Topps Chrome Corbin Carroll RC Auto #CPA-CC | C4: 2023 | D4: Bowman Chrome | E4: RC Auto | F4: 22 | G4: Value Bulk | H4: 32.99 | I4: 95 | J4: =(F4+G4*H4)/(1-0.1325) -> #VALUE! | K4: 48 | L4: =IF(E4<40,"❌ NO-GO",IF(I4>=J4,"✅ GO","❌ NO-GO")) -> #VALUE! | M4: =I4*(1-0.1325)-H4-F4 -> 27.4225 | N4: =IF(F4>0,(M4/F4)*100,0) -> 124.64773 | P4: Queued
A5: 46122 | B5: 2021 Panini Prizm LeBron James #129 Silver | C5: 2021 | D5: Panini Prizm | E5: Silver | F5: 25 | G5: Value Plus | H5: 49.99 | I5: 200 | J5: =(F5+G5*H5)/(1-0.1325) -> #VALUE! | K5: 62 | L5: =IF(E5<40,"❌ NO-GO",IF(I5>=J5,"✅ GO","❌ NO-GO")) -> #VALUE! | M5: =I5*(1-0.1325)-H5-F5 -> 98.51 | N5: =IF(F5>0,(M5/F5)*100,0) -> 394.04 | P5: Queued
A53: SUMMARY
A54: Total Cards: | B54: =COUNTA(A3:A51) -> 3
A55: Total Invested ($): | B55: =SUM(F3:F51) -> 65
A56: Total Est. Net ($): | B56: =SUM(M3:M51) -> 179.0425
A57: Total Actual Net ($): | B57: =SUM(S3:S51) -> 0
A58: GO Decisions: | B58: =COUNTIF(L3:L51,"*GO*")-COUNTIF(L3:L51,"*NO-GO*") -> 0

Sheet Grading Candidates
A1: Grading Candidates — PSA Submission Shortlist
A2: Populate from the Inventory & Aging tab — cards you are considering submitting to PSA
A3: Rank | B3: Card Description | C3: Category | D3: Cost Basis ($) | E3: Gem Rate (%) | F3: Gem Signal | G3: PSA Tier | H3: Target Price ($) | I3: PSA 10 Est. ($) | J3: Est. Net ($) | K3: Est. ROI (%) | L3: Decision | M3: Notes
F4: 🟢 ≥60% | 🟡 40-59% | 🔴 <40% | L4: GO, NO-GO, HOLD, RESEARCH
